Workbook

Sheet TABLEAU DE BORD
B2: TABLEAU DE BORD - SUIVI DES APPRENANTS
B3: APPRENANTS est la table maitre : WEDOF - EXAMEN FINAL, PAIEMENTS & COMMISSIONS et AUTOMATISATION se remplissent automatiquement a partir d'elle (meme ordre de lignes).
B6: INDICATEURS CLES
B7: Total apprenants suivis | D7: =COUNTIF(APPRENANTS!$B$2:$B$153,"?*") -> 152
B8: Dossiers avec documents en attente | D8: =COUNTIF(APPRENANTS!$U$2:$U$153,"?*") -> 152
B9: Dossiers a relancer (J+1 fin formation) | D9: =COUNTIF(APPRENANTS!$W$2:$W$153,"?*") -> 106
B10: Doublons Organisme a verifier | D10: =COUNTIF(APPRENANTS!$X$2:$X$153,"?*") -> 0
B11: Dossiers examen Wedof en attente | D11: =COUNTIF('WEDOF - EXAMEN FINAL'!$M$2:$M$153,"?*") -> 143
B12: Commissions en retard de versement | D12: =COUNTIF('PAIEMENTS & COMMISSIONS'!$L$2:$L$153,"En retard - a verser") -> 57
B13: CA total previsionnel (dossiers confirmes uniquement) | D13: =SUM('PAIEMENTS & COMMISSIONS'!$O$2:$O$153) -> 216000
B14: Commission totale due aux apporteurs (dossiers confirmes uniquement) | D14: =SUM('PAIEMENTS & COMMISSIONS'!$P$2:$P$153) -> 109875
B15: Dossiers prets pour generation (classique) | D15: =COUNTIF(AUTOMATISATION!$T$13:$T$164,TRUE()) -> 139
B16: Dossiers prets pour generation (wedof) | D16: =COUNTIF(AUTOMATISATION!$U$13:$U$164,TRUE()) -> 19
B17: Dossiers avec inscription NON confirmee/payee | D17: =COUNTIF(APPRENANTS!$Y$2:$Y$153,"Non") -> 8
B19: SUIVI COMPLET PAR APPRENANT
B20: Organisme | C20: Nom | D20: Apporteur | E20: Missions documents a faire | F20: % Avancement | G20: Missions examen Wedof a faire | H20: Alerte relance | I20: Alerte doublon | J20: Statut commission | K20: Inscription confirmee
B21: =APPRENANTS!A2 -> Proforma Institut | C21: =APPRENANTS!B2 -> Mohamed Ait Baha | D21: =APPRENANTS!C2 -> Djody | E21: =APPRENANTS!U2 -> Analyse du besoin, CV | F21: =APPRENANTS!V2 -> 0.77777778 | G21: ='WEDOF - EXAMEN FINAL'!M2 -> CV, CIN, 6 dossiers admin | H21: =APPRENANTS!W2 -> A RELANCER : Analyse du besoin, CV | I21: =APPRENANTS!X2 | J21: ='PAIEMENTS & COMMISSIONS'!L2 -> En retard - a verser | K21: =APPRENANTS!Y2 -> Oui
B22: =APPRENANTS!A3 -> Proforma Institut | C22: =APPRENANTS!B3 -> Frederic Roche | D22: =APPRENANTS!C3 -> Nedjma | E22: =APPRENANTS!U3 -> Analyse du besoin | F22: =APPRENANTS!V3 -> 0.88888889 | G22: ='WEDOF - EXAMEN FINAL'!M3 -> CIN | H22: =APPRENANTS!W3 -> A RELANCER : Analyse du besoin | I22: =APPRENANTS!X3 | J22: ='PAIEMENTS & COMMISSIONS'!L3 -> En retard - a verser | K22: =APPRENANTS!Y3 -> Oui
B23: =APPRENANTS!A4 -> Proforma Institut | C23: =APPRENANTS!B4 -> SIAF Kamla | D23: =APPRENANTS!C4 -> Nedjma | E23: =APPRENANTS!U4 -> Analyse du besoin, CV | F23: =APPRENANTS!V4 -> 0.77777778 | G23: ='WEDOF - EXAMEN FINAL'!M4 -> CV, CIN, 6 dossiers admin | H23: =APPRENANTS!W4 -> A RELANCER : Analyse du besoin, CV | I23: =APPRENANTS!X4 | J23: ='PAIEMENTS & COMMISSIONS'!L4 -> En retard - a verser | K23: =APPRENANTS!Y4 -> Oui
B24: =APPRENANTS!A5 -> Proforma Institut | C24: =APPRENANTS!B5 -> HAFIDHOU Mansouri | D24: =APPRENANTS!C5 -> Nedjma | E24: =APPRENANTS!U5 -> Analyse du besoin | F24: =APPRENANTS!V5 -> 0.88888889 | G24: ='WEDOF - EXAMEN FINAL'!M5 | H24: =APPRENANTS!W5 -> A RELANCER : Analyse du besoin | I24: =APPRENANTS!X5 | J24: ='PAIEMENTS & COMMISSIONS'!L5 -> En retard - a verser | K24: =APPRENANTS!Y5 -> Oui
B25: =APPRENANTS!A6 -> Proforma Institut | C25: =APPRENANTS!B6 -> DELGADO DA CRUZ Francisco | D25: =APPRENANTS!C6 -> Nedjma | E25: =APPRENANTS!U6 -> Analyse du besoin | F25: =APPRENANTS!V6 -> 0.88888889 | G25: ='WEDOF - EXAMEN FINAL'!M6 | H25: =APPRENANTS!W6 -> A RELANCER : Analyse du besoin | I25: =APPRENANTS!X6 | J25: ='PAIEMENTS & COMMISSIONS'!L6 -> En retard - a verser | K25: =APPRENANTS!Y6 -> Oui
B26: =APPRENANTS!A7 -> Proforma Institut | C26: =APPRENANTS!B7 -> DOUMENC Christophe | D26: =APPRENANTS!C7 -> Nedjma | E26: =APPRENANTS!U7 -> Analyse du besoin | F26: =APPRENANTS!V7 -> 0.88888889 | G26: ='WEDOF - EXAMEN FINAL'!M7 | H26: =APPRENANTS!W7 -> A RELANCER : Analyse du besoin | I26: =APPRENANTS!X7 | J26: ='PAIEMENTS & COMMISSIONS'!L7 -> En retard - a verser | K26: =APPRENANTS!Y7 -> Oui
B27: =APPRENANTS!A8 -> Proforma Institut | C27: =APPRENANTS!B8 -> AHAMADA BOURHANE Soilihi | D27: =APPRENANTS!C8 -> Nedjma | E27: =APPRENANTS!U8 -> Analyse du besoin, Document de fin | F27: =APPRENANTS!V8 -> 0.77777778 | G27: ='WEDOF - EXAMEN FINAL'!M8 | H27: =APPRENANTS!W8 -> A RELANCER : Analyse du besoin, Document de fin | I27: =APPRENANTS!X8 | J27: ='PAIEMENTS & COMMISSIONS'!L8 -> En retard - a verser | K27: =APPRENANTS!Y8 -> Oui
B28: =APPRENANTS!A9 -> Proforma Institut | C28: =APPRENANTS!B9 -> BENGUEDIH Kader | D28: =APPRENANTS!C9 -> Nedjma | E28: =APPRENANTS!U9 -> Analyse du besoin, Document de fin | F28: =APPRENANTS!V9 -> 0.77777778 | G28: ='WEDOF - EXAMEN FINAL'!M9 -> CIN | H28: =APPRENANTS!W9 -> A RELANCER : Analyse du besoin, Document de fin | I28: =APPRENANTS!X9 | J28: ='PAIEMENTS & COMMISSIONS'!L9 -> En retard - a verser | K28: =APPRENANTS!Y9 -> Oui
B29: =APPRENANTS!A10 -> Proforma Institut | C29: =APPRENANTS!B10 -> Julie Scotto D Aniello | D29: =APPRENANTS!C10 -> Sabri | E29: =APPRENANTS!U10 -> Analyse du besoin | F29: =APPRENANTS!V10 -> 0.88888889 | G29: ='WEDOF - EXAMEN FINAL'!M10 | H29: =APPRENANTS!W10 -> A RELANCER : Analyse du besoin | I29: =APPRENANTS!X10 | J29: ='PAIEMENTS & COMMISSIONS'!L10 -> En retard - a verser | K29: =APPRENANTS!Y10 -> Oui
B30: =APPRENANTS!A11 -> Proforma Institut | C30: =APPRENANTS!B11 -> Malik Benameur | D30: =APPRENANTS!C11 -> Sabri | E30: =APPRENANTS!U11 -> Analyse du besoin | F30: =APPRENANTS!V11 -> 0.88888889 | G30: ='WEDOF - EXAMEN FINAL'!M11 | H30: =APPRENANTS!W11 -> A RELANCER : Analyse du besoin | I30: =APPRENANTS!X11 | J30: ='PAIEMENTS & COMMISSIONS'!L11 -> En retard - a verser | K30: =APPRENANTS!Y11 -> Oui
B31: =APPRENANTS!A12 -> Proforma Institut | C31: =APPRENANTS!B12 -> LEROY Aurelie | D31: =APPRENANTS!C12 -> Sabri | E31: =APPRENANTS!U12 -> Analyse du besoin | F31: =APPRENANTS!V12 -> 0.88888889 | G31: ='WEDOF - EXAMEN FINAL'!M12 | H31: =APPRENANTS!W12 -> A RELANCER : Analyse du besoin | I31: =APPRENANTS!X12 | J31: ='PAIEMENTS & COMMISSIONS'!L12 -> En retard - a verser | K31: =APPRENANTS!Y12 -> Oui
B32: =APPRENANTS!A13 -> Proforma Institut | C32: =APPRENANTS!B13 -> SANIGOU Livan | D32: =APPRENANTS!C13 -> Sabri | E32: =APPRENANTS!U13 -> Analyse du besoin | F32: =APPRENANTS!V13 -> 0.88888889 | G32: ='WEDOF - EXAMEN FINAL'!M13 | H32: =APPRENANTS!W13 -> A RELANCER : Analyse du besoin | I32: =APPRENANTS!X13 | J32: ='PAIEMENTS & COMMISSIONS'!L13 -> En retard - a verser | K32: =APPRENANTS!Y13 -> Oui
... B172: =APPRENANTS!A153 -> Proskills Institut | C172: =APPRENANTS!B153 -> BOGGIO Andre | D172: =APPRENANTS!C153 -> Sabri | E172: =APPRENANTS!U153 -> Analyse du besoin, CV, Questionnaire/Test, Contrat, Convocation, Eval intermediaire, Eval finale, Questionnaire satisfaction, Document de fin | F172: =APPRENANTS!V153 -> 0 | G172: ='WEDOF - EXAMEN FINAL'!M153 -> CV, CIN, 6 dossiers admin, Convocation examen | H172: =APPRENANTS!W153 | I172: =APPRENANTS!X153 | J172: ='PAIEMENTS & COMMISSIONS'!L153 -> Inscription non confirmee | K172: =APPRENANTS!Y153 -> Non

Sheet APPRENANTS
A1: Organisme | B1: Nom | C1: Apporteur | D1: Formation | E1: Date debut session | F1: Date fin session | G1: Statut EDOF | H1: Adresse | I1: Email | J1: Telephone | K1: Date de naissance | L1: Analyse du besoin | M1: CV | N1: Questionnaire/Test | O1: Contrat | P1: Convocation | Q1: Eval intermediaire | R1: Eval finale | S1: Questionnaire satisfaction | T1: Document de fin | U1: Missions a faire | V1: % Avancement | W1: Alerte relance | X1: Alerte doublon | Y1: Inscription confirmee/payee (E)
A2: Proforma Institut | B2: Mohamed Ait Baha | C2: Djody | D2: Réaliser les opérations comptables courantes d'une TPE | E2: 2026-02-18 | F2: 2026-03-06 | G2: Payé | H2: 141 BD Maréchal Juin, 62110 HENIN BEAUMONT | I2: mohamed.aitbaha@hotmail.fr | J2: 782270615 | K2: 1982-09-04 | L2: A faire | M2: ='WEDOF - EXAMEN FINAL'!D2 -> A faire | N2: Fait | O2: Fait | P2: Fait | Q2: Fait | R2: Fait | S2: Fait | T2: Fait | U2: =TEXTJOIN(", ",TRUE(),IF($L2="A faire","Analyse du besoin",""),IF($M2="A faire","CV",""),IF($N2="A faire","Questionnaire/Test",""),IF($O2="A faire","Contrat",""),IF($P2="A faire","Convocation",""),IF($Q2="A faire","Eval intermediaire",""),IF($R2="A faire","Eval finale",""),IF($S2="A faire","Questionnaire satisfaction",""),IF($T2="A faire","Document de fin","")) -> Analyse du besoin, CV | V2: =COUNTIF(L2:T2,"Fait")/9 -> 0.77777778 | W2: =IF($F2="","",IF(AND(TODAY()>=(DATEVALUE($F2)+1),$U2<>""),"A RELANCER : "&$U2,"")) -> A RELANCER : Analyse du besoin, CV | X2: =IF(SUMPRODUCT(($B$2:$B$153=$B2)*($D$2:$D$153=$D2)*($E$2:$E$153=$E2)*($A$2:$A$153<>$A2))>0,"DOUBLON A VERIFIER","") | Y2: Oui
A3: Proforma Institut | B3: Frederic Roche | C3: Nedjma | D3: Réaliser les opérations comptables courantes d'une TPE | E3: 2026-02-18 | F3: 2026-03-06 | G3: Payé | H3: 10 AV Des mimosas, 13015 MARSEILLE | I3: fred_mars13@hotmail.fr | J3: 613637315 | K3: 18/02/1981 | L3: A faire | M3: ='WEDOF - EXAMEN FINAL'!D3 -> Fait | N3: Fait | O3: Fait | P3: Fait | Q3: Fait | R3: Fait | S3: Fait | T3: Fait | U3: =TEXTJOIN(", ",TRUE(),IF($L3="A faire","Analyse du besoin",""),IF($M3="A faire","CV",""),IF($N3="A faire","Questionnaire/Test",""),IF($O3="A faire","Contrat",""),IF($P3="A faire","Convocation",""),IF($Q3="A faire","Eval intermediaire",""),IF($R3="A faire","Eval finale",""),IF($S3="A faire","Questionnaire satisfaction",""),IF($T3="A faire","Document de fin","")) -> Analyse du besoin | V3: =COUNTIF(L3:T3,"Fait")/9 -> 0.88888889 | W3: =IF($F3="","",IF(AND(TODAY()>=(DATEVALUE($F3)+1),$U3<>""),"A RELANCER : "&$U3,"")) -> A RELANCER : Analyse du besoin | X3: =IF(SUMPRODUCT(($B$2:$B$153=$B3)*($D$2:$D$153=$D3)*($E$2:$E$153=$E3)*($A$2:$A$153<>$A3))>0,"DOUBLON A VERIFIER","") | Y3: Oui
A4: Proforma Institut | B4: SIAF Kamla | C4: Nedjma | D4: Réaliser les opérations comptables courantes d'une TPE | E4: 2026-03-09 | F4: 2026-03-27 | G4: Payé | H4: 171 AV du Merlan, 13014 MARSEILLE | I4: mimisiaf@gmail.com | J4: 629924780 | K4: 13/08/1965 | L4: A faire | M4: ='WEDOF - EXAMEN FINAL'!D4 -> A faire | N4: Fait | O4: Fait | P4: Fait | Q4: Fait | R4: Fait | S4: Fait | T4: Fait | U4: =TEXTJOIN(", ",TRUE(),IF($L4="A faire","Analyse du besoin",""),IF($M4="A faire","CV",""),IF($N4="A faire","Questionnaire/Test",""),IF($O4="A faire","Contrat",""),IF($P4="A faire","Convocation",""),IF($Q4="A faire","Eval intermediaire",""),IF($R4="A faire","Eval finale",""),IF($S4="A faire","Questionnaire satisfaction",""),IF($T4="A faire","Document de fin","")) -> Analyse du besoin, CV | V4: =COUNTIF(L4:T4,"Fait")/9 -> 0.77777778 | W4: =IF($F4="","",IF(AND(TODAY()>=(DATEVALUE($F4)+1),$U4<>""),"A RELANCER : "&$U4,"")) -> A RELANCER : Analyse du besoin, CV | X4: =IF(SUMPRODUCT(($B$2:$B$153=$B4)*($D$2:$D$153=$D4)*($E$2:$E$153=$E4)*($A$2:$A$153<>$A4))>0,"DOUBLON A VERIFIER","") | Y4: Oui
A5: Proforma Institut | B5: HAFIDHOU Mansouri | C5: Nedjma | D5: Réaliser les opérations comptables courantes d'une TPE | E5: 2026-03-09 | F5: 2026-03-27 | G5: Payé | H5: 178 AV Des chutes lavie, 13013 MARSEILLE | I5: mansourihafidou@gmail.com | J5: 763179407 | K5: 1990-07-05 | L5: A faire | M5: ='WEDOF - EXAMEN FINAL'!D5 -> Fait | N5: Fait | O5: Fait | P5: Fait | Q5: Fait | R5: Fait | S5: Fait | T5: Fait | U5: =TEXTJOIN(", ",TRUE(),IF($L5="A faire","Analyse du besoin",""),IF($M5="A faire","CV",""),IF($N5="A faire","Questionnaire/Test",""),IF($O5="A faire","Contrat",""),IF($P5="A faire","Convocation",""),IF($Q5="A faire","Eval intermediaire",""),IF($R5="A faire","Eval finale",""),IF($S5="A faire","Questionnaire satisfaction",""),IF($T5="A faire","Document de fin","")) -> Analyse du besoin | V5: =COUNTIF(L5:T5,"Fait")/9 -> 0.88888889 | W5: =IF($F5="","",IF(AND(TODAY()>=(DATEVALUE($F5)+1),$U5<>""),"A RELANCER : "&$U5,"")) -> A RELANCER : Analyse du besoin | X5: =IF(SUMPRODUCT(($B$2:$B$153=$B5)*($D$2:$D$153=$D5)*($E$2:$E$153=$E5)*($A$2:$A$153<>$A5))>0,"DOUBLON A VERIFIER","") | Y5: Oui
A6: Proforma Institut | B6: DELGADO DA CRUZ Francisco | C6: Nedjma | D6: Réaliser les opérations comptables courantes d'une TPE | E6: 2026-03-09 | F6: 2026-03-27 | G6: Payé | H6: 29 PTR Sainte victoire, 13006 MARSEILLE | I6: chicodelgado72@gmail.com | J6: 783823367 | K6: 1972-11-07 | L6: A faire | M6: ='WEDOF - EXAMEN FINAL'!D6 -> Fait | N6: Fait | O6: Fait | P6: Fait | Q6: Fait | R6: Fait | S6: Fait | T6: Fait | U6: =TEXTJOIN(", ",TRUE(),IF($L6="A faire","Analyse du besoin",""),IF($M6="A faire","CV",""),IF($N6="A faire","Questionnaire/Test",""),IF($O6="A faire","Contrat",""),IF($P6="A faire","Convocation",""),IF($Q6="A faire","Eval intermediaire",""),IF($R6="A faire","Eval finale",""),IF($S6="A faire","Questionnaire satisfaction",""),IF($T6="A faire","Document de fin","")) -> Analyse du besoin | V6: =COUNTIF(L6:T6,"Fait")/9 -> 0.88888889 | W6: =IF($F6="","",IF(AND(TODAY()>=(DATEVALUE($F6)+1),$U6<>""),"A RELANCER : "&$U6,"")) -> A RELANCER : Analyse du besoin | X6: =IF(SUMPRODUCT(($B$2:$B$153=$B6)*($D$2:$D$153=$D6)*($E$2:$E$153=$E6)*($A$2:$A$153<>$A6))>0,"DOUBLON A VERIFIER","") | Y6: Oui
A7: Proforma Institut | B7: DOUMENC Christophe | C7: Nedjma | D7: Réaliser les opérations comptables courantes d'une TPE | E7: 2026-03-09 | F7: 2026-03-27 | G7: Payé | H7: 16 RUE Nicolas copernic, 13013 MARSEILLE | I7: christophedoumenc13@gmail.com | J7: 681540974 | K7: 30/12/1972 | L7: A faire | M7: ='WEDOF - EXAMEN FINAL'!D7 -> Fait | N7: Fait | O7: Fait | P7: Fait | Q7: Fait | R7: Fait | S7: Fait | T7: Fait | U7: =TEXTJOIN(", ",TRUE(),IF($L7="A faire","Analyse du besoin",""),IF($M7="A faire","CV",""),IF($N7="A faire","Questionnaire/Test",""),IF($O7="A faire","Contrat",""),IF($P7="A faire","Convocation",""),IF($Q7="A faire","Eval intermediaire",""),IF($R7="A faire","Eval finale",""),IF($S7="A faire","Questionnaire satisfaction",""),IF($T7="A faire","Document de fin","")) -> Analyse du besoin | V7: =COUNTIF(L7:T7,"Fait")/9 -> 0.88888889 | W7: =IF($F7="","",IF(AND(TODAY()>=(DATEVALUE($F7)+1),$U7<>""),"A RELANCER : "&$U7,"")) -> A RELANCER : Analyse du besoin | X7: =IF(SUMPRODUCT(($B$2:$B$153=$B7)*($D$2:$D$153=$D7)*($E$2:$E$153=$E7)*($A$2:$A$153<>$A7))>0,"DOUBLON A VERIFIER","") | Y7: Oui
A8: Proforma Institut | B8: AHAMADA BOURHANE Soilihi | C8: Nedjma | D8: Réaliser les opérations comptables courantes d'une TPE | E8: 2026-03-30 | F8: 2026-04-17 | G8: FACTURE | H8: 257 AV Saint antoine, 13015 MARSEILLE | I8: ahamada.s@live.fr | J8: 652632912 | K8: 22/06/1991 | L8: A faire | M8: ='WEDOF - EXAMEN FINAL'!D8 -> Fait | N8: Fait | O8: Fait | P8: Fait | Q8: Fait | R8: Fait | S8: Fait | T8: A faire | U8: =TEXTJOIN(", ",TRUE(),IF($L8="A faire","Analyse du besoin",""),IF($M8="A faire","CV",""),IF($N8="A faire","Questionnaire/Test",""),IF($O8="A faire","Contrat",""),IF($P8="A faire","Convocation",""),IF($Q8="A faire","Eval intermediaire",""),IF($R8="A faire","Eval finale",""),IF($S8="A faire","Questionnaire satisfaction",""),IF($T8="A faire","Document de fin","")) -> Analyse du besoin, Document de fin | V8: =COUNTIF(L8:T8,"Fait")/9 -> 0.77777778 | W8: =IF($F8="","",IF(AND(TODAY()>=(DATEVALUE($F8)+1),$U8<>""),"A RELANCER : "&$U8,"")) -> A RELANCER : Analyse du besoin, Document de fin | X8: =IF(SUMPRODUCT(($B$2:$B$153=$B8)*($D$2:$D$153=$D8)*($E$2:$E$153=$E8)*($A$2:$A$153<>$A8))>0,"DOUBLON A VERIFIER","") | Y8: Oui
A9: Proforma Institut | B9: BENGUEDIH Kader | C9: Nedjma | D9: Réaliser les opérations comptables courantes d'une TPE | E9: 2026-03-30 | F9: 2026-04-17 | G9: FACTURE | H9: 130 CHE Château gombert, 13013 MARSEILLE | I9: Benguedihk@yahoo.fr | J9: 617440902 | K9: 19/08/1987 | L9: A faire | M9: ='WEDOF - EXAMEN FINAL'!D9 -> Fait | N9: Fait | O9: Fait | P9: Fait | Q9: Fait | R9: Fait | S9: Fait | T9: A faire | U9: =TEXTJOIN(", ",TRUE(),IF($L9="A faire","Analyse du besoin",""),IF($M9="A faire","CV",""),IF($N9="A faire","Questionnaire/Test",""),IF($O9="A faire","Contrat",""),IF($P9="A faire","Convocation",""),IF($Q9="A faire","Eval intermediaire",""),IF($R9="A faire","Eval finale",""),IF($S9="A faire","Questionnaire satisfaction",""),IF($T9="A faire","Document de fin","")) -> Analyse du besoin, Document de fin | V9: =COUNTIF(L9:T9,"Fait")/9 -> 0.77777778 | W9: =IF($F9="","",IF(AND(TODAY()>=(DATEVALUE($F9)+1),$U9<>""),"A RELANCER : "&$U9,"")) -> A RELANCER : Analyse du besoin, Document de fin | X9: =IF(SUMPRODUCT(($B$2:$B$153=$B9)*($D$2:$D$153=$D9)*($E$2:$E$153=$E9)*($A$2:$A$153<>$A9))>0,"DOUBLON A VERIFIER","") | Y9: Oui
A10: Proforma Institut | B10: Julie Scotto D Aniello | C10: Sabri | D10: Réaliser les opérations comptables courantes d'une TPE | E10: 2026-02-18 | F10: 2026-03-04 | G10: Payé | H10: 23 BD Boulevard Georges Clemenceau, 13700 MARIGNANE | I10: 13julie@free.fr | J10: 643092268 | K10: 1994-05-09 | L10: A faire | M10: ='WEDOF - EXAMEN FINAL'!D10 -> Fait | N10: Fait | O10: Fait | P10: Fait | Q10: Fait | R10: Fait | S10: Fait | T10: Fait | U10: =TEXTJOIN(", ",TRUE(),IF($L10="A faire","Analyse du besoin",""),IF($M10="A faire","CV",""),IF($N10="A faire","Questionnaire/Test",""),IF($O10="A faire","Contrat",""),IF($P10="A faire","Convocation",""),IF($Q10="A faire","Eval intermediaire",""),IF($R10="A faire","Eval finale",""),IF($S10="A faire","Questionnaire satisfaction",""),IF($T10="A faire","Document de fin","")) -> Analyse du besoin | V10: =COUNTIF(L10:T10,"Fait")/9 -> 0.88888889 | W10: =IF($F10="","",IF(AND(TODAY()>=(DATEVALUE($F10)+1),$U10<>""),"A RELANCER : "&$U10,"")) -> A RELANCER : Analyse du besoin | X10: =IF(SUMPRODUCT(($B$2:$B$153=$B10)*($D$2:$D$153=$D10)*($E$2:$E$153=$E10)*($A$2:$A$153<>$A10))>0,"DOUBLON A VERIFIER","") | Y10: Oui
A11: Proforma Institut | B11: Malik Benameur | C11: Sabri | D11: Réaliser les opérations comptables courantes d'une TPE | E11: 2026-02-20 | F11: 2026-03-11 | G11: Payé | H11: 12 RUE Pour la paix, 13120 GARDANNE | I11: Malik13950@gmail.com | J11: 608544404 | K11: 24/06/1994 | L11: A faire | M11: ='WEDOF - EXAMEN FINAL'!D11 -> Fait | N11: Fait | O11: Fait | P11: Fait | Q11: Fait | R11: Fait | S11: Fait | T11: Fait | U11: =TEXTJOIN(", ",TRUE(),IF($L11="A faire","Analyse du besoin",""),IF($M11="A faire","CV",""),IF($N11="A faire","Questionnaire/Test",""),IF($O11="A faire","Contrat",""),IF($P11="A faire","Convocation",""),IF($Q11="A faire","Eval intermediaire",""),IF($R11="A faire","Eval finale",""),IF($S11="A faire","Questionnaire satisfaction",""),IF($T11="A faire","Document de fin","")) -> Analyse du besoin | V11: =COUNTIF(L11:T11,"Fait")/9 -> 0.88888889 | W11: =IF($F11="","",IF(AND(TODAY()>=(DATEVALUE($F11)+1),$U11<>""),"A RELANCER : "&$U11,"")) -> A RELANCER : Analyse du besoin | X11: =IF(SUMPRODUCT(($B$2:$B$153=$B11)*($D$2:$D$153=$D11)*($E$2:$E$153=$E11)*($A$2:$A$153<>$A11))>0,"DOUBLON A VERIFIER","") | Y11: Oui
A12: Proforma Institut | B12: LEROY Aurelie | C12: Sabri | D12: Réaliser les opérations comptables courantes d'une TPE | E12: 2026-03-09 | F12: 2026-03-27 | G12: Payé | H12: 335 CHE Chemin des romarins, 13820 ENSUES LA REDONNE | I12: aurelie542@hotmail.fr | J12: 631344712 | K12: 1986-04-07 | L12: A faire | M12: ='WEDOF - EXAMEN FINAL'!D12 -> Fait | N12: Fait | O12: Fait | P12: Fait | Q12: Fait | R12: Fait | S12: Fait | T12: Fait | U12: =TEXTJOIN(", ",TRUE(),IF($L12="A faire","Analyse du besoin",""),IF($M12="A faire","CV",""),IF($N12="A faire","Questionnaire/Test",""),IF($O12="A faire","Contrat",""),IF($P12="A faire","Convocation",""),IF($Q12="A faire","Eval intermediaire",""),IF($R12="A faire","Eval finale",""),IF($S12="A faire","Questionnaire satisfaction",""),IF($T12="A faire","Document de fin","")) -> Analyse du besoin | V12: =COUNTIF(L12:T12,"Fait")/9 -> 0.88888889 | W12: =IF($F12="","",IF(AND(TODAY()>=(DATEVALUE($F12)+1),$U12<>""),"A RELANCER : "&$U12,"")) -> A RELANCER : Analyse du besoin | X12: =IF(SUMPRODUCT(($B$2:$B$153=$B12)*($D$2:$D$153=$D12)*($E$2:$E$153=$E12)*($A$2:$A$153<>$A12))>0,"DOUBLON A VERIFIER","") | Y12: Oui
A13: Proforma Institut | B13: SANIGOU Livan | C13: Sabri | D13: Réaliser les opérations comptables courantes d'une TPE | E13: 2026-03-09 | F13: 2026-03-27 | G13: Payé | H13: 1 IMP Du stade, 13080 AIX EN PROVENCE | I13: livansanigou@yahoo.fr | J13: 775959572 | K13: 19/10/1983 | L13: A faire | M13: ='WEDOF - EXAMEN FINAL'!D13 -> Fait | N13: Fait | O13: Fait | P13: Fait | Q13: Fait | R13: Fait | S13: Fait | T13: Fait | U13: =TEXTJOIN(", ",TRUE(),IF($L13="A faire","Analyse du besoin",""),IF($M13="A faire","CV",""),IF($N13="A faire","Questionnaire/Test",""),IF($O13="A faire","Contrat",""),IF($P13="A faire","Convocation",""),IF($Q13="A faire","Eval intermediaire",""),IF($R13="A faire","Eval finale",""),IF($S13="A faire","Questionnaire satisfaction",""),IF($T13="A faire","Document de fin","")) -> Analyse du besoin | V13: =COUNTIF(L13:T13,"Fait")/9 -> 0.88888889 | W13: =IF($F13="","",IF(AND(TODAY()>=(DATEVALUE($F13)+1),$U13<>""),"A RELANCER : "&$U13,"")) -> A RELANCER : Analyse du besoin | X13: =IF(SUMPRODUCT(($B$2:$B$153=$B13)*($D$2:$D$153=$D13)*($E$2:$E$153=$E13)*($A$2:$A$153<>$A13))>0,"DOUBLON A VERIFIER","") | Y13: Oui
... A29: Proforma Institut | B29: Alexandre Schmerber | C29: Sabri | D29: Développer son activité avec l’intelligence artificielle | E29: 2026-05-18 | F29: 2026-05-29 | G29: Payé | H29: 24 MTE De le belle france, 13015 MARSEILLE | I29: alexandre.schmerber@hotmail.com | J29: 699574950 | K29: 24/05/1993 | L29: A faire | M29: ='WEDOF - EXAMEN FINAL'!D29 -> A faire | N29: Fait | O29: A faire | P29: A faire | Q29: Fait | R29: Fait | S29: Fait | T29: A faire | U29: =TEXTJOIN(", ",TRUE(),IF($L29="A faire","Analyse du besoin",""),IF($M29="A faire","CV",""),IF($N29="A faire","Questionnaire/Test",""),IF($O29="A faire","Contrat",""),IF($P29="A faire","Convocation",""),IF($Q29="A faire","Eval intermediaire",""),IF($R29="A faire","Eval finale",""),IF($S29="A faire","Questionnaire satisfaction",""),IF($T29="A faire","Document de fin","")) -> Analyse du besoin, CV, Contrat, Convocation, Document de fin | V29: =COUNTIF(L29:T29,"Fait")/9 -> 0.44444444 | W29: =IF($F29="","",IF(AND(TODAY()>=(DATEVALUE($F29)+1),$U29<>""),"A RELANCER : "&$U29,"")) -> A RELANCER : Analyse du besoin, CV, Contrat, Convocation, Document de fin | X29: =IF(SUMPRODUCT(($B$2:$B$153=$B29)*($D$2:$D$153=$D29)*($E$2:$E$153=$E29)*($A$2:$A$153<>$A29))>0,"DOUBLON A VERIFIER","") | Y29: Oui
A30: Proforma Institut | B30: CHAFIL Amine | D30: Développer son activité avec l’intelligence artificielle | E30: 2026-06-08 | F30: 2026-06-13 | G30: Accepté | H30: 23 RUE Professeur marcel Arnaud, 13013 MARSEILLE | I30: amine_du_13010@hotmail.fr | J30: 624685745 | K30: 1990-11-07 | L30: A faire | M30: ='WEDOF - EXAMEN FINAL'!D30 -> A faire | N30: Fait | O30: A faire | P30: A faire | Q30: Fait | R30: Fait | S30: Fait | T30: A faire | U30: =TEXTJOIN(", ",TRUE(),IF($L30="A faire","Analyse du besoin",""),IF($M30="A faire","CV",""),IF($N30="A faire","Questionnaire/Test",""),IF($O30="A faire","Contrat",""),IF($P30="A faire","Convocation",""),IF($Q30="A faire","Eval intermediaire",""),IF($R30="A faire","Eval finale",""),IF($S30="A faire","Questionnaire satisfaction",""),IF($T30="A faire","Document de fin","")) -> Analyse du besoin, CV, Contrat, Convocation, Document de fin | V30: =COUNTIF(L30:T30,"Fait")/9 -> 0.44444444 | W30: =IF($F30="","",IF(AND(TODAY()>=(DATEVALUE($F30)+1),$U30<>""),"A RELANCER : "&$U30,"")) -> A RELANCER : Analyse du besoin, CV, Contrat, Convocation, Document de fin | X30: =IF(SUMPRODUCT(($B$2:$B$153=$B30)*($D$2:$D$153=$D30)*($E$2:$E$153=$E30)*($A$2:$A$153<>$A30))>0,"DOUBLON A VERIFIER","") | Y30: Oui
A31: Proforma Institut | B31: MARIOTTI Regis | C31: Sabri | D31: Développer son activité avec l’intelligence artificielle | E31: 2026-06-08 | F31: 2026-06-13 | G31: Accepté | H31: 11 TRA de la dominique, 13011 MARSEILLE | I31: regismariotti@hotmail.fr | J31: 612877388 | K31: 27/08/1977 | L31: A faire | M31: ='WEDOF - EXAMEN FINAL'!D31 -> A faire | N31: Fait | O31: A faire | P31: A faire | Q31: Fait | R31: Fait | S31: Fait | T31: A faire | U31: =TEXTJOIN(", ",TRUE(),IF($L31="A faire","Analyse du besoin",""),IF($M31="A faire","CV",""),IF($N31="A faire","Questionnaire/Test",""),IF($O31="A faire","Contrat",""),IF($P31="A faire","Convocation",""),IF($Q31="A faire","Eval intermediaire",""),IF($R31="A faire","Eval finale",""),IF($S31="A faire","Questionnaire satisfaction",""),IF($T31="A faire","Document de fin","")) -> Analyse du besoin, CV, Contrat, Convocation, Document de fin | V31: =COUNTIF(L31:T31,"Fait")/9 -> 0.44444444 | W31: =IF($F31="","",IF(AND(TODAY()>=(DATEVALUE($F31)+1),$U31<>""),"A RELANCER : "&$U31,"")) -> A RELANCER : Analyse du besoin, CV, Contrat, Convocation, Document de fin | X31: =IF(SUMPRODUCT(($B$2:$B$153=$B31)*($D$2:$D$153=$D31)*($E$2:$E$153=$E31)*($A$2:$A$153<>$A31))>0,"DOUBLON A VERIFIER","") | Y31: Oui
A32: Proforma Institut | B32: GAUTHEROT Pascal | C32: GRAS | D32: Améliorer l'efficacité de sa TPE à l'aide de l'IA | E32: 2026-06-15 | F32: 2026-06-20 | G32: Accepté | H32: 192 CHE du tour de l'étang, 13800 ISTRES | I32: pascal-gautherot@wanadoo.fr | J32: 689407179 | K32: 22/04/1966 | L32: A faire | M32: ='WEDOF - EXAMEN FINAL'!D32 -> A faire | N32: A faire | O32: A faire | P32: A faire | Q32: A faire | R32: A faire | S32: A faire | T32: A faire | U32: =TEXTJOIN(", ",TRUE(),IF($L32="A faire","Analyse du besoin",""),IF($M32="A faire","CV",""),IF($N32="A faire","Questionnaire/Test",""),IF($O32="A faire","Contrat",""),IF($P32="A faire","Convocation",""),IF($Q32="A faire","Eval intermediaire",""),IF($R32="A faire","Eval finale",""),IF($S32="A faire","Questionnaire satisfaction",""),IF($T32="A faire","Document de fin","")) -> Analyse du besoin, CV, Questionnaire/Test, Contrat, Convocation, Eval intermediaire, Eval finale, Questionnaire satisfaction, Document de fin | V32: =COUNTIF(L32:T32,"Fait")/9 -> 0 | W32: =IF($F32="","",IF(AND(TODAY()>=(DATEVALUE($F32)+1),$U32<>""),"A RELANCER : "&$U32,"")) -> A RELANCER : Analyse du besoin, CV, Questionnaire/Test, Contrat, Convocation, Eval intermediaire, Eval finale, Questionnaire satisfaction, Document de fin | X32: =IF(SUMPRODUCT(($B$2:$B$153=$B32)*($D$2:$D$153=$D32)*($E$2:$E$153=$E32)*($A$2:$A$153<>$A32))>0,"DOUBLON A VERIFIER","") | Y32: Oui
A33: Proforma Institut | B33: GAUTHEROT Pascal | C33: GRAS | D33: Communiquer sur les réseaux sociaux pour promouvoir sa TPE | E33: 2026-06-22 | F33: 2026-06-27 | G33: Accepté | H33: 192 CHE du tour de l'étang, 13800 ISTRES | I33: pascal-gautherot@wanadoo.fr | J33: 689407179 | K33: 22/04/1966 | L33: A faire | M33: ='WEDOF - EXAMEN FINAL'!D33 -> A faire | N33: A faire | O33: A faire | P33: A faire | Q33: A faire | R33: A faire | S33: A faire | T33: A faire | U33: =TEXTJOIN(", ",TRUE(),IF($L33="A faire","Analyse du besoin",""),IF($M33="A faire","CV",""),IF($N33="A faire","Questionnaire/Test",""),IF($O33="A faire","Contrat",""),IF($P33="A faire","Convocation",""),IF($Q33="A faire","Eval intermediaire",""),IF($R33="A faire","Eval finale",""),IF($S33="A faire","Questionnaire satisfaction",""),IF($T33="A faire","Document de fin","")) -> Analyse du besoin, CV, Questionnaire/Test, Contrat, Convocation, Eval intermediaire, Eval finale, Questionnaire satisfaction, Document de fin | V33: =COUNTIF(L33:T33,"Fait")/9 -> 0 | W33: =IF($F33="","",IF(AND(TODAY()>=(DATEVALUE($F33)+1),$U33<>""),"A RELANCER : "&$U33,"")) -> A RELANCER : Analyse du besoin, CV, Questionnaire/Test, Contrat, Convocation, Eval intermediaire, Eval finale, Questionnaire satisfaction, Document de fin | X33: =IF(SUMPRODUCT(($B$2:$B$153=$B33)*($D$2:$D$153=$D33)*($E$2:$E$153=$E33)*($A$2:$A$153<>$A33))>0,"DOUBLON A VERIFIER","") | Y33: Oui
A34: Proforma Institut | B34: GAUTHEROT Pascal | C34: GRAS | D34: Réaliser les opérations comptables courantes d'une TPE | E34: 2026-06-29 | F34: 2026-07-04 | G34: Accepté | H34: 192 CHE du tour de l'étang, 13800 ISTRES | I34: pascal-gautherot@wanadoo.fr | J34: 689407179 | K34: 22/04/1966 | L34: A faire | M34: ='WEDOF - EXAMEN FINAL'!D34 -> A faire | N34: A faire | O34: A faire | P34: A faire | Q34: A faire | R34: A faire | S34: A faire | T34: A faire | U34: =TEXTJOIN(", ",TRUE(),IF($L34="A faire","Analyse du besoin",""),IF($M34="A faire","CV",""),IF($N34="A faire","Questionnaire/Test",""),IF($O34="A faire","Contrat",""),IF($P34="A faire","Convocation",""),IF($Q34="A faire","Eval intermediaire",""),IF($R34="A faire","Eval finale",""),IF($S34="A faire","Questionnaire satisfaction",""),IF($T34="A faire","Document de fin","")) -> Analyse du besoin, CV, Questionnaire/Test, Contrat, Convocation, Eval intermediaire, Eval finale, Questionnaire satisfaction, Document de fin | V34: =COUNTIF(L34:T34,"Fait")/9 -> 0 | W34: =IF($F34="","",IF(AND(TODAY()>=(DATEVALUE($F34)+1),$U34<>""),"A RELANCER : "&$U34,"")) -> A RELANCER : Analyse du besoin, CV, Questionnaire/Test, Contrat, Convocation, Eval intermediaire, Eval finale, Questionnaire satisfaction, Document de fin | X34: =IF(SUMPRODUCT(($B$2:$B$153=$B34)*($D$2:$D$153=$D34)*($E$2:$E$153=$E34)*($A$2:$A$153<>$A34))>0,"DOUBLON A VERIFIER","") | Y34: Oui
A35: Proforma Institut | B35: VIRAPHONG Thuy | C35: jules | D35: Développer son activité avec l’intelligence artificielle | E35: 2026-06-15 | F35: 2026-06-20 | G35: Accepté | H35: 81 CHE De figuerolles, 13180 GIGNAC LA NERTHE | I35: johana131@gmail.com | J35: 769874867 | K35: 15/10/1989 | L35: A faire | M35: ='WEDOF - EXAMEN FINAL'!D35 -> A faire | N35: Fait | O35: A faire | P35: A faire | Q35: Fait | R35: Fait | S35: Fait | T35: A faire | U35: =TEXTJOIN(", ",TRUE(),IF($L35="A faire","Analyse du besoin",""),IF($M35="A faire","CV",""),IF($N35="A faire","Questionnaire/Test",""),IF($O35="A faire","Contrat",""),IF($P35="A faire","Convocation",""),IF($Q35="A faire","Eval intermediaire",""),IF($R35="A faire","Eval finale",""),IF($S35="A faire","Questionnaire satisfaction",""),IF($T35="A faire","Document de fin","")) -> Analyse du besoin, CV, Contrat, Convocation, Document de fin | V35: =COUNTIF(L35:T35,"Fait")/9 -> 0.44444444 | W35: =IF($F35="","",IF(AND(TODAY()>=(DATEVALUE($F35)+1),$U35<>""),"A RELANCER : "&$U35,"")) -> A RELANCER : Analyse du besoin, CV, Contrat, Convocation, Document de fin | X35: =IF(SUMPRODUCT(($B$2:$B$153=$B35)*($D$2:$D$153=$D35)*($E$2:$E$153=$E35)*($A$2:$A$153<>$A35))>0,"DOUBLON A VERIFIER","") | Y35: Oui
A36: Proforma Institut | B36: POGGI Eric | C36: Sabri | E36: 2026-06-15 | F36: 2026-06-20 | G36: Accepté | L36: A faire | M36: ='WEDOF - EXAMEN FINAL'!D36 -> A faire | N36: Fait | O36: A faire | P36: A faire | Q36: A faire | R36: A faire | S36: A faire | T36: A faire | U36: =TEXTJOIN(", ",TRUE(),IF($L36="A faire","Analyse du besoin",""),IF($M36="A faire","CV",""),IF($N36="A faire","Questionnaire/Test",""),IF($O36="A faire","Contrat",""),IF($P36="A faire","Convocation",""),IF($Q36="A faire","Eval intermediaire",""),IF($R36="A faire","Eval finale",""),IF($S36="A faire","Questionnaire satisfaction",""),IF($T36="A faire","Document de fin","")) -> Analyse du besoin, CV, Contrat, Convocation, Eval intermediaire, Eval finale, Questionnaire satisfaction, Document de fin | V36: =COUNTIF(L36:T36,"Fait")/9 -> 0.11111111 | W36: =IF($F36="","",IF(AND(TODAY()>=(DATEVALUE($F36)+1),$U36<>""),"A RELANCER : "&$U36,"")) -> A RELANCER : Analyse du besoin, CV, Contrat, Convocation, Eval intermediaire, Eval finale, Questionnaire satisfaction, Document de fin | X36: =IF(SUMPRODUCT(($B$2:$B$153=$B36)*($D$2:$D$153=$D36)*($E$2:$E$153=$E36)*($A$2:$A$153<>$A36))>0,"DOUBLON A VERIFIER","") | Y36: Oui
A37: Proforma Institut | B37: POGGI Eric | C37: Sabri | D37: Communiquer sur les réseaux sociaux pour promouvoir sa TPE | E37: 2026-06-22 | F37: 2026-06-27 | G37: Accepté | L37: A faire | M37: ='WEDOF - EXAMEN FINAL'!D37 -> A faire | N37: Fait | O37: A faire | P37: A faire | Q37: A faire | R37: A faire | S37: A faire | T37: A faire | U37: =TEXTJOIN(", ",TRUE(),IF($L37="A faire","Analyse du besoin",""),IF($M37="A faire","CV",""),IF($N37="A faire","Questionnaire/Test",""),IF($O37="A faire","Contrat",""),IF($P37="A faire","Convocation",""),IF($Q37="A faire","Eval intermediaire",""),IF($R37="A faire","Eval finale",""),IF($S37="A faire","Questionnaire satisfaction",""),IF($T37="A faire","Document de fin","")) -> Analyse du besoin, CV, Contrat, Convocation, Eval intermediaire, Eval finale, Questionnaire satisfaction, Document de fin | V37: =COUNTIF(L37:T37,"Fait")/9 -> 0.11111111 | W37: =IF($F37="","",IF(AND(TODAY()>=(DATEVALUE($F37)+1),$U37<>""),"A RELANCER : "&$U37,"")) -> A RELANCER : Analyse du besoin, CV, Contrat, Convocation, Eval intermediaire, Eval finale, Questionnaire satisfaction, Document de fin | X37: =IF(SUMPRODUCT(($B$2:$B$153=$B37)*($D$2:$D$153=$D37)*($E$2:$E$153=$E37)*($A$2:$A$153<>$A37))>0,"DOUBLON A VERIFIER","") | Y37: Oui
A38: Proforma Institut | B38: MENDY Jean | C38: jean | D38: Développer son activité avec l’intelligence artificielle | E38: 2026-06-15 | F38: 2026-06-20 | G38: Accepté | H38: 11 CDEP Chemin des broutieres, 13015 MARSEILLE | I38: mendyjean1207@gmail.com | J38: 784862602 | K38: 1987-12-07 | L38: A faire | M38: ='WEDOF - EXAMEN FINAL'!D38 -> A faire | N38: Fait | O38: A faire | P38: A faire | Q38: Fait | R38: Fait | S38: Fait | T38: A faire | U38: =TEXTJOIN(", ",TRUE(),IF($L38="A faire","Analyse du besoin",""),IF($M38="A faire","CV",""),IF($N38="A faire","Questionnaire/Test",""),IF($O38="A faire","Contrat",""),IF($P38="A faire","Convocation",""),IF($Q38="A faire","Eval intermediaire",""),IF($R38="A faire","Eval finale",""),IF($S38="A faire","Questionnaire satisfaction",""),IF($T38="A faire","Document de fin","")) -> Analyse du besoin, CV, Contrat, Convocation, Document de fin | V38: =COUNTIF(L38:T38,"Fait")/9 -> 0.44444444 | W38: =IF($F38="","",IF(AND(TODAY()>=(DATEVALUE($F38)+1),$U38<>""),"A RELANCER : "&$U38,"")) -> A RELANCER : Analyse du besoin, CV, Contrat, Convocation, Document de fin | X38: =IF(SUMPRODUCT(($B$2:$B$153=$B38)*($D$2:$D$153=$D38)*($E$2:$E$153=$E38)*($A$2:$A$153<>$A38))>0,"DOUBLON A VERIFIER","") | Y38: Oui
A39: Proforma Institut | B39: BOUASRIA Najwa | C39: frere karim | D39: Développer son activité avec l’intelligence artificielle | E39: 2026-06-15 | F39: 2026-06-20 | G39: Accepté | H39: AV Marius Ruinat, 13700 MARIGNANE | I39: najwa.bouasria@gmail.com | J39: 761272644 | K39: 1997-06-09 | L39: A faire | M39: ='WEDOF - EXAMEN FINAL'!D39 -> A faire | N39: Fait | O39: A faire | P39: A faire | Q39: Fait | R39: Fait | S39: Fait | T39: A faire | U39: =TEXTJOIN(", ",TRUE(),IF($L39="A faire","Analyse du besoin",""),IF($M39="A faire","CV",""),IF($N39="A faire","Questionnaire/Test",""),IF($O39="A faire","Contrat",""),IF($P39="A faire","Convocation",""),IF($Q39="A faire","Eval intermediaire",""),IF($R39="A faire","Eval finale",""),IF($S39="A faire","Questionnaire satisfaction",""),IF($T39="A faire","Document de fin","")) -> Analyse du besoin, CV, Contrat, Convocation, Document de fin | V39: =COUNTIF(L39:T39,"Fait")/9 -> 0.44444444 | W39: =IF($F39="","",IF(AND(TODAY()>=(DATEVALUE($F39)+1),$U39<>""),"A RELANCER : "&$U39,"")) -> A RELANCER : Analyse du besoin, CV, Contrat, Convocation, Document de fin | X39: =IF(SUMPRODUCT(($B$2:$B$153=$B39)*($D$2:$D$153=$D39)*($E$2:$E$153=$E39)*($A$2:$A$153<>$A39))>0,"DOUBLON A VERIFIER","") | Y39: Oui
A40: Proforma Institut | B40: JAVAZZO Jerome | C40: hak | D40: Améliorer l'efficacité de sa TPE à l'aide de l'IA | E40: 2026-06-29 | F40: 2026-07-04 | G40: Accepté | L40: A faire | M40: ='WEDOF - EXAMEN FINAL'!D40 -> A faire | N40: A faire | O40: A faire | P40: A faire | Q40: A faire | R40: A faire | S40: A faire | T40: A faire | U40: =TEXTJOIN(", ",TRUE(),IF($L40="A faire","Analyse du besoin",""),IF($M40="A faire","CV",""),IF($N40="A faire","Questionnaire/Test",""),IF($O40="A faire","Contrat",""),IF($P40="A faire","Convocation",""),IF($Q40="A faire","Eval intermediaire",""),IF($R40="A faire","Eval finale",""),IF($S40="A faire","Questionnaire satisfaction",""),IF($T40="A faire","Document de fin","")) -> Analyse du besoin, CV, Questionnaire/Test, Contrat, Convocation, Eval intermediaire, Eval finale, Questionnaire satisfaction, Document de fin | V40: =COUNTIF(L40:T40,"Fait")/9 -> 0 | W40: =IF($F40="","",IF(AND(TODAY()>=(DATEVALUE($F40)+1),$U40<>""),"A RELANCER : "&$U40,"")) -> A RELANCER : Analyse du besoin, CV, Questionnaire/Test, Contrat, Convocation, Eval intermediaire, Eval finale, Questionnaire satisfaction, Document de fin | X40: =IF(SUMPRODUCT(($B$2:$B$153=$B40)*($D$2:$D$153=$D40)*($E$2:$E$153=$E40)*($A$2:$A$153<>$A40))>0,"DOUBLON A VERIFIER","") | Y40: Oui
A41: Proforma Institut | B41: JAVAZZO Jerome | C41: hak | D41: Communiquer sur les réseaux sociaux pour promouvoir sa TPE | E41: 2026-06-22 | F41: 2026-06-27 | G41: Accepté | L41: A faire | M41: ='WEDOF - EXAMEN FINAL'!D41 -> A faire | N41: A faire | O41: A faire | P41: A faire | Q41: A faire | R41: A faire | S41: A faire | T41: A faire | U41: =TEXTJOIN(", ",TRUE(),IF($L41="A faire","Analyse du besoin",""),IF($M41="A faire","CV",""),IF($N41="A faire","Questionnaire/Test",""),IF($O41="A faire","Contrat",""),IF($P41="A faire","Convocation",""),IF($Q41="A faire","Eval intermediaire",""),IF($R41="A faire","Eval finale",""),IF($S41="A faire","Questionnaire satisfaction",""),IF($T41="A faire","Document de fin","")) -> Analyse du besoin, CV, Questionnaire/Test, Contrat, Convocation, Eval intermediaire, Eval finale, Questionnaire satisfaction, Document de fin | V41: =COUNTIF(L41:T41,"Fait")/9 -> 0 | W41: =IF($F41="","",IF(AND(TODAY()>=(DATEVALUE($F41)+1),$U41<>""),"A RELANCER : "&$U41,"")) -> A RELANCER : Analyse du besoin, CV, Questionnaire/Test, Contrat, Convocation, Eval intermediaire, Eval finale, Questionnaire satisfaction, Document de fin | X41: =IF(SUMPRODUCT(($B$2:$B$153=$B41)*($D$2:$D$153=$D41)*($E$2:$E$153=$E41)*($A$2:$A$153<>$A41))>0,"DOUBLON A VERIFIER","") | Y41: Oui
A42: Proforma Institut | B42: KECHIOUCHE Younes | C42: hak | D42: Développer son activité avec l’intelligence artificielle | E42: 2026-06-22 | F42: 2026-06-27 | G42: Accepté | L42: A faire | M42: ='WEDOF - EXAMEN FINAL'!D42 -> A faire | N42: A faire | O42: A faire | P42: A faire | Q42: Fait | R42: Fait | S42: Fait | T42: A faire | U42: =TEXTJOIN(", ",TRUE(),IF($L42="A faire","Analyse du besoin",""),IF($M42="A faire","CV",""),IF($N42="A faire","Questionnaire/Test",""),IF($O42="A faire","Contrat",""),IF($P42="A faire","Convocation",""),IF($Q42="A faire","Eval intermediaire",""),IF($R42="A faire","Eval finale",""),IF($S42="A faire","Questionnaire satisfaction",""),IF($T42="A faire","Document de fin","")) -> Analyse du besoin, CV, Questionnaire/Test, Contrat, Convocation, Document de fin | V42: =COUNTIF(L42:T42,"Fait")/9 -> 0.33333333 | W42: =IF($F42="","",IF(AND(TODAY()>=(DATEVALUE($F42)+1),$U42<>""),"A RELANCER : "&$U42,"")) -> A RELANCER : Analyse du besoin, CV, Questionnaire/Test, Contrat, Convocation, Document de fin | X42: =IF(SUMPRODUCT(($B$2:$B$153=$B42)*($D$2:$D$153=$D42)*($E$2:$E$153=$E42)*($A$2:$A$153<>$A42))>0,"DOUBLON A VERIFIER","") | Y42: Oui
A43: Proforma Institut | B43: LAHRAOUI Amir | C43: GRAS | D43: Améliorer l'efficacité de sa TPE à l'aide de l'IA | E43: 2026-06-29 | F43: 2026-07-04 | G43: Accepté | L43: A faire | M43: ='WEDOF - EXAMEN FINAL'!D43 -> A faire | N43: A faire | O43: A faire | P43: A faire | Q43: A faire | R43: A faire | S43: A faire | T43: A faire | U43: =TEXTJOIN(", ",TRUE(),IF($L43="A faire","Analyse du besoin",""),IF($M43="A faire","CV",""),IF($N43="A faire","Questionnaire/Test",""),IF($O43="A faire","Contrat",""),IF($P43="A faire","Convocation",""),IF($Q43="A faire","Eval intermediaire",""),IF($R43="A faire","Eval finale",""),IF($S43="A faire","Questionnaire satisfaction",""),IF($T43="A faire","Document de fin","")) -> Analyse du besoin, CV, Questionnaire/Test, Contrat, Convocation, Eval intermediaire, Eval finale, Questionnaire satisfaction, Document de fin | V43: =COUNTIF(L43:T43,"Fait")/9 -> 0 | W43: =IF($F43="","",IF(AND(TODAY()>=(DATEVALUE($F43)+1),$U43<>""),"A RELANCER : "&$U43,"")) -> A RELANCER : Analyse du besoin, CV, Questionnaire/Test, Contrat, Convocation, Eval intermediaire, Eval finale, Questionnaire satisfaction, Document de fin | X43: =IF(SUMPRODUCT(($B$2:$B$153=$B43)*($D$2:$D$153=$D43)*($E$2:$E$153=$E43)*($A$2:$A$153<>$A43))>0,"DOUBLON A VERIFIER","") | Y43: Oui
A44: Proforma Institut | B44: LAHRAOUI Amir | C44: GRAS | D44: Communiquer sur les réseaux sociaux pour promouvoir sa TPE | E44: 2026-07-06 | F44: 2026-07-11 | G44: Accepté | L44: A faire | M44: ='WEDOF - EXAMEN FINAL'!D44 -> A faire | N44: A faire | O44: A faire | P44: A faire | Q44: A faire | R44: A faire | S44: A faire | T44: A faire | U44: =TEXTJOIN(", ",TRUE(),IF($L44="A faire","Analyse du besoin",""),IF($M44="A faire","CV",""),IF($N44="A faire","Questionnaire/Test",""),IF($O44="A faire","Contrat",""),IF($P44="A faire","Convocation",""),IF($Q44="A faire","Eval intermediaire",""),IF($R44="A faire","Eval finale",""),IF($S44="A faire","Questionnaire satisfaction",""),IF($T44="A faire","Document de fin","")) -> Analyse du besoin, CV, Questionnaire/Test, Contrat, Convocation, Eval intermediaire, Eval finale, Questionnaire satisfaction, Document de fin | V44: =COUNTIF(L44:T44,"Fait")/9 -> 0 | W44: =IF($F44="","",IF(AND(TODAY()>=(DATEVALUE($F44)+1),$U44<>""),"A RELANCER : "&$U44,"")) -> A RELANCER : Analyse du besoin, CV, Questionnaire/Test, Contrat, Convocation, Eval intermediaire, Eval finale, Questionnaire satisfaction, Document de fin | X44: =IF(SUMPRODUCT(($B$2:$B$153=$B44)*($D$2:$D$153=$D44)*($E$2:$E$153=$E44)*($A$2:$A$153<>$A44))>0,"DOUBLON A VERIFIER","") | Y44: Oui
A45: Proforma Institut | B45: LAHRAOUI Amir | C45: GRAS | D45: Réaliser les opérations comptables courantes d'une TPE | E45: 2026-07-13 | F45: 2026-07-18 | G45: Accepté | L45: A faire | M45: ='WEDOF - EXAMEN FINAL'!D45 -> A faire | N45: A faire | O45: A faire | P45: A faire | Q45: A faire | R45: A faire | S45: A faire | T45: A faire | U45: =TEXTJOIN(", ",TRUE(),IF($L45="A faire","Analyse du besoin",""),IF($M45="A faire","CV",""),IF($N45="A faire","Questionnaire/Test",""),IF($O45="A faire","Contrat",""),IF($P45="A faire","Convocation",""),IF($Q45="A faire","Eval intermediaire",""),IF($R45="A faire","Eval finale",""),IF($S45="A faire","Questionnaire satisfaction",""),IF($T45="A faire","Document de fin","")) -> Analyse du besoin, CV, Questionnaire/Test, Contrat, Convocation, Eval intermediaire, Eval finale, Questionnaire satisfaction, Document de fin | V45: =COUNTIF(L45:T45,"Fait")/9 -> 0 | W45: =IF($F45="","",IF(AND(TODAY()>=(DATEVALUE($F45)+1),$U45<>""),"A RELANCER : "&$U45,"")) -> A RELANCER : Analyse du besoin, CV, Questionnaire/Test, Contrat, Convocation, Eval intermediaire, Eval finale, Questionnaire satisfaction, Document de fin | X45: =IF(SUMPRODUCT(($B$2:$B$153=$B45)*($D$2:$D$153=$D45)*($E$2:$E$153=$E45)*($A$2:$A$153<>$A45))>0,"DOUBLON A VERIFIER","") | Y45: Oui
A46: Proforma Institut | B46: blot valerie | C46: Djody | D46: Réaliser les opérations comptables courantes d'une TPE | E46: 2026-06-24 | F46: 2026-07-24 | G46: Accepté | L46: A faire | M46: ='WEDOF - EXAMEN FINAL'!D46 -> A faire | N46: A faire | O46: A faire | P46: A faire | Q46: A faire | R46: A faire | S46: A faire | T46: A faire | U46: =TEXTJOIN(", ",TRUE(),IF($L46="A faire","Analyse du besoin",""),IF($M46="A faire","CV",""),IF($N46="A faire","Questionnaire/Test",""),IF($O46="A faire","Contrat",""),IF($P46="A faire","Convocation",""),IF($Q46="A faire","Eval intermediaire",""),IF($R46="A faire","Eval finale",""),IF($S46="A faire","Questionnaire satisfaction",""),IF($T46="A faire","Document de fin","")) -> Analyse du besoin, CV, Questionnaire/Test, Contrat, Convocation, Eval intermediaire, Eval finale, Questionnaire satisfaction, Document de fin | V46: =COUNTIF(L46:T46,"Fait")/9 -> 0 | W46: =IF($F46="","",IF(AND(TODAY()>=(DATEVALUE($F46)+1),$U46<>""),"A RELANCER : "&$U46,"")) | X46: =IF(SUMPRODUCT(($B$2:$B$153=$B46)*($D$2:$D$153=$D46)*($E$2:$E$153=$E46)*($A$2:$A$153<>$A46))>0,"DOUBLON A VERIFIER","") | Y46: Oui
A47: Proforma Institut | B47: CARRETTA Capucine | C47: jules | D47: Développer son activité avec l’intelligence artificielle | E47: 2026-06-29 | F47: 2026-07-04 | G47: Accepté | L47: A faire | M47: ='WEDOF - EXAMEN FINAL'!D47 -> A faire | N47: A faire | O47: A faire | P47: A faire | Q47: Fait | R47: Fait | S47: Fait | T47: A faire | U47: =TEXTJOIN(", ",TRUE(),IF($L47="A faire","Analyse du besoin",""),IF($M47="A faire","CV",""),IF($N47="A faire","Questionnaire/Test",""),IF($O47="A faire","Contrat",""),IF($P47="A faire","Convocation",""),IF($Q47="A faire","Eval intermediaire",""),IF($R47="A faire","Eval finale",""),IF($S47="A faire","Questionnaire satisfaction",""),IF($T47="A faire","Document de fin","")) -> Analyse du besoin, CV, Questionnaire/Test, Contrat, Convocation, Document de fin | V47: =COUNTIF(L47:T47,"Fait")/9 -> 0.33333333 | W47: =IF($F47="","",IF(AND(TODAY()>=(DATEVALUE($F47)+1),$U47<>""),"A RELANCER : "&$U47,"")) -> A RELANCER : Analyse du besoin, CV, Questionnaire/Test, Contrat, Convocation, Document de fin | X47: =IF(SUMPRODUCT(($B$2:$B$153=$B47)*($D$2:$D$153=$D47)*($E$2:$E$153=$E47)*($A$2:$A$153<>$A47))>0,"DOUBLON A VERIFIER","") | Y47: Oui
A48: Proforma Institut | B48: OUAHAB Yanis | C48: priscot | D48: Améliorer l'efficacité de sa TPE à l'aide de l'IA | E48: 2026-06-29 | F48: 2026-07-04 | G48: Accepté | L48: A faire | M48: ='WEDOF - EXAMEN FINAL'!D48 -> A faire | N48: A faire | O48: A faire | P48: A faire | Q48: A faire | R48: A faire | S48: A faire | T48: A faire | U48: =TEXTJOIN(", ",TRUE(),IF($L48="A faire","Analyse du besoin",""),IF($M48="A faire","CV",""),IF($N48="A faire","Questionnaire/Test",""),IF($O48="A faire","Contrat",""),IF($P48="A faire","Convocation",""),IF($Q48="A faire","Eval intermediaire",""),IF($R48="A faire","Eval finale",""),IF($S48="A faire","Questionnaire satisfaction",""),IF($T48="A faire","Document de fin","")) -> Analyse du besoin, CV, Questionnaire/Test, Contrat, Convocation, Eval intermediaire, Eval finale, Questionnaire satisfaction, Document de fin | V48: =COUNTIF(L48:T48,"Fait")/9 -> 0 | W48: =IF($F48="","",IF(AND(TODAY()>=(DATEVALUE($F48)+1),$U48<>""),"A RELANCER : "&$U48,"")) -> A RELANCER : Analyse du besoin, CV, Questionnaire/Test, Contrat, Convocation, Eval intermediaire, Eval finale, Questionnaire satisfaction, Document de fin | X48: =IF(SUMPRODUCT(($B$2:$B$153=$B48)*($D$2:$D$153=$D48)*($E$2:$E$153=$E48)*($A$2:$A$153<>$A48))>0,"DOUBLON A VERIFIER","") | Y48: Oui
A49: Proforma Institut | B49: OUAHAB Yanis | C49: priscot | D49: Communiquer sur les réseaux sociaux pour promouvoir sa TPE | E49: 2026-07-06 | F49: 2026-07-11 | G49: Accepté | L49: A faire | M49: ='WEDOF - EXAMEN FINAL'!D49 -> A faire | N49: A faire | O49: A faire | P49: A faire | Q49: A faire | R49: A faire | S49: A faire | T49: A faire | U49: =TEXTJOIN(", ",TRUE(),IF($L49="A faire","Analyse du besoin",""),IF($M49="A faire","CV",""),IF($N49="A faire","Questionnaire/Test",""),IF($O49="A faire","Contrat",""),IF($P49="A faire","Convocation",""),IF($Q49="A faire","Eval intermediaire",""),IF($R49="A faire","Eval finale",""),IF($S49="A faire","Questionnaire satisfaction",""),IF($T49="A faire","Document de fin","")) -> Analyse du besoin, CV, Questionnaire/Test, Contrat, Convocation, Eval intermediaire, Eval finale, Questionnaire satisfaction, Document de fin | V49: =COUNTIF(L49:T49,"Fait")/9 -> 0 | W49: =IF($F49="","",IF(AND(TODAY()>=(DATEVALUE($F49)+1),$U49<>""),"A RELANCER : "&$U49,"")) -> A RELANCER : Analyse du besoin, CV, Questionnaire/Test, Contrat, Convocation, Eval intermediaire, Eval finale, Questionnaire satisfaction, Document de fin | X49: =IF(SUMPRODUCT(($B$2:$B$153=$B49)*($D$2:$D$153=$D49)*($E$2:$E$153=$E49)*($A$2:$A$153<>$A49))>0,"DOUBLON A VERIFIER","") | Y49: Oui
A50: Proforma Institut | B50: DJIBILIAN Yoann | C50: Nedjma | D50: Améliorer l'efficacité de sa TPE à l'aide de l'IA | E50: 2026-06-29 | F50: 2026-07-04 | G50: Accepté | H50: 18 PL place d'Amont, 13390 AURIOL | I50: yoann.djibilian@laposte.net | J50: 645742336 | K50: 26/09/1999 | L50: A faire | M50: ='WEDOF - EXAMEN FINAL'!D50 -> A faire | N50: A faire | O50: A faire | P50: A faire | Q50: A faire | R50: A faire | S50: A faire | T50: A faire | U50: =TEXTJOIN(", ",TRUE(),IF($L50="A faire","Analyse du besoin",""),IF($M50="A faire","CV",""),IF($N50="A faire","Questionnaire/Test",""),IF($O50="A faire","Contrat",""),IF($P50="A faire","Convocation",""),IF($Q50="A faire","Eval intermediaire",""),IF($R50="A faire","Eval finale",""),IF($S50="A faire","Questionnaire satisfaction",""),IF($T50="A faire","Document de fin","")) -> Analyse du besoin, CV, Questionnaire/Test, Contrat, Convocation, Eval intermediaire, Eval finale, Questionnaire satisfaction, Document de fin | V50: =COUNTIF(L50:T50,"Fait")/9 -> 0 | W50: =IF($F50="","",IF(AND(TODAY()>=(DATEVALUE($F50)+1),$U50<>""),"A RELANCER : "&$U50,"")) -> A RELANCER : Analyse du besoin, CV, Questionnaire/Test, Contrat, Convocation, Eval intermediaire, Eval finale, Questionnaire satisfaction, Document de fin | X50: =IF(SUMPRODUCT(($B$2:$B$153=$B50)*($D$2:$D$153=$D50)*($E$2:$E$153=$E50)*($A$2:$A$153<>$A50))>0,"DOUBLON A VERIFIER","") | Y50: Oui
A51: Proforma Institut | B51: DJIBILIAN Yoann | C51: Nedjma | D51: Communiquer sur les réseaux sociaux pour promouvoir sa TPE | E51: 2026-07-06 | F51: 2026-07-11 | G51: Accepté | H51: 18 PL place d'Amont, 13390 AURIOL | I51: yoann.djibilian@laposte.net | J51: 645742336 | K51: 26/09/1999 | L51: A faire | M51: ='WEDOF - EXAMEN FINAL'!D51 -> A faire | N51: A faire | O51: A faire | P51: A faire | Q51: A faire | R51: A faire | S51: A faire | T51: A faire | U51: =TEXTJOIN(", ",TRUE(),IF($L51="A faire","Analyse du besoin",""),IF($M51="A faire","CV",""),IF($N51="A faire","Questionnaire/Test",""),IF($O51="A faire","Contrat",""),IF($P51="A faire","Convocation",""),IF($Q51="A faire","Eval intermediaire",""),IF($R51="A faire","Eval finale",""),IF($S51="A faire","Questionnaire satisfaction",""),IF($T51="A faire","Document de fin","")) -> Analyse du besoin, CV, Questionnaire/Test, Contrat, Convocation, Eval intermediaire, Eval finale, Questionnaire satisfaction, Document de fin | V51: =COUNTIF(L51:T51,"Fait")/9 -> 0 | W51: =IF($F51="","",IF(AND(TODAY()>=(DATEVALUE($F51)+1),$U51<>""),"A RELANCER : "&$U51,"")) -> A RELANCER : Analyse du besoin, CV, Questionnaire/Test, Contrat, Convocation, Eval intermediaire, Eval finale, Questionnaire satisfaction, Document de fin | X51: =IF(SUMPRODUCT(($B$2:$B$153=$B51)*($D$2:$D$153=$D51)*($E$2:$E$153=$E51)*($A$2:$A$153<>$A51))>0,"DOUBLON A VERIFIER","") | Y51: Oui
A52: Proforma Institut | B52: FRANGIAN Vazguen | C52: GRAS | D52: Améliorer l'efficacité de sa TPE à l'aide de l'IA | E52: 2026-07-13 | F52: 2026-07-18 | G52: Accepté | L52: A faire | M52: ='WEDOF - EXAMEN FINAL'!D52 -> A faire | N52: A faire | O52: A faire | P52: A faire | Q52: A faire | R52: A faire | S52: A faire | T52: A faire | U52: =TEXTJOIN(", ",TRUE(),IF($L52="A faire","Analyse du besoin",""),IF($M52="A faire","CV",""),IF($N52="A faire","Questionnaire/Test",""),IF($O52="A faire","Contrat",""),IF($P52="A faire","Convocation",""),IF($Q52="A faire","Eval intermediaire",""),IF($R52="A faire","Eval finale",""),IF($S52="A faire","Questionnaire satisfaction",""),IF($T52="A faire","Document de fin","")) -> Analyse du besoin, CV, Questionnaire/Test, Contrat, Convocation, Eval intermediaire, Eval finale, Questionnaire satisfaction, Document de fin | V52: =COUNTIF(L52:T52,"Fait")/9 -> 0 | W52: =IF($F52="","",IF(AND(TODAY()>=(DATEVALUE($F52)+1),$U52<>""),"A RELANCER : "&$U52,"")) -> A RELANCER : Analyse du besoin, CV, Questionnaire/Test, Contrat, Convocation, Eval intermediaire, Eval finale, Questionnaire satisfaction, Document de fin | X52: =IF(SUMPRODUCT(($B$2:$B$153=$B52)*($D$2:$D$153=$D52)*($E$2:$E$153=$E52)*($A$2:$A$153<>$A52))>0,"DOUBLON A VERIFIER","") | Y52: Oui
A53: Proforma Institut | B53: FRANGIAN Vazguen | C53: GRAS | D53: Communiquer sur les réseaux sociaux pour promouvoir sa TPE | E53: 2026-07-20 | F53: 2026-07-25 | G53: Accepté | L53: A faire | M53: ='WEDOF - EXAMEN FINAL'!D53 -> A faire | N53: A faire | O53: A faire | P53: A faire | Q53: A faire | R53: A faire | S53: A faire | T53: A faire | U53: =TEXTJOIN(", ",TRUE(),IF($L53="A faire","Analyse du besoin",""),IF($M53="A faire","CV",""),IF($N53="A faire","Questionnaire/Test",""),IF($O53="A faire","Contrat",""),IF($P53="A faire","Convocation",""),IF($Q53="A faire","Eval intermediaire",""),IF($R53="A faire","Eval finale",""),IF($S53="A faire","Questionnaire satisfaction",""),IF($T53="A faire","Document de fin","")) -> Analyse du besoin, CV, Questionnaire/Test, Contrat, Convocation, Eval intermediaire, Eval finale, Questionnaire satisfaction, Document de fin | V53: =COUNTIF(L53:T53,"Fait")/9 -> 0 | W53: =IF($F53="","",IF(AND(TODAY()>=(DATEVALUE($F53)+1),$U53<>""),"A RELANCER : "&$U53,"")) | X53: =IF(SUMPRODUCT(($B$2:$B$153=$B53)*($D$2:$D$153=$D53)*($E$2:$E$153=$E53)*($A$2:$A$153<>$A53))>0,"DOUBLON A VERIFIER","") | Y53: Oui
A54: Proforma Institut | B54: FRANGIAN Vazguen | C54: GRAS | D54: Réaliser les opérations comptables courantes d'une TPE | E54: 2026-07-27 | F54: 2026-08-01 | G54: Accepté | L54: A faire | M54: ='WEDOF - EXAMEN FINAL'!D54 -> A faire | N54: A faire | O54: A faire | P54: A faire | Q54: A faire | R54: A faire | S54: A faire | T54: A faire | U54: =TEXTJOIN(", ",TRUE(),IF($L54="A faire","Analyse du besoin",""),IF($M54="A faire","CV",""),IF($N54="A faire","Questionnaire/Test",""),IF($O54="A faire","Contrat",""),IF($P54="A faire","Convocation",""),IF($Q54="A faire","Eval intermediaire",""),IF($R54="A faire","Eval finale",""),IF($S54="A faire","Questionnaire satisfaction",""),IF($T54="A faire","Document de fin","")) -> Analyse du besoin, CV, Questionnaire/Test, Contrat, Convocation, Eval intermediaire, Eval finale, Questionnaire satisfaction, Document de fin | V54: =COUNTIF(L54:T54,"Fait")/9 -> 0 | W54: =IF($F54="","",IF(AND(TODAY()>=(DATEVALUE($F54)+1),$U54<>""),"A RELANCER : "&$U54,"")) | X54: =IF(SUMPRODUCT(($B$2:$B$153=$B54)*($D$2:$D$153=$D54)*($E$2:$E$153=$E54)*($A$2:$A$153<>$A54))>0,"DOUBLON A VERIFIER","") | Y54: Oui
A55: Proforma Institut | B55: MELIKSETIAN Suren | C55: Sabri | D55: Développer son activité avec l’intelligence artificielle | E55: 2026-07-06 | F55: 2026-07-11 | G55: Accepté | L55: A faire | M55: ='WEDOF - EXAMEN FINAL'!D55 -> A faire | N55: A faire | O55: A faire | P55: A faire | Q55: Fait | R55: Fait | S55: Fait | T55: A faire | U55: =TEXTJOIN(", ",TRUE(),IF($L55="A faire","Analyse du besoin",""),IF($M55="A faire","CV",""),IF($N55="A faire","Questionnaire/Test",""),IF($O55="A faire","Contrat",""),IF($P55="A faire","Convocation",""),IF($Q55="A faire","Eval intermediaire",""),IF($R55="A faire","Eval finale",""),IF($S55="A faire","Questionnaire satisfaction",""),IF($T55="A faire","Document de fin","")) -> Analyse du besoin, CV, Questionnaire/Test, Contrat, Convocation, Document de fin | V55: =COUNTIF(L55:T55,"Fait")/9 -> 0.33333333 | W55: =IF($F55="","",IF(AND(TODAY()>=(DATEVALUE($F55)+1),$U55<>""),"A RELANCER : "&$U55,"")) -> A RELANCER : Analyse du besoin, CV, Questionnaire/Test, Contrat, Convocation, Document de fin | X55: =IF(SUMPRODUCT(($B$2:$B$153=$B55)*($D$2:$D$153=$D55)*($E$2:$E$153=$E55)*($A$2:$A$153<>$A55))>0,"DOUBLON A VERIFIER","") | Y55: Oui
A56: Proforma Institut | B56: ATAYAN Julieta | C56: Sabri | D56: Développer son activité avec l’intelligence artificielle | E56: 2026-07-06 | F56: 2026-07-11 | G56: Accepté | L56: A faire | M56: ='WEDOF - EXAMEN FINAL'!D56 -> A faire | N56: A faire | O56: A faire | P56: A faire | Q56: Fait | R56: Fait | S56: Fait | T56: A faire | U56: =TEXTJOIN(", ",TRUE(),IF($L56="A faire","Analyse du besoin",""),IF($M56="A faire","CV",""),IF($N56="A faire","Questionnaire/Test",""),IF($O56="A faire","Contrat",""),IF($P56="A faire","Convocation",""),IF($Q56="A faire","Eval intermediaire",""),IF($R56="A faire","Eval finale",""),IF($S56="A faire","Questionnaire satisfaction",""),IF($T56="A faire","Document de fin","")) -> Analyse du besoin, CV, Questionnaire/Test, Contrat, Convocation, Document de fin | V56: =COUNTIF(L56:T56,"Fait")/9 -> 0.33333333 | W56: =IF($F56="","",IF(AND(TODAY()>=(DATEVALUE($F56)+1),$U56<>""),"A RELANCER : "&$U56,"")) -> A RELANCER : Analyse du besoin, CV, Questionnaire/Test, Contrat, Convocation, Document de fin | X56: =IF(SUMPRODUCT(($B$2:$B$153=$B56)*($D$2:$D$153=$D56)*($E$2:$E$153=$E56)*($A$2:$A$153<>$A56))>0,"DOUBLON A VERIFIER","") | Y56: Oui
A57: Proforma Institut | B57: VARDANYAN Anait | C57: Sabri | D57: Développer son activité avec l’intelligence artificielle | E57: 2026-07-06 | F57: 2026-07-11 | G57: Accepté | L57: A faire | M57: ='WEDOF - EXAMEN FINAL'!D57 -> A faire | N57: A faire | O57: A faire | P57: A faire | Q57: Fait | R57: Fait | S57: Fait | T57: A faire | U57: =TEXTJOIN(", ",TRUE(),IF($L57="A faire","Analyse du besoin",""),IF($M57="A faire","CV",""),IF($N57="A faire","Questionnaire/Test",""),IF($O57="A faire","Contrat",""),IF($P57="A faire","Convocation",""),IF($Q57="A faire","Eval intermediaire",""),IF($R57="A faire","Eval finale",""),IF($S57="A faire","Questionnaire satisfaction",""),IF($T57="A faire","Document de fin","")) -> Analyse du besoin, CV, Questionnaire/Test, Contrat, Convocation, Document de fin | V57: =COUNTIF(L57:T57,"Fait")/9 -> 0.33333333 | W57: =IF($F57="","",IF(AND(TODAY()>=(DATEVALUE($F57)+1),$U57<>""),"A RELANCER : "&$U57,"")) -> A RELANCER : Analyse du besoin, CV, Questionnaire/Test, Contrat, Convocation, Document de fin | X57: =IF(SUMPRODUCT(($B$2:$B$153=$B57)*($D$2:$D$153=$D57)*($E$2:$E$153=$E57)*($A$2:$A$153<>$A57))>0,"DOUBLON A VERIFIER","") | Y57: Oui
A58: Proforma Institut | B58: EL BOUGHABI Adil | C58: MOH | D58: Améliorer l'efficacité de sa TPE à l'aide de l'IA | E58: 2026-07-13 | F58: 2026-07-18 | G58: Accepté | L58: A faire | M58: ='WEDOF - EXAMEN FINAL'!D58 -> A faire | N58: A faire | O58: A faire | P58: A faire | Q58: A faire | R58: A faire | S58: A faire | T58: A faire | U58: =TEXTJOIN(", ",TRUE(),IF($L58="A faire","Analyse du besoin",""),IF($M58="A faire","CV",""),IF($N58="A faire","Questionnaire/Test",""),IF($O58="A faire","Contrat",""),IF($P58="A faire","Convocation",""),IF($Q58="A faire","Eval intermediaire",""),IF($R58="A faire","Eval finale",""),IF($S58="A faire","Questionnaire satisfaction",""),IF($T58="A faire","Document de fin","")) -> Analyse du besoin, CV, Questionnaire/Test, Contrat, Convocation, Eval intermediaire, Eval finale, Questionnaire satisfaction, Document de fin | V58: =COUNTIF(L58:T58,"Fait")/9 -> 0 | W58: =IF($F58="","",IF(AND(TODAY()>=(DATEVALUE($F58)+1),$U58<>""),"A RELANCER : "&$U58,"")) -> A RELANCER : Analyse du besoin, CV, Questionnaire/Test, Contrat, Convocation, Eval intermediaire, Eval finale, Questionnaire satisfaction, Document de fin | X58: =IF(SUMPRODUCT(($B$2:$B$153=$B58)*($D$2:$D$153=$D58)*($E$2:$E$153=$E58)*($A$2:$A$153<>$A58))>0,"DOUBLON A VERIFIER","") | Y58: Oui
A59: Proforma Institut | B59: EL BOUGHABI Adil | C59: MOH | D59: Communiquer sur les réseaux sociaux pour promouvoir sa TPE | E59: 2026-07-20 | F59: 2026-07-25 | G59: Accepté | L59: A faire | M59: ='WEDOF - EXAMEN FINAL'!D59 -> A faire | N59: A faire | O59: A faire | P59: A faire | Q59: A faire | R59: A faire | S59: A faire | T59: A faire | U59: =TEXTJOIN(", ",TRUE(),IF($L59="A faire","Analyse du besoin",""),IF($M59="A faire","CV",""),IF($N59="A faire","Questionnaire/Test",""),IF($O59="A faire","Contrat",""),IF($P59="A faire","Convocation",""),IF($Q59="A faire","Eval intermediaire",""),IF($R59="A faire","Eval finale",""),IF($S59="A faire","Questionnaire satisfaction",""),IF($T59="A faire","Document de fin","")) -> Analyse du besoin, CV, Questionnaire/Test, Contrat, Convocation, Eval intermediaire, Eval finale, Questionnaire satisfaction, Document de fin | V59: =COUNTIF(L59:T59,"Fait")/9 -> 0 | W59: =IF($F59="","",IF(AND(TODAY()>=(DATEVALUE($F59)+1),$U59<>""),"A RELANCER : "&$U59,"")) | X59: =IF(SUMPRODUCT(($B$2:$B$153=$B59)*($D$2:$D$153=$D59)*($E$2:$E$153=$E59)*($A$2:$A$153<>$A59))>0,"DOUBLON A VERIFIER","") | Y59: Oui
A60: Proforma Institut | B60: ALARCON Lucas | C60: MOH | D60: Améliorer l'efficacité de sa TPE à l'aide de l'IA | E60: 2026-07-13 | F60: 2026-07-18 | G60: Accepté | L60: A faire | M60: ='WEDOF - EXAMEN FINAL'!D60 -> A faire | N60: A faire | O60: A faire | P60: A faire | Q60: A faire | R60: A faire | S60: A faire | T60: A faire | U60: =TEXTJOIN(", ",TRUE(),IF($L60="A faire","Analyse du besoin",""),IF($M60="A faire","CV",""),IF($N60="A faire","Questionnaire/Test",""),IF($O60="A faire","Contrat",""),IF($P60="A faire","Convocation",""),IF($Q60="A faire","Eval intermediaire",""),IF($R60="A faire","Eval finale",""),IF($S60="A faire","Questionnaire satisfaction",""),IF($T60="A faire","Document de fin","")) -> Analyse du besoin, CV, Questionnaire/Test, Contrat, Convocation, Eval intermediaire, Eval finale, Questionnaire satisfaction, Document de fin | V60: =COUNTIF(L60:T60,"Fait")/9 -> 0 | W60: =IF($F60="","",IF(AND(TODAY()>=(DATEVALUE($F60)+1),$U60<>""),"A RELANCER : "&$U60,"")) -> A RELANCER : Analyse du besoin, CV, Questionnaire/Test, Contrat, Convocation, Eval intermediaire, Eval finale, Questionnaire satisfaction, Document de fin | X60: =IF(SUMPRODUCT(($B$2:$B$153=$B60)*($D$2:$D$153=$D60)*($E$2:$E$153=$E60)*($A$2:$A$153<>$A60))>0,"DOUBLON A VERIFIER","") | Y60: Oui
A61: Proforma Institut | B61: ALARCON Lucas | C61: MOH | D61: Communiquer sur les réseaux sociaux pour promouvoir sa TPE | E61: 2026-07-20 | F61: 2026-07-25 | G61: Accepté | L61: A faire | M61: ='WEDOF - EXAMEN FINAL'!D61 -> A faire | N61: A faire | O61: A faire | P61: A faire | Q61: A faire | R61: A faire | S61: A faire | T61: A faire | U61: =TEXTJOIN(", ",TRUE(),IF($L61="A faire","Analyse du besoin",""),IF($M61="A faire","CV",""),IF($N61="A faire","Questionnaire/Test",""),IF($O61="A faire","Contrat",""),IF($P61="A faire","Convocation",""),IF($Q61="A faire","Eval intermediaire",""),IF($R61="A faire","Eval finale",""),IF($S61="A faire","Questionnaire satisfaction",""),IF($T61="A faire","Document de fin","")) -> Analyse du besoin, CV, Questionnaire/Test, Contrat, Convocation, Eval intermediaire, Eval finale, Questionnaire satisfaction, Document de fin | V61: =COUNTIF(L61:T61,"Fait")/9 -> 0 | W61: =IF($F61="","",IF(AND(TODAY()>=(DATEVALUE($F61)+1),$U61<>""),"A RELANCER : "&$U61,"")) | X61: =IF(SUMPRODUCT(($B$2:$B$153=$B61)*($D$2:$D$153=$D61)*($E$2:$E$153=$E61)*($A$2:$A$153<>$A61))>0,"DOUBLON A VERIFIER","") | Y61: Oui
A62: Proforma Institut | B62: ARGOUBI Karim | C62: Djody | D62: Améliorer l'efficacité de sa TPE à l'aide de l'IA | E62: 2026-07-13 | F62: 2026-07-18 | G62: Accepté | L62: A faire | M62: ='WEDOF - EXAMEN FINAL'!D62 -> A faire | N62: A faire | O62: A faire | P62: A faire | Q62: A faire | R62: A faire | S62: A faire | T62: A faire | U62: =TEXTJOIN(", ",TRUE(),IF($L62="A faire","Analyse du besoin",""),IF($M62="A faire","CV",""),IF($N62="A faire","Questionnaire/Test",""),IF($O62="A faire","Contrat",""),IF($P62="A faire","Convocation",""),IF($Q62="A faire","Eval intermediaire",""),IF($R62="A faire","Eval finale",""),IF($S62="A faire","Questionnaire satisfaction",""),IF($T62="A faire","Document de fin","")) -> Analyse du besoin, CV, Questionnaire/Test, Contrat, Convocation, Eval intermediaire, Eval finale, Questionnaire satisfaction, Document de fin | V62: =COUNTIF(L62:T62,"Fait")/9 -> 0 | W62: =IF($F62="","",IF(AND(TODAY()>=(DATEVALUE($F62)+1),$U62<>""),"A RELANCER : "&$U62,"")) -> A RELANCER : Analyse du besoin, CV, Questionnaire/Test, Contrat, Convocation, Eval intermediaire, Eval finale, Questionnaire satisfaction, Document de fin | X62: =IF(SUMPRODUCT(($B$2:$B$153=$B62)*($D$2:$D$153=$D62)*($E$2:$E$153=$E62)*($A$2:$A$153<>$A62))>0,"DOUBLON A VERIFIER","") | Y62: Oui
A63: Proforma Institut | B63: ARGOUBI Karim | C63: Djody | D63: Communiquer sur les réseaux sociaux pour promouvoir sa TPE | E63: 2026-07-20 | F63: 2026-07-25 | G63: Accepté | L63: A faire | M63: ='WEDOF - EXAMEN FINAL'!D63 -> A faire | N63: A faire | O63: A faire | P63: A faire | Q63: A faire | R63: A faire | S63: A faire | T63: A faire | U63: =TEXTJOIN(", ",TRUE(),IF($L63="A faire","Analyse du besoin",""),IF($M63="A faire","CV",""),IF($N63="A faire","Questionnaire/Test",""),IF($O63="A faire","Contrat",""),IF($P63="A faire","Convocation",""),IF($Q63="A faire","Eval intermediaire",""),IF($R63="A faire","Eval finale",""),IF($S63="A faire","Questionnaire satisfaction",""),IF($T63="A faire","Document de fin","")) -> Analyse du besoin, CV, Questionnaire/Test, Contrat, Convocation, Eval intermediaire, Eval finale, Questionnaire satisfaction, Document de fin | V63: =COUNTIF(L63:T63,"Fait")/9 -> 0 | W63: =IF($F63="","",IF(AND(TODAY()>=(DATEVALUE($F63)+1),$U63<>""),"A RELANCER : "&$U63,"")) | X63: =IF(SUMPRODUCT(($B$2:$B$153=$B63)*($D$2:$D$153=$D63)*($E$2:$E$153=$E63)*($A$2:$A$153<>$A63))>0,"DOUBLON A VERIFIER","") | Y63: Oui
... A81: Proforma Institut | B81: BENSAID Lahouari | C81: hak | D81: Réaliser les opérations comptables courantes d'une TPE | E81: 2026-08-10 | F81: 2026-08-15 | G81: en attente | L81: A faire | M81: ='WEDOF - EXAMEN FINAL'!D81 -> A faire | N81: A faire | O81: A faire | P81: A faire | Q81: A faire | R81: A faire | S81: A faire | T81: A faire | U81: =TEXTJOIN(", ",TRUE(),IF($L81="A faire","Analyse du besoin",""),IF($M81="A faire","CV",""),IF($N81="A faire","Questionnaire/Test",""),IF($O81="A faire","Contrat",""),IF($P81="A faire","Convocation",""),IF($Q81="A faire","Eval intermediaire",""),IF($R81="A faire","Eval finale",""),IF($S81="A faire","Questionnaire satisfaction",""),IF($T81="A faire","Document de fin","")) -> Analyse du besoin, CV, Questionnaire/Test, Contrat, Convocation, Eval intermediaire, Eval finale, Questionnaire satisfaction, Document de fin | V81: =COUNTIF(L81:T81,"Fait")/9 -> 0 | W81: =IF($F81="","",IF(AND(TODAY()>=(DATEVALUE($F81)+1),$U81<>""),"A RELANCER : "&$U81,"")) | X81: =IF(SUMPRODUCT(($B$2:$B$153=$B81)*($D$2:$D$153=$D81)*($E$2:$E$153=$E81)*($A$2:$A$153<>$A81))>0,"DOUBLON A VERIFIER","") | Y81: Oui
A82: Proskills Institut | B82: LAUZERO Jose | C82: Jules | D82: Améliorer l'efficacité de sa TPE à l'aide de l'IA | E82: 2026-05-18 | F82: 2026-05-22 | G82: payé | H82: 75 VMIN VIEUX CHEMIN D'ISTRES 13300 SALON DE PROVENCE | I82: jose.lauzero@gmail.com | J82: 0687216599 | L82: A faire | M82: ='WEDOF - EXAMEN FINAL'!D82 -> A faire | N82: A faire | O82: A faire | P82: A faire | Q82: A faire | R82: A faire | S82: A faire | T82: A faire | U82: =TEXTJOIN(", ",TRUE(),IF($L82="A faire","Analyse du besoin",""),IF($M82="A faire","CV",""),IF($N82="A faire","Questionnaire/Test",""),IF($O82="A faire","Contrat",""),IF($P82="A faire","Convocation",""),IF($Q82="A faire","Eval intermediaire",""),IF($R82="A faire","Eval finale",""),IF($S82="A faire","Questionnaire satisfaction",""),IF($T82="A faire","Document de fin","")) -> Analyse du besoin, CV, Questionnaire/Test, Contrat, Convocation, Eval intermediaire, Eval finale, Questionnaire satisfaction, Document de fin | V82: =COUNTIF(L82:T82,"Fait")/9 -> 0 | W82: =IF($F82="","",IF(AND(TODAY()>=(DATEVALUE($F82)+1),$U82<>""),"A RELANCER : "&$U82,"")) -> A RELANCER : Analyse du besoin, CV, Questionnaire/Test, Contrat, Convocation, Eval intermediaire, Eval finale, Questionnaire satisfaction, Document de fin | X82: =IF(SUMPRODUCT(($B$2:$B$153=$B82)*($D$2:$D$153=$D82)*($E$2:$E$153=$E82)*($A$2:$A$153<>$A82))>0,"DOUBLON A VERIFIER","") | Y82: Oui
A83: Proskills Institut | B83: LAUZERO Jose | C83: Jules | D83: Communiquer sur les réseaux sociaux pour promouvoir sa TPE | E83: 2026-05-25 | F83: 2026-05-30 | G83: payé | H83: 75 VMIN VIEUX CHEMIN D'ISTRES 13300 SALON DE PROVENCE | I83: jose.lauzero@gmail.com | L83: A faire | M83: ='WEDOF - EXAMEN FINAL'!D83 -> A faire | N83: A faire | O83: Fait | P83: A faire | Q83: A faire | R83: A faire | S83: A faire | T83: A faire | U83: =TEXTJOIN(", ",TRUE(),IF($L83="A faire","Analyse du besoin",""),IF($M83="A faire","CV",""),IF($N83="A faire","Questionnaire/Test",""),IF($O83="A faire","Contrat",""),IF($P83="A faire","Convocation",""),IF($Q83="A faire","Eval intermediaire",""),IF($R83="A faire","Eval finale",""),IF($S83="A faire","Questionnaire satisfaction",""),IF($T83="A faire","Document de fin","")) -> Analyse du besoin, CV, Questionnaire/Test, Convocation, Eval intermediaire, Eval finale, Questionnaire satisfaction, Document de fin | V83: =COUNTIF(L83:T83,"Fait")/9 -> 0.11111111 | W83: =IF($F83="","",IF(AND(TODAY()>=(DATEVALUE($F83)+1),$U83<>""),"A RELANCER : "&$U83,"")) -> A RELANCER : Analyse du besoin, CV, Questionnaire/Test, Convocation, Eval intermediaire, Eval finale, Questionnaire satisfaction, Document de fin | X83: =IF(SUMPRODUCT(($B$2:$B$153=$B83)*($D$2:$D$153=$D83)*($E$2:$E$153=$E83)*($A$2:$A$153<>$A83))>0,"DOUBLON A VERIFIER","") | Y83: Oui
A84: Proskills Institut | B84: LAUZERO Jose | C84: Jules | D84: Réaliser les opérations comptables courantes d'une TPE | E84: 2026-06-01 | F84: 2026-06-05 | G84: FACTURE | H84: 75 VMIN VIEUX CHEMIN D'ISTRES 13300 SALON DE PROVENCE | I84: jose.lauzero@gmail.com | L84: A faire | M84: ='WEDOF - EXAMEN FINAL'!D84 -> A faire | N84: A faire | O84: Fait | P84: A faire | Q84: A faire | R84: A faire | S84: A faire | T84: A faire | U84: =TEXTJOIN(", ",TRUE(),IF($L84="A faire","Analyse du besoin",""),IF($M84="A faire","CV",""),IF($N84="A faire","Questionnaire/Test",""),IF($O84="A faire","Contrat",""),IF($P84="A faire","Convocation",""),IF($Q84="A faire","Eval intermediaire",""),IF($R84="A faire","Eval finale",""),IF($S84="A faire","Questionnaire satisfaction",""),IF($T84="A faire","Document de fin","")) -> Analyse du besoin, CV, Questionnaire/Test, Convocation, Eval intermediaire, Eval finale, Questionnaire satisfaction, Document de fin | V84: =COUNTIF(L84:T84,"Fait")/9 -> 0.11111111 | W84: =IF($F84="","",IF(AND(TODAY()>=(DATEVALUE($F84)+1),$U84<>""),"A RELANCER : "&$U84,"")) -> A RELANCER : Analyse du besoin, CV, Questionnaire/Test, Convocation, Eval intermediaire, Eval finale, Questionnaire satisfaction, Document de fin | X84: =IF(SUMPRODUCT(($B$2:$B$153=$B84)*($D$2:$D$153=$D84)*($E$2:$E$153=$E84)*($A$2:$A$153<>$A84))>0,"DOUBLON A VERIFIER","") | Y84: Oui
A85: Proskills Institut | B85: MIEGE Cesar | C85: Jules | D85: Améliorer l'efficacité de sa TPE à l'aide de l'IA | E85: 2026-05-19 | F85: 2026-05-22 | G85: payé | H85: 75 VMIN Vieux chemin d’istres 13300 SALON DE PROVENCE | I85: cesarmege17@gmail.com | J85: 0686428862 | L85: A faire | M85: ='WEDOF - EXAMEN FINAL'!D85 -> A faire | N85: A faire | O85: Fait | P85: A faire | Q85: A faire | R85: A faire | S85: A faire | T85: A faire | U85: =TEXTJOIN(", ",TRUE(),IF($L85="A faire","Analyse du besoin",""),IF($M85="A faire","CV",""),IF($N85="A faire","Questionnaire/Test",""),IF($O85="A faire","Contrat",""),IF($P85="A faire","Convocation",""),IF($Q85="A faire","Eval intermediaire",""),IF($R85="A faire","Eval finale",""),IF($S85="A faire","Questionnaire satisfaction",""),IF($T85="A faire","Document de fin","")) -> Analyse du besoin, CV, Questionnaire/Test, Convocation, Eval intermediaire, Eval finale, Questionnaire satisfaction, Document de fin | V85: =COUNTIF(L85:T85,"Fait")/9 -> 0.11111111 | W85: =IF($F85="","",IF(AND(TODAY()>=(DATEVALUE($F85)+1),$U85<>""),"A RELANCER : "&$U85,"")) -> A RELANCER : Analyse du besoin, CV, Questionnaire/Test, Convocation, Eval intermediaire, Eval finale, Questionnaire satisfaction, Document de fin | X85: =IF(SUMPRODUCT(($B$2:$B$153=$B85)*($D$2:$D$153=$D85)*($E$2:$E$153=$E85)*($A$2:$A$153<>$A85))>0,"DOUBLON A VERIFIER","") | Y85: Oui
A86: Proskills Institut | B86: MIEGE Cesar | C86: Jules | D86: Communiquer sur les réseaux sociaux pour promouvoir sa TPE | E86: 2026-05-25 | F86: 2026-05-30 | G86: payé | H86: 75 VMIN Vieux chemin d’istres 13300 SALON DE PROVENCE | I86: cesarmege17@gmail.com | L86: A faire | M86: ='WEDOF - EXAMEN FINAL'!D86 -> A faire | N86: A faire | O86: Fait | P86: A faire | Q86: A faire | R86: A faire | S86: A faire | T86: A faire | U86: =TEXTJOIN(", ",TRUE(),IF($L86="A faire","Analyse du besoin",""),IF($M86="A faire","CV",""),IF($N86="A faire","Questionnaire/Test",""),IF($O86="A faire","Contrat",""),IF($P86="A faire","Convocation",""),IF($Q86="A faire","Eval intermediaire",""),IF($R86="A faire","Eval finale",""),IF($S86="A faire","Questionnaire satisfaction",""),IF($T86="A faire","Document de fin","")) -> Analyse du besoin, CV, Questionnaire/Test, Convocation, Eval intermediaire, Eval finale, Questionnaire satisfaction, Document de fin | V86: =COUNTIF(L86:T86,"Fait")/9 -> 0.11111111 | W86: =IF($F86="","",IF(AND(TODAY()>=(DATEVALUE($F86)+1),$U86<>""),"A RELANCER : "&$U86,"")) -> A RELANCER : Analyse du besoin, CV, Questionnaire/Test, Convocation, Eval intermediaire, Eval finale, Questionnaire satisfaction, Document de fin | X86: =IF(SUMPRODUCT(($B$2:$B$153=$B86)*($D$2:$D$153=$D86)*($E$2:$E$153=$E86)*($A$2:$A$153<>$A86))>0,"DOUBLON A VERIFIER","") | Y86: Oui
A87: Proskills Institut | B87: BONILLO Olivier | C87: Jules | D87: Améliorer l'efficacité de sa TPE à l'aide de l'IA | E87: 2026-05-19 | F87: 2026-05-22 | G87: payé | H87: 190 RTE Petite route des milles 13290 AIX EN PROVENCE | I87: gilly.oliver1810@gmail.com | J87: 0761243015 | L87: A faire | M87: ='WEDOF - EXAMEN FINAL'!D87 -> A faire | N87: A faire | O87: Fait | P87: A faire | Q87: A faire | R87: A faire | S87: A faire | T87: A faire | U87: =TEXTJOIN(", ",TRUE(),IF($L87="A faire","Analyse du besoin",""),IF($M87="A faire","CV",""),IF($N87="A faire","Questionnaire/Test",""),IF($O87="A faire","Contrat",""),IF($P87="A faire","Convocation",""),IF($Q87="A faire","Eval intermediaire",""),IF($R87="A faire","Eval finale",""),IF($S87="A faire","Questionnaire satisfaction",""),IF($T87="A faire","Document de fin","")) -> Analyse du besoin, CV, Questionnaire/Test, Convocation, Eval intermediaire, Eval finale, Questionnaire satisfaction, Document de fin | V87: =COUNTIF(L87:T87,"Fait")/9 -> 0.11111111 | W87: =IF($F87="","",IF(AND(TODAY()>=(DATEVALUE($F87)+1),$U87<>""),"A RELANCER : "&$U87,"")) -> A RELANCER : Analyse du besoin, CV, Questionnaire/Test, Convocation, Eval intermediaire, Eval finale, Questionnaire satisfaction, Document de fin | X87: =IF(SUMPRODUCT(($B$2:$B$153=$B87)*($D$2:$D$153=$D87)*($E$2:$E$153=$E87)*($A$2:$A$153<>$A87))>0,"DOUBLON A VERIFIER","") | Y87: Oui
A88: Proskills Institut | B88: BONILLO Olivier | C88: Jules | D88: Communiquer sur les réseaux sociaux pour promouvoir sa TPE | E88: 2026-05-25 | F88: 2026-05-30 | G88: payé | H88: 190 RTE Petite route des milles 13290 AIX EN PROVENCE | I88: gilly.oliver1810@gmail.com | L88: A faire | M88: ='WEDOF - EXAMEN FINAL'!D88 -> A faire | N88: A faire | O88: Fait | P88: A faire | Q88: A faire | R88: A faire | S88: A faire | T88: A faire | U88: =TEXTJOIN(", ",TRUE(),IF($L88="A faire","Analyse du besoin",""),IF($M88="A faire","CV",""),IF($N88="A faire","Questionnaire/Test",""),IF($O88="A faire","Contrat",""),IF($P88="A faire","Convocation",""),IF($Q88="A faire","Eval intermediaire",""),IF($R88="A faire","Eval finale",""),IF($S88="A faire","Questionnaire satisfaction",""),IF($T88="A faire","Document de fin","")) -> Analyse du besoin, CV, Questionnaire/Test, Convocation, Eval intermediaire, Eval finale, Questionnaire satisfaction, Document de fin | V88: =COUNTIF(L88:T88,"Fait")/9 -> 0.11111111 | W88: =IF($F88="","",IF(AND(TODAY()>=(DATEVALUE($F88)+1),$U88<>""),"A RELANCER : "&$U88,"")) -> A RELANCER : Analyse du besoin, CV, Questionnaire/Test, Convocation, Eval intermediaire, Eval finale, Questionnaire satisfaction, Document de fin | X88: =IF(SUMPRODUCT(($B$2:$B$153=$B88)*($D$2:$D$153=$D88)*($E$2:$E$153=$E88)*($A$2:$A$153<>$A88))>0,"DOUBLON A VERIFIER","") | Y88: Oui
A89: Proskills Institut | B89: GRAS Arnaud | C89: Djody | D89: Développer son activité avec l'intelligence artificielle | E89: 2026-05-25 | F89: 2026-06-05 | G89: payé | H89: 86 RUE francois mauriac 13010 MARSEILLE | I89: arnaudgras@hotmail.com | J89: 0649516676 | L89: A faire | M89: ='WEDOF - EXAMEN FINAL'!D89 -> A faire | N89: A faire | O89: A faire | P89: A faire | Q89: A faire | R89: A faire | S89: A faire | T89: A faire | U89: =TEXTJOIN(", ",TRUE(),IF($L89="A faire","Analyse du besoin",""),IF($M89="A faire","CV",""),IF($N89="A faire","Questionnaire/Test",""),IF($O89="A faire","Contrat",""),IF($P89="A faire","Convocation",""),IF($Q89="A faire","Eval intermediaire",""),IF($R89="A faire","Eval finale",""),IF($S89="A faire","Questionnaire satisfaction",""),IF($T89="A faire","Document de fin","")) -> Analyse du besoin, CV, Questionnaire/Test, Contrat, Convocation, Eval intermediaire, Eval finale, Questionnaire satisfaction, Document de fin | V89: =COUNTIF(L89:T89,"Fait")/9 -> 0 | W89: =IF($F89="","",IF(AND(TODAY()>=(DATEVALUE($F89)+1),$U89<>""),"A RELANCER : "&$U89,"")) -> A RELANCER : Analyse du besoin, CV, Questionnaire/Test, Contrat, Convocation, Eval intermediaire, Eval finale, Questionnaire satisfaction, Document de fin | X89: =IF(SUMPRODUCT(($B$2:$B$153=$B89)*($D$2:$D$153=$D89)*($E$2:$E$153=$E89)*($A$2:$A$153<>$A89))>0,"DOUBLON A VERIFIER","") | Y89: Oui
A90: Proskills Institut | B90: GUILLOU Mael | C90: Sabri | D90: Réaliser les opérations comptables courantes d'une TPE | E90: 2026-06-01 | F90: 2026-06-05 | G90: FACTURE | H90: 46 RUE Résidence du bosquet 13127 VITROLLES | I90: maelguilloux@yahoo.fr | J90: 0609475106 | L90: A faire | M90: ='WEDOF - EXAMEN FINAL'!D90 -> A faire | N90: A faire | O90: A faire | P90: A faire | Q90: A faire | R90: A faire | S90: A faire | T90: A faire | U90: =TEXTJOIN(", ",TRUE(),IF($L90="A faire","Analyse du besoin",""),IF($M90="A faire","CV",""),IF($N90="A faire","Questionnaire/Test",""),IF($O90="A faire","Contrat",""),IF($P90="A faire","Convocation",""),IF($Q90="A faire","Eval intermediaire",""),IF($R90="A faire","Eval finale",""),IF($S90="A faire","Questionnaire satisfaction",""),IF($T90="A faire","Document de fin","")) -> Analyse du besoin, CV, Questionnaire/Test, Contrat, Convocation, Eval intermediaire, Eval finale, Questionnaire satisfaction, Document de fin | V90: =COUNTIF(L90:T90,"Fait")/9 -> 0 | W90: =IF($F90="","",IF(AND(TODAY()>=(DATEVALUE($F90)+1),$U90<>""),"A RELANCER : "&$U90,"")) -> A RELANCER : Analyse du besoin, CV, Questionnaire/Test, Contrat, Convocation, Eval intermediaire, Eval finale, Questionnaire satisfaction, Document de fin | X90: =IF(SUMPRODUCT(($B$2:$B$153=$B90)*($D$2:$D$153=$D90)*($E$2:$E$153=$E90)*($A$2:$A$153<>$A90))>0,"DOUBLON A VERIFIER","") | Y90: Oui
A91: Proskills Institut | B91: GUILLOU Mael | C91: Sabri | D91: Communiquer sur les réseaux sociaux pour promouvoir sa TPE | E91: 2026-05-25 | F91: 2026-05-30 | G91: payé | H91: 46 RUE Résidence du bosquet 13127 VITROLLES | L91: A faire | M91: ='WEDOF - EXAMEN FINAL'!D91 -> A faire | N91: A faire | O91: A faire | P91: A faire | Q91: A faire | R91: A faire | S91: A faire | T91: A faire | U91: =TEXTJOIN(", ",TRUE(),IF($L91="A faire","Analyse du besoin",""),IF($M91="A faire","CV",""),IF($N91="A faire","Questionnaire/Test",""),IF($O91="A faire","Contrat",""),IF($P91="A faire","Convocation",""),IF($Q91="A faire","Eval intermediaire",""),IF($R91="A faire","Eval finale",""),IF($S91="A faire","Questionnaire satisfaction",""),IF($T91="A faire","Document de fin","")) -> Analyse du besoin, CV, Questionnaire/Test, Contrat, Convocation, Eval intermediaire, Eval finale, Questionnaire satisfaction, Document de fin | V91: =COUNTIF(L91:T91,"Fait")/9 -> 0 | W91: =IF($F91="","",IF(AND(TODAY()>=(DATEVALUE($F91)+1),$U91<>""),"A RELANCER : "&$U91,"")) -> A RELANCER : Analyse du besoin, CV, Questionnaire/Test, Contrat, Convocation, Eval intermediaire, Eval finale, Questionnaire satisfaction, Document de fin | X91: =IF(SUMPRODUCT(($B$2:$B$153=$B91)*($D$2:$D$153=$D91)*($E$2:$E$153=$E91)*($A$2:$A$153<>$A91))>0,"DOUBLON A VERIFIER","") | Y91: Oui
A92: Proskills Institut | B92: AMEUR Kamel | C92: Brian | D92: Réaliser les opérations comptables courantes d'une TPE | E92: 2026-06-01 | F92: 2026-06-05 | G92: Accepté | H92: 12 RES Rue Arthur lamendin 62430 SALLAUMINES | I92: kamel621@outlook.fr | J92: 0762665937 | L92: A faire | M92: ='WEDOF - EXAMEN FINAL'!D92 -> A faire | N92: A faire | O92: Fait | P92: A faire | Q92: A faire | R92: A faire | S92: A faire | T92: A faire | U92: =TEXTJOIN(", ",TRUE(),IF($L92="A faire","Analyse du besoin",""),IF($M92="A faire","CV",""),IF($N92="A faire","Questionnaire/Test",""),IF($O92="A faire","Contrat",""),IF($P92="A faire","Convocation",""),IF($Q92="A faire","Eval intermediaire",""),IF($R92="A faire","Eval finale",""),IF($S92="A faire","Questionnaire satisfaction",""),IF($T92="A faire","Document de fin","")) -> Analyse du besoin, CV, Questionnaire/Test, Convocation, Eval intermediaire, Eval finale, Questionnaire satisfaction, Document de fin | V92: =COUNTIF(L92:T92,"Fait")/9 -> 0.11111111 | W92: =IF($F92="","",IF(AND(TODAY()>=(DATEVALUE($F92)+1),$U92<>""),"A RELANCER : "&$U92,"")) -> A RELANCER : Analyse du besoin, CV, Questionnaire/Test, Convocation, Eval intermediaire, Eval finale, Questionnaire satisfaction, Document de fin | X92: =IF(SUMPRODUCT(($B$2:$B$153=$B92)*($D$2:$D$153=$D92)*($E$2:$E$153=$E92)*($A$2:$A$153<>$A92))>0,"DOUBLON A VERIFIER","") | Y92: Oui
A93: Proskills Institut | B93: AMEUR Kamel | C93: Brian | D93: Communiquer sur les réseaux sociaux pour promouvoir sa TPE | E93: 2026-05-25 | F93: 2026-05-30 | G93: payé | H93: 12 RES Rue Arthur lamendin 62430 SALLAUMINES | I93: kamel621@outlook.fr | L93: A faire | M93: ='WEDOF - EXAMEN FINAL'!D93 -> A faire | N93: A faire | O93: A faire | P93: A faire | Q93: A faire | R93: A faire | S93: A faire | T93: A faire | U93: =TEXTJOIN(", ",TRUE(),IF($L93="A faire","Analyse du besoin",""),IF($M93="A faire","CV",""),IF($N93="A faire","Questionnaire/Test",""),IF($O93="A faire","Contrat",""),IF($P93="A faire","Convocation",""),IF($Q93="A faire","Eval intermediaire",""),IF($R93="A faire","Eval finale",""),IF($S93="A faire","Questionnaire satisfaction",""),IF($T93="A faire","Document de fin","")) -> Analyse du besoin, CV, Questionnaire/Test, Contrat, Convocation, Eval intermediaire, Eval finale, Questionnaire satisfaction, Document de fin | V93: =COUNTIF(L93:T93,"Fait")/9 -> 0 | W93: =IF($F93="","",IF(AND(TODAY()>=(DATEVALUE($F93)+1),$U93<>""),"A RELANCER : "&$U93,"")) -> A RELANCER : Analyse du besoin, CV, Questionnaire/Test, Contrat, Convocation, Eval intermediaire, Eval finale, Questionnaire satisfaction, Document de fin | X93: =IF(SUMPRODUCT(($B$2:$B$153=$B93)*($D$2:$D$153=$D93)*($E$2:$E$153=$E93)*($A$2:$A$153<>$A93))>0,"DOUBLON A VERIFIER","") | Y93: Oui
A94: Proskills Institut | B94: LAUZERO Caroline | C94: Jules | D94: Améliorer l'efficacité de sa TPE à l'aide de l'IA | E94: 2026-06-08 | F94: 2026-06-13 | G94: FACTURE | H94: 75 VMIN VIEUX CHEMIN D'ISTRES 13300 SALON DE PROVENCE | I94: cclauzero@gmail.com | J94: 0647572721 | L94: A faire | M94: ='WEDOF - EXAMEN FINAL'!D94 -> A faire | N94: A faire | O94: A faire | P94: A faire | Q94: A faire | R94: A faire | S94: A faire | T94: A faire | U94: =TEXTJOIN(", ",TRUE(),IF($L94="A faire","Analyse du besoin",""),IF($M94="A faire","CV",""),IF($N94="A faire","Questionnaire/Test",""),IF($O94="A faire","Contrat",""),IF($P94="A faire","Convocation",""),IF($Q94="A faire","Eval intermediaire",""),IF($R94="A faire","Eval finale",""),IF($S94="A faire","Questionnaire satisfaction",""),IF($T94="A faire","Document de fin","")) -> Analyse du besoin, CV, Questionnaire/Test, Contrat, Convocation, Eval intermediaire, Eval finale, Questionnaire satisfaction, Document de fin | V94: =COUNTIF(L94:T94,"Fait")/9 -> 0 | W94: =IF($F94="","",IF(AND(TODAY()>=(DATEVALUE($F94)+1),$U94<>""),"A RELANCER : "&$U94,"")) -> A RELANCER : Analyse du besoin, CV, Questionnaire/Test, Contrat, Convocation, Eval intermediaire, Eval finale, Questionnaire satisfaction, Document de fin | X94: =IF(SUMPRODUCT(($B$2:$B$153=$B94)*($D$2:$D$153=$D94)*($E$2:$E$153=$E94)*($A$2:$A$153<>$A94))>0,"DOUBLON A VERIFIER","") | Y94: Oui
A95: Proskills Institut | B95: LAUZERO Caroline | C95: Jules | D95: Communiquer sur les réseaux sociaux pour promouvoir sa TPE | E95: 2026-05-25 | F95: 2026-05-30 | G95: payé | H95: 75 VMIN VIEUX CHEMIN D'ISTRES 13300 SALON DE PROVENCE | L95: A faire | M95: ='WEDOF - EXAMEN FINAL'!D95 -> A faire | N95: A faire | O95: A faire | P95: A faire | Q95: A faire | R95: A faire | S95: A faire | T95: A faire | U95: =TEXTJOIN(", ",TRUE(),IF($L95="A faire","Analyse du besoin",""),IF($M95="A faire","CV",""),IF($N95="A faire","Questionnaire/Test",""),IF($O95="A faire","Contrat",""),IF($P95="A faire","Convocation",""),IF($Q95="A faire","Eval intermediaire",""),IF($R95="A faire","Eval finale",""),IF($S95="A faire","Questionnaire satisfaction",""),IF($T95="A faire","Document de fin","")) -> Analyse du besoin, CV, Questionnaire/Test, Contrat, Convocation, Eval intermediaire, Eval finale, Questionnaire satisfaction, Document de fin | V95: =COUNTIF(L95:T95,"Fait")/9 -> 0 | W95: =IF($F95="","",IF(AND(TODAY()>=(DATEVALUE($F95)+1),$U95<>""),"A RELANCER : "&$U95,"")) -> A RELANCER : Analyse du besoin, CV, Questionnaire/Test, Contrat, Convocation, Eval intermediaire, Eval finale, Questionnaire satisfaction, Document de fin | X95: =IF(SUMPRODUCT(($B$2:$B$153=$B95)*($D$2:$D$153=$D95)*($E$2:$E$153=$E95)*($A$2:$A$153<>$A95))>0,"DOUBLON A VERIFIER","") | Y95: Oui
A96: Proskills Institut | B96: LAUZERO Caroline | C96: Jules | D96: Réaliser les opérations comptables courantes d'une TPE | E96: 2026-06-01 | F96: 2026-06-05 | G96: FACTURE | H96: 75 VMIN VIEUX CHEMIN D'ISTRES 13300 SALON DE PROVENCE | L96: A faire | M96: ='WEDOF - EXAMEN FINAL'!D96 -> A faire | N96: A faire | O96: A faire | P96: A faire | Q96: A faire | R96: A faire | S96: A faire | T96: A faire | U96: =TEXTJOIN(", ",TRUE(),IF($L96="A faire","Analyse du besoin",""),IF($M96="A faire","CV",""),IF($N96="A faire","Questionnaire/Test",""),IF($O96="A faire","Contrat",""),IF($P96="A faire","Convocation",""),IF($Q96="A faire","Eval intermediaire",""),IF($R96="A faire","Eval finale",""),IF($S96="A faire","Questionnaire satisfaction",""),IF($T96="A faire","Document de fin","")) -> Analyse du besoin, CV, Questionnaire/Test, Contrat, Convocation, Eval intermediaire, Eval finale, Questionnaire satisfaction, Document de fin | V96: =COUNTIF(L96:T96,"Fait")/9 -> 0 | W96: =IF($F96="","",IF(AND(TODAY()>=(DATEVALUE($F96)+1),$U96<>""),"A RELANCER : "&$U96,"")) -> A RELANCER : Analyse du besoin, CV, Questionnaire/Test, Contrat, Convocation, Eval intermediaire, Eval finale, Questionnaire satisfaction, Document de fin | X96: =IF(SUMPRODUCT(($B$2:$B$153=$B96)*($D$2:$D$153=$D96)*($E$2:$E$153=$E96)*($A$2:$A$153<>$A96))>0,"DOUBLON A VERIFIER","") | Y96: Oui
A97: Proskills Institut | B97: HUGARD Jose | C97: Brian | D97: Améliorer l'efficacité de sa TPE à l'aide de l'IA | E97: 2026-06-08 | F97: 2026-06-13 | G97: FACTURE | H97: 191 RUE Voisin 62110 HENIN BEAUMONT | I97: jose.hugard62110@gmail.com | J97: 0781329761 | L97: A faire | M97: ='WEDOF - EXAMEN FINAL'!D97 -> A faire | N97: A faire | O97: A faire | P97: A faire | Q97: A faire | R97: A faire | S97: A faire | T97: A faire | U97: =TEXTJOIN(", ",TRUE(),IF($L97="A faire","Analyse du besoin",""),IF($M97="A faire","CV",""),IF($N97="A faire","Questionnaire/Test",""),IF($O97="A faire","Contrat",""),IF($P97="A faire","Convocation",""),IF($Q97="A faire","Eval intermediaire",""),IF($R97="A faire","Eval finale",""),IF($S97="A faire","Questionnaire satisfaction",""),IF($T97="A faire","Document de fin","")) -> Analyse du besoin, CV, Questionnaire/Test, Contrat, Convocation, Eval intermediaire, Eval finale, Questionnaire satisfaction, Document de fin | V97: =COUNTIF(L97:T97,"Fait")/9 -> 0 | W97: =IF($F97="","",IF(AND(TODAY()>=(DATEVALUE($F97)+1),$U97<>""),"A RELANCER : "&$U97,"")) -> A RELANCER : Analyse du besoin, CV, Questionnaire/Test, Contrat, Convocation, Eval intermediaire, Eval finale, Questionnaire satisfaction, Document de fin | X97: =IF(SUMPRODUCT(($B$2:$B$153=$B97)*($D$2:$D$153=$D97)*($E$2:$E$153=$E97)*($A$2:$A$153<>$A97))>0,"DOUBLON A VERIFIER","") | Y97: Oui
A98: Proskills Institut | B98: HUGARD Jose | C98: Brian | D98: Communiquer sur les réseaux sociaux pour promouvoir sa TPE | E98: 2026-05-25 | F98: 2026-05-30 | G98: payé | H98: 191 RUE Voisin 62110 HENIN BEAUMONT | L98: A faire | M98: ='WEDOF - EXAMEN FINAL'!D98 -> A faire | N98: A faire | O98: A faire | P98: A faire | Q98: A faire | R98: A faire | S98: A faire | T98: A faire | U98: =TEXTJOIN(", ",TRUE(),IF($L98="A faire","Analyse du besoin",""),IF($M98="A faire","CV",""),IF($N98="A faire","Questionnaire/Test",""),IF($O98="A faire","Contrat",""),IF($P98="A faire","Convocation",""),IF($Q98="A faire","Eval intermediaire",""),IF($R98="A faire","Eval finale",""),IF($S98="A faire","Questionnaire satisfaction",""),IF($T98="A faire","Document de fin","")) -> Analyse du besoin, CV, Questionnaire/Test, Contrat, Convocation, Eval intermediaire, Eval finale, Questionnaire satisfaction, Document de fin | V98: =COUNTIF(L98:T98,"Fait")/9 -> 0 | W98: =IF($F98="","",IF(AND(TODAY()>=(DATEVALUE($F98)+1),$U98<>""),"A RELANCER : "&$U98,"")) -> A RELANCER : Analyse du besoin, CV, Questionnaire/Test, Contrat, Convocation, Eval intermediaire, Eval finale, Questionnaire satisfaction, Document de fin | X98: =IF(SUMPRODUCT(($B$2:$B$153=$B98)*($D$2:$D$153=$D98)*($E$2:$E$153=$E98)*($A$2:$A$153<>$A98))>0,"DOUBLON A VERIFIER","") | Y98: Oui
A99: Proskills Institut | B99: HUGARD Jose | C99: Brian | D99: Réaliser les opérations comptables courantes d'une TPE | E99: 2026-06-01 | F99: 2026-06-05 | G99: FACTURE | H99: 191 RUE Voisin 62110 HENIN BEAUMONT | L99: A faire | M99: ='WEDOF - EXAMEN FINAL'!D99 -> A faire | N99: A faire | O99: A faire | P99: A faire | Q99: A faire | R99: A faire | S99: A faire | T99: A faire | U99: =TEXTJOIN(", ",TRUE(),IF($L99="A faire","Analyse du besoin",""),IF($M99="A faire","CV",""),IF($N99="A faire","Questionnaire/Test",""),IF($O99="A faire","Contrat",""),IF($P99="A faire","Convocation",""),IF($Q99="A faire","Eval intermediaire",""),IF($R99="A faire","Eval finale",""),IF($S99="A faire","Questionnaire satisfaction",""),IF($T99="A faire","Document de fin","")) -> Analyse du besoin, CV, Questionnaire/Test, Contrat, Convocation, Eval intermediaire, Eval finale, Questionnaire satisfaction, Document de fin | V99: =COUNTIF(L99:T99,"Fait")/9 -> 0 | W99: =IF($F99="","",IF(AND(TODAY()>=(DATEVALUE($F99)+1),$U99<>""),"A RELANCER : "&$U99,"")) -> A RELANCER : Analyse du besoin, CV, Questionnaire/Test, Contrat, Convocation, Eval intermediaire, Eval finale, Questionnaire satisfaction, Document de fin | X99: =IF(SUMPRODUCT(($B$2:$B$153=$B99)*($D$2:$D$153=$D99)*($E$2:$E$153=$E99)*($A$2:$A$153<>$A99))>0,"DOUBLON A VERIFIER","") | Y99: Oui
A100: Proskills Institut | B100: GILLY Laurent | C100: Jules | D100: Améliorer l'efficacité de sa TPE à l'aide de l'IA | E100: 2026-06-08 | F100: 2026-06-13 | G100: FACTURE | H100: 190 RTE petite routes des milles 13290 AIX EN PROVENCE | I100: laurent@les-garcons-formations.fr | J100: 0761193855 | L100: A faire | M100: ='WEDOF - EXAMEN FINAL'!D100 -> A faire | N100: A faire | O100: A faire | P100: A faire | Q100: A faire | R100: A faire | S100: A faire | T100: A faire | U100: =TEXTJOIN(", ",TRUE(),IF($L100="A faire","Analyse du besoin",""),IF($M100="A faire","CV",""),IF($N100="A faire","Questionnaire/Test",""),IF($O100="A faire","Contrat",""),IF($P100="A faire","Convocation",""),IF($Q100="A faire","Eval intermediaire",""),IF($R100="A faire","Eval finale",""),IF($S100="A faire","Questionnaire satisfaction",""),IF($T100="A faire","Document de fin","")) -> Analyse du besoin, CV, Questionnaire/Test, Contrat, Convocation, Eval intermediaire, Eval finale, Questionnaire satisfaction, Document de fin | V100: =COUNTIF(L100:T100,"Fait")/9 -> 0 | W100: =IF($F100="","",IF(AND(TODAY()>=(DATEVALUE($F100)+1),$U100<>""),"A RELANCER : "&$U100,"")) -> A RELANCER : Analyse du besoin, CV, Questionnaire/Test, Contrat, Convocation, Eval intermediaire, Eval finale, Questionnaire satisfaction, Document de fin | X100: =IF(SUMPRODUCT(($B$2:$B$153=$B100)*($D$2:$D$153=$D100)*($E$2:$E$153=$E100)*($A$2:$A$153<>$A100))>0,"DOUBLON A VERIFIER","") | Y100: Oui
A101: Proskills Institut | B101: GILLY Laurent | C101: Jules | D101: Communiquer sur les réseaux sociaux pour promouvoir sa TPE | E101: 2026-05-25 | F101: 2026-05-30 | G101: payé | H101: 190 RTE petite routes des milles 13290 AIX EN PROVENCE | L101: A faire | M101: ='WEDOF - EXAMEN FINAL'!D101 -> A faire | N101: A faire | O101: A faire | P101: A faire | Q101: A faire | R101: A faire | S101: A faire | T101: A faire | U101: =TEXTJOIN(", ",TRUE(),IF($L101="A faire","Analyse du besoin",""),IF($M101="A faire","CV",""),IF($N101="A faire","Questionnaire/Test",""),IF($O101="A faire","Contrat",""),IF($P101="A faire","Convocation",""),IF($Q101="A faire","Eval intermediaire",""),IF($R101="A faire","Eval finale",""),IF($S101="A faire","Questionnaire satisfaction",""),IF($T101="A faire","Document de fin","")) -> Analyse du besoin, CV, Questionnaire/Test, Contrat, Convocation, Eval intermediaire, Eval finale, Questionnaire satisfaction, Document de fin | V101: =COUNTIF(L101:T101,"Fait")/9 -> 0 | W101: =IF($F101="","",IF(AND(TODAY()>=(DATEVALUE($F101)+1),$U101<>""),"A RELANCER : "&$U101,"")) -> A RELANCER : Analyse du besoin, CV, Questionnaire/Test, Contrat, Convocation, Eval intermediaire, Eval finale, Questionnaire satisfaction, Document de fin | X101: =IF(SUMPRODUCT(($B$2:$B$153=$B101)*($D$2:$D$153=$D101)*($E$2:$E$153=$E101)*($A$2:$A$153<>$A101))>0,"DOUBLON A VERIFIER","") | Y101: Oui
A102: Proskills Institut | B102: Mona Bahar | C102: frere karim | D102: Développer son activité avec l'intelligence artificielle | E102: 2026-05-26 | F102: 2026-06-05 | G102: payé | H102: 2 RUE André Calvin 13700 MARIGNANE | I102: monabahar@outlook.fr | J102: 0783626910 | L102: A faire | M102: ='WEDOF - EXAMEN FINAL'!D102 -> A faire | N102: A faire | O102: A faire | P102: A faire | Q102: A faire | R102: A faire | S102: A faire | T102: A faire | U102: =TEXTJOIN(", ",TRUE(),IF($L102="A faire","Analyse du besoin",""),IF($M102="A faire","CV",""),IF($N102="A faire","Questionnaire/Test",""),IF($O102="A faire","Contrat",""),IF($P102="A faire","Convocation",""),IF($Q102="A faire","Eval intermediaire",""),IF($R102="A faire","Eval finale",""),IF($S102="A faire","Questionnaire satisfaction",""),IF($T102="A faire","Document de fin","")) -> Analyse du besoin, CV, Questionnaire/Test, Contrat, Convocation, Eval intermediaire, Eval finale, Questionnaire satisfaction, Document de fin | V102: =COUNTIF(L102:T102,"Fait")/9 -> 0 | W102: =IF($F102="","",IF(AND(TODAY()>=(DATEVALUE($F102)+1),$U102<>""),"A RELANCER : "&$U102,"")) -> A RELANCER : Analyse du besoin, CV, Questionnaire/Test, Contrat, Convocation, Eval intermediaire, Eval finale, Questionnaire satisfaction, Document de fin | X102: =IF(SUMPRODUCT(($B$2:$B$153=$B102)*($D$2:$D$153=$D102)*($E$2:$E$153=$E102)*($A$2:$A$153<>$A102))>0,"DOUBLON A VERIFIER","") | Y102: Oui
A103: Proskills Institut | B103: REIG Stephane | C103: GRAS | D103: Améliorer l'efficacité de sa TPE à l'aide de l'IA | E103: 2026-06-08 | F103: 2026-06-13 | G103: FACTURE | H103: 15 BD du vaissaux 13009 MARSEILLE | I103: stephane.reig1@orange.fr | J103: 0615817731 | L103: A faire | M103: ='WEDOF - EXAMEN FINAL'!D103 -> A faire | N103: A faire | O103: A faire | P103: A faire | Q103: A faire | R103: A faire | S103: A faire | T103: A faire | U103: =TEXTJOIN(", ",TRUE(),IF($L103="A faire","Analyse du besoin",""),IF($M103="A faire","CV",""),IF($N103="A faire","Questionnaire/Test",""),IF($O103="A faire","Contrat",""),IF($P103="A faire","Convocation",""),IF($Q103="A faire","Eval intermediaire",""),IF($R103="A faire","Eval finale",""),IF($S103="A faire","Questionnaire satisfaction",""),IF($T103="A faire","Document de fin","")) -> Analyse du besoin, CV, Questionnaire/Test, Contrat, Convocation, Eval intermediaire, Eval finale, Questionnaire satisfaction, Document de fin | V103: =COUNTIF(L103:T103,"Fait")/9 -> 0 | W103: =IF($F103="","",IF(AND(TODAY()>=(DATEVALUE($F103)+1),$U103<>""),"A RELANCER : "&$U103,"")) -> A RELANCER : Analyse du besoin, CV, Questionnaire/Test, Contrat, Convocation, Eval intermediaire, Eval finale, Questionnaire satisfaction, Document de fin | X103: =IF(SUMPRODUCT(($B$2:$B$153=$B103)*($D$2:$D$153=$D103)*($E$2:$E$153=$E103)*($A$2:$A$153<>$A103))>0,"DOUBLON A VERIFIER","") | Y103: Oui
A104: Proskills Institut | B104: REIG Stephane | C104: GRAS | D104: Communiquer sur les réseaux sociaux pour promouvoir sa TPE | E104: 2026-06-15 | F104: 2026-06-20 | G104: FACTURE | H104: 15 BD du vaissaux 13009 MARSEILLE | L104: A faire | M104: ='WEDOF - EXAMEN FINAL'!D104 -> A faire | N104: A faire | O104: A faire | P104: A faire | Q104: A faire | R104: A faire | S104: A faire | T104: A faire | U104: =TEXTJOIN(", ",TRUE(),IF($L104="A faire","Analyse du besoin",""),IF($M104="A faire","CV",""),IF($N104="A faire","Questionnaire/Test",""),IF($O104="A faire","Contrat",""),IF($P104="A faire","Convocation",""),IF($Q104="A faire","Eval intermediaire",""),IF($R104="A faire","Eval finale",""),IF($S104="A faire","Questionnaire satisfaction",""),IF($T104="A faire","Document de fin","")) -> Analyse du besoin, CV, Questionnaire/Test, Contrat, Convocation, Eval intermediaire, Eval finale, Questionnaire satisfaction, Document de fin | V104: =COUNTIF(L104:T104,"Fait")/9 -> 0 | W104: =IF($F104="","",IF(AND(TODAY()>=(DATEVALUE($F104)+1),$U104<>""),"A RELANCER : "&$U104,"")) -> A RELANCER : Analyse du besoin, CV, Questionnaire/Test, Contrat, Convocation, Eval intermediaire, Eval finale, Questionnaire satisfaction, Document de fin | X104: =IF(SUMPRODUCT(($B$2:$B$153=$B104)*($D$2:$D$153=$D104)*($E$2:$E$153=$E104)*($A$2:$A$153<>$A104))>0,"DOUBLON A VERIFIER","") | Y104: Oui
A105: Proskills Institut | B105: BAHAR Achraf | C105: frere karim | D105: Améliorer l'efficacité de sa TPE à l'aide de l'IA | E105: 2026-06-08 | F105: 2026-06-13 | G105: FACTURE | H105: 9 IMP Impasse du gourg 13127 VITROLLES | I105: achraf.baharp@gmail.com | J105: 0668689045 | L105: A faire | M105: ='WEDOF - EXAMEN FINAL'!D105 -> A faire | N105: A faire | O105: A faire | P105: A faire | Q105: A faire | R105: A faire | S105: A faire | T105: A faire | U105: =TEXTJOIN(", ",TRUE(),IF($L105="A faire","Analyse du besoin",""),IF($M105="A faire","CV",""),IF($N105="A faire","Questionnaire/Test",""),IF($O105="A faire","Contrat",""),IF($P105="A faire","Convocation",""),IF($Q105="A faire","Eval intermediaire",""),IF($R105="A faire","Eval finale",""),IF($S105="A faire","Questionnaire satisfaction",""),IF($T105="A faire","Document de fin","")) -> Analyse du besoin, CV, Questionnaire/Test, Contrat, Convocation, Eval intermediaire, Eval finale, Questionnaire satisfaction, Document de fin | V105: =COUNTIF(L105:T105,"Fait")/9 -> 0 | W105: =IF($F105="","",IF(AND(TODAY()>=(DATEVALUE($F105)+1),$U105<>""),"A RELANCER : "&$U105,"")) -> A RELANCER : Analyse du besoin, CV, Questionnaire/Test, Contrat, Convocation, Eval intermediaire, Eval finale, Questionnaire satisfaction, Document de fin | X105: =IF(SUMPRODUCT(($B$2:$B$153=$B105)*($D$2:$D$153=$D105)*($E$2:$E$153=$E105)*($A$2:$A$153<>$A105))>0,"DOUBLON A VERIFIER","") | Y105: Oui
A106: Proskills Institut | B106: BAHAR Achraf | C106: frere karim | D106: Communiquer sur les réseaux sociaux pour promouvoir sa TPE | E106: 2026-06-15 | F106: 2026-06-20 | G106: FACTURE | H106: 9 IMP Impasse du gourg 13127 VITROLLES | L106: A faire | M106: ='WEDOF - EXAMEN FINAL'!D106 -> A faire | N106: A faire | O106: A faire | P106: A faire | Q106: A faire | R106: A faire | S106: A faire | T106: A faire | U106: =TEXTJOIN(", ",TRUE(),IF($L106="A faire","Analyse du besoin",""),IF($M106="A faire","CV",""),IF($N106="A faire","Questionnaire/Test",""),IF($O106="A faire","Contrat",""),IF($P106="A faire","Convocation",""),IF($Q106="A faire","Eval intermediaire",""),IF($R106="A faire","Eval finale",""),IF($S106="A faire","Questionnaire satisfaction",""),IF($T106="A faire","Document de fin","")) -> Analyse du besoin, CV, Questionnaire/Test, Contrat, Convocation, Eval intermediaire, Eval finale, Questionnaire satisfaction, Document de fin | V106: =COUNTIF(L106:T106,"Fait")/9 -> 0 | W106: =IF($F106="","",IF(AND(TODAY()>=(DATEVALUE($F106)+1),$U106<>""),"A RELANCER : "&$U106,"")) -> A RELANCER : Analyse du besoin, CV, Questionnaire/Test, Contrat, Convocation, Eval intermediaire, Eval finale, Questionnaire satisfaction, Document de fin | X106: =IF(SUMPRODUCT(($B$2:$B$153=$B106)*($D$2:$D$153=$D106)*($E$2:$E$153=$E106)*($A$2:$A$153<>$A106))>0,"DOUBLON A VERIFIER","") | Y106: Oui
A107: Proskills Institut | B107: LAREF Faouzi | C107: Nedjma | D107: Améliorer l'efficacité de sa TPE à l'aide de l'IA | E107: 2026-06-08 | F107: 2026-06-13 | G107: FACTURE | H107: 350 BD National 13003 MARSEILLE | I107: laref.ferroudja@yahoo.fr | J107: 0634554074 | L107: A faire | M107: ='WEDOF - EXAMEN FINAL'!D107 -> A faire | N107: A faire | O107: A faire | P107: A faire | Q107: A faire | R107: A faire | S107: A faire | T107: A faire | U107: =TEXTJOIN(", ",TRUE(),IF($L107="A faire","Analyse du besoin",""),IF($M107="A faire","CV",""),IF($N107="A faire","Questionnaire/Test",""),IF($O107="A faire","Contrat",""),IF($P107="A faire","Convocation",""),IF($Q107="A faire","Eval intermediaire",""),IF($R107="A faire","Eval finale",""),IF($S107="A faire","Questionnaire satisfaction",""),IF($T107="A faire","Document de fin","")) -> Analyse du besoin, CV, Questionnaire/Test, Contrat, Convocation, Eval intermediaire, Eval finale, Questionnaire satisfaction, Document de fin | V107: =COUNTIF(L107:T107,"Fait")/9 -> 0 | W107: =IF($F107="","",IF(AND(TODAY()>=(DATEVALUE($F107)+1),$U107<>""),"A RELANCER : "&$U107,"")) -> A RELANCER : Analyse du besoin, CV, Questionnaire/Test, Contrat, Convocation, Eval intermediaire, Eval finale, Questionnaire satisfaction, Document de fin | X107: =IF(SUMPRODUCT(($B$2:$B$153=$B107)*($D$2:$D$153=$D107)*($E$2:$E$153=$E107)*($A$2:$A$153<>$A107))>0,"DOUBLON A VERIFIER","") | Y107: Oui
A108: Proskills Institut | B108: LAREF Faouzi | C108: Nedjma | D108: Communiquer sur les réseaux sociaux pour promouvoir sa TPE | E108: 2026-06-15 | F108: 2026-06-20 | G108: FACTURE | H108: 350 BD National 13003 MARSEILLE | L108: A faire | M108: ='WEDOF - EXAMEN FINAL'!D108 -> A faire | N108: A faire | O108: A faire | P108: A faire | Q108: A faire | R108: A faire | S108: A faire | T108: A faire | U108: =TEXTJOIN(", ",TRUE(),IF($L108="A faire","Analyse du besoin",""),IF($M108="A faire","CV",""),IF($N108="A faire","Questionnaire/Test",""),IF($O108="A faire","Contrat",""),IF($P108="A faire","Convocation",""),IF($Q108="A faire","Eval intermediaire",""),IF($R108="A faire","Eval finale",""),IF($S108="A faire","Questionnaire satisfaction",""),IF($T108="A faire","Document de fin","")) -> Analyse du besoin, CV, Questionnaire/Test, Contrat, Convocation, Eval intermediaire, Eval finale, Questionnaire satisfaction, Document de fin | V108: =COUNTIF(L108:T108,"Fait")/9 -> 0 | W108: =IF($F108="","",IF(AND(TODAY()>=(DATEVALUE($F108)+1),$U108<>""),"A RELANCER : "&$U108,"")) -> A RELANCER : Analyse du besoin, CV, Questionnaire/Test, Contrat, Convocation, Eval intermediaire, Eval finale, Questionnaire satisfaction, Document de fin | X108: =IF(SUMPRODUCT(($B$2:$B$153=$B108)*($D$2:$D$153=$D108)*($E$2:$E$153=$E108)*($A$2:$A$153<>$A108))>0,"DOUBLON A VERIFIER","") | Y108: Oui
A109: Proskills Institut | B109: LAREF Faouzi | C109: Nedjma | D109: Réaliser les opérations comptables courantes d'une TPE | E109: 2026-06-01 | F109: 2026-06-05 | G109: FACTURE | H109: 350 BD National 13003 MARSEILLE | L109: A faire | M109: ='WEDOF - EXAMEN FINAL'!D109 -> A faire | N109: A faire | O109: A faire | P109: A faire | Q109: A faire | R109: A faire | S109: A faire | T109: A faire | U109: =TEXTJOIN(", ",TRUE(),IF($L109="A faire","Analyse du besoin",""),IF($M109="A faire","CV",""),IF($N109="A faire","Questionnaire/Test",""),IF($O109="A faire","Contrat",""),IF($P109="A faire","Convocation",""),IF($Q109="A faire","Eval intermediaire",""),IF($R109="A faire","Eval finale",""),IF($S109="A faire","Questionnaire satisfaction",""),IF($T109="A faire","Document de fin","")) -> Analyse du besoin, CV, Questionnaire/Test, Contrat, Convocation, Eval intermediaire, Eval finale, Questionnaire satisfaction, Document de fin | V109: =COUNTIF(L109:T109,"Fait")/9 -> 0 | W109: =IF($F109="","",IF(AND(TODAY()>=(DATEVALUE($F109)+1),$U109<>""),"A RELANCER : "&$U109,"")) -> A RELANCER : Analyse du besoin, CV, Questionnaire/Test, Contrat, Convocation, Eval intermediaire, Eval finale, Questionnaire satisfaction, Document de fin | X109: =IF(SUMPRODUCT(($B$2:$B$153=$B109)*($D$2:$D$153=$D109)*($E$2:$E$153=$E109)*($A$2:$A$153<>$A109))>0,"DOUBLON A VERIFIER","") | Y109: Oui
A110: Proskills Institut | B110: SCHIANCHI Emmanuel | C110: Djody | D110: Améliorer l'efficacité de sa TPE à l'aide de l'IA | E110: 2026-06-08 | F110: 2026-06-13 | G110: FACTURE | H110: 24 RUE Marengo 13006 MARSEILLE | I110: manu.schianchi@gmail.com | J110: 0666482176 | L110: A faire | M110: ='WEDOF - EXAMEN FINAL'!D110 -> A faire | N110: A faire | O110: A faire | P110: A faire | Q110: A faire | R110: A faire | S110: A faire | T110: A faire | U110: =TEXTJOIN(", ",TRUE(),IF($L110="A faire","Analyse du besoin",""),IF($M110="A faire","CV",""),IF($N110="A faire","Questionnaire/Test",""),IF($O110="A faire","Contrat",""),IF($P110="A faire","Convocation",""),IF($Q110="A faire","Eval intermediaire",""),IF($R110="A faire","Eval finale",""),IF($S110="A faire","Questionnaire satisfaction",""),IF($T110="A faire","Document de fin","")) -> Analyse du besoin, CV, Questionnaire/Test, Contrat, Convocation, Eval intermediaire, Eval finale, Questionnaire satisfaction, Document de fin | V110: =COUNTIF(L110:T110,"Fait")/9 -> 0 | W110: =IF($F110="","",IF(AND(TODAY()>=(DATEVALUE($F110)+1),$U110<>""),"A RELANCER : "&$U110,"")) -> A RELANCER : Analyse du besoin, CV, Questionnaire/Test, Contrat, Convocation, Eval intermediaire, Eval finale, Questionnaire satisfaction, Document de fin | X110: =IF(SUMPRODUCT(($B$2:$B$153=$B110)*($D$2:$D$153=$D110)*($E$2:$E$153=$E110)*($A$2:$A$153<>$A110))>0,"DOUBLON A VERIFIER","") | Y110: Oui
A111: Proskills Institut | B111: SCHIANCHI Emmanuel | C111: Djody | D111: Communiquer sur les réseaux sociaux pour promouvoir sa TPE | E111: 2026-06-15 | F111: 2026-06-20 | G111: FACTURE | H111: 24 RUE Marengo 13006 MARSEILLE | L111: A faire | M111: ='WEDOF - EXAMEN FINAL'!D111 -> A faire | N111: A faire | O111: A faire | P111: A faire | Q111: A faire | R111: A faire | S111: A faire | T111: A faire | U111: =TEXTJOIN(", ",TRUE(),IF($L111="A faire","Analyse du besoin",""),IF($M111="A faire","CV",""),IF($N111="A faire","Questionnaire/Test",""),IF($O111="A faire","Contrat",""),IF($P111="A faire","Convocation",""),IF($Q111="A faire","Eval intermediaire",""),IF($R111="A faire","Eval finale",""),IF($S111="A faire","Questionnaire satisfaction",""),IF($T111="A faire","Document de fin","")) -> Analyse du besoin, CV, Questionnaire/Test, Contrat, Convocation, Eval intermediaire, Eval finale, Questionnaire satisfaction, Document de fin | V111: =COUNTIF(L111:T111,"Fait")/9 -> 0 | W111: =IF($F111="","",IF(AND(TODAY()>=(DATEVALUE($F111)+1),$U111<>""),"A RELANCER : "&$U111,"")) -> A RELANCER : Analyse du besoin, CV, Questionnaire/Test, Contrat, Convocation, Eval intermediaire, Eval finale, Questionnaire satisfaction, Document de fin | X111: =IF(SUMPRODUCT(($B$2:$B$153=$B111)*($D$2:$D$153=$D111)*($E$2:$E$153=$E111)*($A$2:$A$153<>$A111))>0,"DOUBLON A VERIFIER","") | Y111: Oui
A112: Proskills Institut | B112: SCHIANCHI Emmanuel | C112: Djody | D112: Réaliser les opérations comptables courantes d'une TPE | E112: 2026-06-01 | F112: 2026-06-05 | G112: FACTURE | H112: 24 RUE Marengo 13006 MARSEILLE | L112: A faire | M112: ='WEDOF - EXAMEN FINAL'!D112 -> A faire | N112: A faire | O112: A faire | P112: A faire | Q112: A faire | R112: A faire | S112: A faire | T112: A faire | U112: =TEXTJOIN(", ",TRUE(),IF($L112="A faire","Analyse du besoin",""),IF($M112="A faire","CV",""),IF($N112="A faire","Questionnaire/Test",""),IF($O112="A faire","Contrat",""),IF($P112="A faire","Convocation",""),IF($Q112="A faire","Eval intermediaire",""),IF($R112="A faire","Eval finale",""),IF($S112="A faire","Questionnaire satisfaction",""),IF($T112="A faire","Document de fin","")) -> Analyse du besoin, CV, Questionnaire/Test, Contrat, Convocation, Eval intermediaire, Eval finale, Questionnaire satisfaction, Document de fin | V112: =COUNTIF(L112:T112,"Fait")/9 -> 0 | W112: =IF($F112="","",IF(AND(TODAY()>=(DATEVALUE($F112)+1),$U112<>""),"A RELANCER : "&$U112,"")) -> A RELANCER : Analyse du besoin, CV, Questionnaire/Test, Contrat, Convocation, Eval intermediaire, Eval finale, Questionnaire satisfaction, Document de fin | X112: =IF(SUMPRODUCT(($B$2:$B$153=$B112)*($D$2:$D$153=$D112)*($E$2:$E$153=$E112)*($A$2:$A$153<>$A112))>0,"DOUBLON A VERIFIER","") | Y112: Oui
A113: Proskills Institut | B113: Yasmina Bessa | C113: Jean | D113: Améliorer l'efficacité de sa TPE à l'aide de l'IA | E113: 2026-06-15 | F113: 2026-06-20 | G113: FACTURE | H113: 52 BD Louis villecroze 13014 MARSEILLE | I113: rekika.yasmina@gmail.com | J113: 0669596133 | L113: A faire | M113: ='WEDOF - EXAMEN FINAL'!D113 -> A faire | N113: A faire | O113: A faire | P113: A faire | Q113: A faire | R113: A faire | S113: A faire | T113: A faire | U113: =TEXTJOIN(", ",TRUE(),IF($L113="A faire","Analyse du besoin",""),IF($M113="A faire","CV",""),IF($N113="A faire","Questionnaire/Test",""),IF($O113="A faire","Contrat",""),IF($P113="A faire","Convocation",""),IF($Q113="A faire","Eval intermediaire",""),IF($R113="A faire","Eval finale",""),IF($S113="A faire","Questionnaire satisfaction",""),IF($T113="A faire","Document de fin","")) -> Analyse du besoin, CV, Questionnaire/Test, Contrat, Convocation, Eval intermediaire, Eval finale, Questionnaire satisfaction, Document de fin | V113: =COUNTIF(L113:T113,"Fait")/9 -> 0 | W113: =IF($F113="","",IF(AND(TODAY()>=(DATEVALUE($F113)+1),$U113<>""),"A RELANCER : "&$U113,"")) -> A RELANCER : Analyse du besoin, CV, Questionnaire/Test, Contrat, Convocation, Eval intermediaire, Eval finale, Questionnaire satisfaction, Document de fin | X113: =IF(SUMPRODUCT(($B$2:$B$153=$B113)*($D$2:$D$153=$D113)*($E$2:$E$153=$E113)*($A$2:$A$153<>$A113))>0,"DOUBLON A VERIFIER","") | Y113: Oui
A114: Proskills Institut | B114: Yasmina Bessa | C114: Jean | D114: Communiquer sur les réseaux sociaux pour promouvoir sa TPE | E114: 2026-06-29 | F114: 2026-07-04 | G114: FACTURE | H114: 52 BD Louis villecroze 13014 MARSEILLE | L114: A faire | M114: ='WEDOF - EXAMEN FINAL'!D114 -> A faire | N114: A faire | O114: A faire | P114: A faire | Q114: A faire | R114: A faire | S114: A faire | T114: A faire | U114: =TEXTJOIN(", ",TRUE(),IF($L114="A faire","Analyse du besoin",""),IF($M114="A faire","CV",""),IF($N114="A faire","Questionnaire/Test",""),IF($O114="A faire","Contrat",""),IF($P114="A faire","Convocation",""),IF($Q114="A faire","Eval intermediaire",""),IF($R114="A faire","Eval finale",""),IF($S114="A faire","Questionnaire satisfaction",""),IF($T114="A faire","Document de fin","")) -> Analyse du besoin, CV, Questionnaire/Test, Contrat, Convocation, Eval intermediaire, Eval finale, Questionnaire satisfaction, Document de fin | V114: =COUNTIF(L114:T114,"Fait")/9 -> 0 | W114: =IF($F114="","",IF(AND(TODAY()>=(DATEVALUE($F114)+1),$U114<>""),"A RELANCER : "&$U114,"")) -> A RELANCER : Analyse du besoin, CV, Questionnaire/Test, Contrat, Convocation, Eval intermediaire, Eval finale, Questionnaire satisfaction, Document de fin | X114: =IF(SUMPRODUCT(($B$2:$B$153=$B114)*($D$2:$D$153=$D114)*($E$2:$E$153=$E114)*($A$2:$A$153<>$A114))>0,"DOUBLON A VERIFIER","") | Y114: Oui
A115: Proskills Institut | B115: Lyess Mohamed | C115: Jean | D115: Développer son activité avec l'intelligence artificielle | E115: 2026-06-29 | F115: 2026-07-04 | G115: FACTURE | H115: 32 TRA De gibbes 13003 MARSEILLE | I115: lyessm210711@gmail.com | J115: 0761703962 | L115: A faire | M115: ='WEDOF - EXAMEN FINAL'!D115 -> A faire | N115: A faire | O115: A faire | P115: A faire | Q115: A faire | R115: A faire | S115: A faire | T115: A faire | U115: =TEXTJOIN(", ",TRUE(),IF($L115="A faire","Analyse du besoin",""),IF($M115="A faire","CV",""),IF($N115="A faire","Questionnaire/Test",""),IF($O115="A faire","Contrat",""),IF($P115="A faire","Convocation",""),IF($Q115="A faire","Eval intermediaire",""),IF($R115="A faire","Eval finale",""),IF($S115="A faire","Questionnaire satisfaction",""),IF($T115="A faire","Document de fin","")) -> Analyse du besoin, CV, Questionnaire/Test, Contrat, Convocation, Eval intermediaire, Eval finale, Questionnaire satisfaction, Document de fin | V115: =COUNTIF(L115:T115,"Fait")/9 -> 0 | W115: =IF($F115="","",IF(AND(TODAY()>=(DATEVALUE($F115)+1),$U115<>""),"A RELANCER : "&$U115,"")) -> A RELANCER : Analyse du besoin, CV, Questionnaire/Test, Contrat, Convocation, Eval intermediaire, Eval finale, Questionnaire satisfaction, Document de fin | X115: =IF(SUMPRODUCT(($B$2:$B$153=$B115)*($D$2:$D$153=$D115)*($E$2:$E$153=$E115)*($A$2:$A$153<>$A115))>0,"DOUBLON A VERIFIER","") | Y115: Oui
A116: Proskills Institut | B116: BASCUNANA Jean-Christophe | D116: Communiquer sur les réseaux sociaux pour promouvoir sa TPE | E116: 2026-06-29 | F116: 2026-07-04 | G116: Accepté | H116: 14 AV Fuveau 13013 MARSEILLE | I116: jcbascunana@gmail.com | J116: 0623704619 | L116: A faire | M116: ='WEDOF - EXAMEN FINAL'!D116 -> A faire | N116: A faire | O116: A faire | P116: A faire | Q116: A faire | R116: A faire | S116: A faire | T116: A faire | U116: =TEXTJOIN(", ",TRUE(),IF($L116="A faire","Analyse du besoin",""),IF($M116="A faire","CV",""),IF($N116="A faire","Questionnaire/Test",""),IF($O116="A faire","Contrat",""),IF($P116="A faire","Convocation",""),IF($Q116="A faire","Eval intermediaire",""),IF($R116="A faire","Eval finale",""),IF($S116="A faire","Questionnaire satisfaction",""),IF($T116="A faire","Document de fin","")) -> Analyse du besoin, CV, Questionnaire/Test, Contrat, Convocation, Eval intermediaire, Eval finale, Questionnaire satisfaction, Document de fin | V116: =COUNTIF(L116:T116,"Fait")/9 -> 0 | W116: =IF($F116="","",IF(AND(TODAY()>=(DATEVALUE($F116)+1),$U116<>""),"A RELANCER : "&$U116,"")) -> A RELANCER : Analyse du besoin, CV, Questionnaire/Test, Contrat, Convocation, Eval intermediaire, Eval finale, Questionnaire satisfaction, Document de fin | X116: =IF(SUMPRODUCT(($B$2:$B$153=$B116)*($D$2:$D$153=$D116)*($E$2:$E$153=$E116)*($A$2:$A$153<>$A116))>0,"DOUBLON A VERIFIER","") | Y116: Oui
A117: Proskills Institut | B117: BASCUNANA Jean-Christophe | D117: Améliorer l'efficacité de sa TPE à l'aide de l'IA | E117: 2026-07-06 | F117: 2026-07-11 | G117: Accepté | H117: 14 AV Fuveau 13013 MARSEILLE | I117: jcbascunana@gmail.com | L117: A faire | M117: ='WEDOF - EXAMEN FINAL'!D117 -> A faire | N117: A faire | O117: A faire | P117: A faire | Q117: A faire | R117: A faire | S117: A faire | T117: A faire | U117: =TEXTJOIN(", ",TRUE(),IF($L117="A faire","Analyse du besoin",""),IF($M117="A faire","CV",""),IF($N117="A faire","Questionnaire/Test",""),IF($O117="A faire","Contrat",""),IF($P117="A faire","Convocation",""),IF($Q117="A faire","Eval intermediaire",""),IF($R117="A faire","Eval finale",""),IF($S117="A faire","Questionnaire satisfaction",""),IF($T117="A faire","Document de fin","")) -> Analyse du besoin, CV, Questionnaire/Test, Contrat, Convocation, Eval intermediaire, Eval finale, Questionnaire satisfaction, Document de fin | V117: =COUNTIF(L117:T117,"Fait")/9 -> 0 | W117: =IF($F117="","",IF(AND(TODAY()>=(DATEVALUE($F117)+1),$U117<>""),"A RELANCER : "&$U117,"")) -> A RELANCER : Analyse du besoin, CV, Questionnaire/Test, Contrat, Convocation, Eval intermediaire, Eval finale, Questionnaire satisfaction, Document de fin | X117: =IF(SUMPRODUCT(($B$2:$B$153=$B117)*($D$2:$D$153=$D117)*($E$2:$E$153=$E117)*($A$2:$A$153<>$A117))>0,"DOUBLON A VERIFIER","") | Y117: Oui
A118: Proskills Institut | B118: BASCUNANA Jean-Christophe | D118: Réaliser les opérations comptables courantes d'une TPE | E118: 2026-07-13 | F118: 2026-07-18 | G118: Accepté | H118: 14 AV Fuveau 13013 MARSEILLE | I118: jcbascunana@gmail.com | L118: A faire | M118: ='WEDOF - EXAMEN FINAL'!D118 -> A faire | N118: A faire | O118: A faire | P118: A faire | Q118: A faire | R118: A faire | S118: A faire | T118: A faire | U118: =TEXTJOIN(", ",TRUE(),IF($L118="A faire","Analyse du besoin",""),IF($M118="A faire","CV",""),IF($N118="A faire","Questionnaire/Test",""),IF($O118="A faire","Contrat",""),IF($P118="A faire","Convocation",""),IF($Q118="A faire","Eval intermediaire",""),IF($R118="A faire","Eval finale",""),IF($S118="A faire","Questionnaire satisfaction",""),IF($T118="A faire","Document de fin","")) -> Analyse du besoin, CV, Questionnaire/Test, Contrat, Convocation, Eval intermediaire, Eval finale, Questionnaire satisfaction, Document de fin | V118: =COUNTIF(L118:T118,"Fait")/9 -> 0 | W118: =IF($F118="","",IF(AND(TODAY()>=(DATEVALUE($F118)+1),$U118<>""),"A RELANCER : "&$U118,"")) -> A RELANCER : Analyse du besoin, CV, Questionnaire/Test, Contrat, Convocation, Eval intermediaire, Eval finale, Questionnaire satisfaction, Document de fin | X118: =IF(SUMPRODUCT(($B$2:$B$153=$B118)*($D$2:$D$153=$D118)*($E$2:$E$153=$E118)*($A$2:$A$153<>$A118))>0,"DOUBLON A VERIFIER","") | Y118: Oui
A119: Proskills Institut | B119: BUIDIN Michael | C119: frere karim | D119: Communiquer sur les réseaux sociaux pour promouvoir sa TPE | E119: 2026-06-29 | F119: 2026-07-04 | G119: Accepté | H119: 17 RUE Marquis de condorcet 13700 MARIGNANE | I119: michael.om.dd@live.fr | J119: 0622744148 | L119: A faire | M119: ='WEDOF - EXAMEN FINAL'!D119 -> A faire | N119: A faire | O119: A faire | P119: A faire | Q119: A faire | R119: A faire | S119: A faire | T119: A faire | U119: =TEXTJOIN(", ",TRUE(),IF($L119="A faire","Analyse du besoin",""),IF($M119="A faire","CV",""),IF($N119="A faire","Questionnaire/Test",""),IF($O119="A faire","Contrat",""),IF($P119="A faire","Convocation",""),IF($Q119="A faire","Eval intermediaire",""),IF($R119="A faire","Eval finale",""),IF($S119="A faire","Questionnaire satisfaction",""),IF($T119="A faire","Document de fin","")) -> Analyse du besoin, CV, Questionnaire/Test, Contrat, Convocation, Eval intermediaire, Eval finale, Questionnaire satisfaction, Document de fin | V119: =COUNTIF(L119:T119,"Fait")/9 -> 0 | W119: =IF($F119="","",IF(AND(TODAY()>=(DATEVALUE($F119)+1),$U119<>""),"A RELANCER : "&$U119,"")) -> A RELANCER : Analyse du besoin, CV, Questionnaire/Test, Contrat, Convocation, Eval intermediaire, Eval finale, Questionnaire satisfaction, Document de fin | X119: =IF(SUMPRODUCT(($B$2:$B$153=$B119)*($D$2:$D$153=$D119)*($E$2:$E$153=$E119)*($A$2:$A$153<>$A119))>0,"DOUBLON A VERIFIER","") | Y119: Oui
A120: Proskills Institut | B120: BUIDIN Michael | C120: frere karim | D120: Améliorer l'efficacité de sa TPE à l'aide de l'IA | E120: 2026-07-06 | F120: 2026-07-11 | G120: Accepté | L120: A faire | M120: ='WEDOF - EXAMEN FINAL'!D120 -> A faire | N120: A faire | O120: A faire | P120: A faire | Q120: A faire | R120: A faire | S120: A faire | T120: A faire | U120: =TEXTJOIN(", ",TRUE(),IF($L120="A faire","Analyse du besoin",""),IF($M120="A faire","CV",""),IF($N120="A faire","Questionnaire/Test",""),IF($O120="A faire","Contrat",""),IF($P120="A faire","Convocation",""),IF($Q120="A faire","Eval intermediaire",""),IF($R120="A faire","Eval finale",""),IF($S120="A faire","Questionnaire satisfaction",""),IF($T120="A faire","Document de fin","")) -> Analyse du besoin, CV, Questionnaire/Test, Contrat, Convocation, Eval intermediaire, Eval finale, Questionnaire satisfaction, Document de fin | V120: =COUNTIF(L120:T120,"Fait")/9 -> 0 | W120: =IF($F120="","",IF(AND(TODAY()>=(DATEVALUE($F120)+1),$U120<>""),"A RELANCER : "&$U120,"")) -> A RELANCER : Analyse du besoin, CV, Questionnaire/Test, Contrat, Convocation, Eval intermediaire, Eval finale, Questionnaire satisfaction, Document de fin | X120: =IF(SUMPRODUCT(($B$2:$B$153=$B120)*($D$2:$D$153=$D120)*($E$2:$E$153=$E120)*($A$2:$A$153<>$A120))>0,"DOUBLON A VERIFIER","") | Y120: Oui
A121: Proskills Institut | B121: BUIDIN Michael | C121: frere karim | D121: Réaliser les opérations comptables courantes d'une TPE | E121: 2026-07-13 | F121: 2026-07-18 | G121: Accepté | L121: A faire | M121: ='WEDOF - EXAMEN FINAL'!D121 -> A faire | N121: A faire | O121: A faire | P121: A faire | Q121: A faire | R121: A faire | S121: A faire | T121: A faire | U121: =TEXTJOIN(", ",TRUE(),IF($L121="A faire","Analyse du besoin",""),IF($M121="A faire","CV",""),IF($N121="A faire","Questionnaire/Test",""),IF($O121="A faire","Contrat",""),IF($P121="A faire","Convocation",""),IF($Q121="A faire","Eval intermediaire",""),IF($R121="A faire","Eval finale",""),IF($S121="A faire","Questionnaire satisfaction",""),IF($T121="A faire","Document de fin","")) -> Analyse du besoin, CV, Questionnaire/Test, Contrat, Convocation, Eval intermediaire, Eval finale, Questionnaire satisfaction, Document de fin | V121: =COUNTIF(L121:T121,"Fait")/9 -> 0 | W121: =IF($F121="","",IF(AND(TODAY()>=(DATEVALUE($F121)+1),$U121<>""),"A RELANCER : "&$U121,"")) -> A RELANCER : Analyse du besoin, CV, Questionnaire/Test, Contrat, Convocation, Eval intermediaire, Eval finale, Questionnaire satisfaction, Document de fin | X121: =IF(SUMPRODUCT(($B$2:$B$153=$B121)*($D$2:$D$153=$D121)*($E$2:$E$153=$E121)*($A$2:$A$153<>$A121))>0,"DOUBLON A VERIFIER","") | Y121: Oui
A122: Proskills Institut | B122: JIMENEZ Joris | C122: frere karim | D122: Communiquer sur les réseaux sociaux pour promouvoir sa TPE | E122: 2026-06-29 | F122: 2026-07-04 | G122: Accepté | H122: 370 PARC Parc des amandiers 13170 LES PENNES MIRABEAU | I122: Jorisjimenez@outlook.fr | J122: 0777754770 | L122: A faire | M122: ='WEDOF - EXAMEN FINAL'!D122 -> A faire | N122: A faire | O122: A faire | P122: A faire | Q122: A faire | R122: A faire | S122: A faire | T122: A faire | U122: =TEXTJOIN(", ",TRUE(),IF($L122="A faire","Analyse du besoin",""),IF($M122="A faire","CV",""),IF($N122="A faire","Questionnaire/Test",""),IF($O122="A faire","Contrat",""),IF($P122="A faire","Convocation",""),IF($Q122="A faire","Eval intermediaire",""),IF($R122="A faire","Eval finale",""),IF($S122="A faire","Questionnaire satisfaction",""),IF($T122="A faire","Document de fin","")) -> Analyse du besoin, CV, Questionnaire/Test, Contrat, Convocation, Eval intermediaire, Eval finale, Questionnaire satisfaction, Document de fin | V122: =COUNTIF(L122:T122,"Fait")/9 -> 0 | W122: =IF($F122="","",IF(AND(TODAY()>=(DATEVALUE($F122)+1),$U122<>""),"A RELANCER : "&$U122,"")) -> A RELANCER : Analyse du besoin, CV, Questionnaire/Test, Contrat, Convocation, Eval intermediaire, Eval finale, Questionnaire satisfaction, Document de fin | X122: =IF(SUMPRODUCT(($B$2:$B$153=$B122)*($D$2:$D$153=$D122)*($E$2:$E$153=$E122)*($A$2:$A$153<>$A122))>0,"DOUBLON A VERIFIER","") | Y122: Oui
A123: Proskills Institut | B123: JIMENEZ Joris | C123: frere karim | D123: Améliorer l'efficacité de sa TPE à l'aide de l'IA | E123: 2026-07-06 | F123: 2026-07-11 | G123: Accepté | H123: 370 PARC Parc des amandiers 13170 LES PENNES MIRABEAU | I123: Jorisjimenez@outlook.fr | L123: A faire | M123: ='WEDOF - EXAMEN FINAL'!D123 -> A faire | N123: A faire | O123: A faire | P123: A faire | Q123: A faire | R123: A faire | S123: A faire | T123: A faire | U123: =TEXTJOIN(", ",TRUE(),IF($L123="A faire","Analyse du besoin",""),IF($M123="A faire","CV",""),IF($N123="A faire","Questionnaire/Test",""),IF($O123="A faire","Contrat",""),IF($P123="A faire","Convocation",""),IF($Q123="A faire","Eval intermediaire",""),IF($R123="A faire","Eval finale",""),IF($S123="A faire","Questionnaire satisfaction",""),IF($T123="A faire","Document de fin","")) -> Analyse du besoin, CV, Questionnaire/Test, Contrat, Convocation, Eval intermediaire, Eval finale, Questionnaire satisfaction, Document de fin | V123: =COUNTIF(L123:T123,"Fait")/9 -> 0 | W123: =IF($F123="","",IF(AND(TODAY()>=(DATEVALUE($F123)+1),$U123<>""),"A RELANCER : "&$U123,"")) -> A RELANCER : Analyse du besoin, CV, Questionnaire/Test, Contrat, Convocation, Eval intermediaire, Eval finale, Questionnaire satisfaction, Document de fin | X123: =IF(SUMPRODUCT(($B$2:$B$153=$B123)*($D$2:$D$153=$D123)*($E$2:$E$153=$E123)*($A$2:$A$153<>$A123))>0,"DOUBLON A VERIFIER","") | Y123: Oui
A124: Proskills Institut | B124: MERAH Sarah | C124: Jean | D124: Développer son activité avec l'intelligence artificielle | E124: 2026-06-29 | F124: 2026-07-04 | G124: Accepté | H124: 75 RUE De la joliette 13002 MARSEILLE | I124: sarirou@icloud.com | J124: 0698791399 | L124: A faire | M124: ='WEDOF - EXAMEN FINAL'!D124 -> A faire | N124: A faire | O124: A faire | P124: A faire | Q124: A faire | R124: A faire | S124: A faire | T124: A faire | U124: =TEXTJOIN(", ",TRUE(),IF($L124="A faire","Analyse du besoin",""),IF($M124="A faire","CV",""),IF($N124="A faire","Questionnaire/Test",""),IF($O124="A faire","Contrat",""),IF($P124="A faire","Convocation",""),IF($Q124="A faire","Eval intermediaire",""),IF($R124="A faire","Eval finale",""),IF($S124="A faire","Questionnaire satisfaction",""),IF($T124="A faire","Document de fin","")) -> Analyse du besoin, CV, Questionnaire/Test, Contrat, Convocation, Eval intermediaire, Eval finale, Questionnaire satisfaction, Document de fin | V124: =COUNTIF(L124:T124,"Fait")/9 -> 0 | W124: =IF($F124="","",IF(AND(TODAY()>=(DATEVALUE($F124)+1),$U124<>""),"A RELANCER : "&$U124,"")) -> A RELANCER : Analyse du besoin, CV, Questionnaire/Test, Contrat, Convocation, Eval intermediaire, Eval finale, Questionnaire satisfaction, Document de fin | X124: =IF(SUMPRODUCT(($B$2:$B$153=$B124)*($D$2:$D$153=$D124)*($E$2:$E$153=$E124)*($A$2:$A$153<>$A124))>0,"DOUBLON A VERIFIER","") | Y124: Oui
A125: Proskills Institut | B125: TORRES Aurore | C125: GRAS | D125: Développer son activité avec l'intelligence artificielle | E125: 2026-06-29 | F125: 2026-07-04 | G125: Accepté | H125: AV Batistin raphael 13240 SEPTEMES LES VALLONS | I125: laurette13240@hotmail.fr | J125: 0660080861 | L125: A faire | M125: ='WEDOF - EXAMEN FINAL'!D125 -> A faire | N125: A faire | O125: A faire | P125: A faire | Q125: A faire | R125: A faire | S125: A faire | T125: A faire | U125: =TEXTJOIN(", ",TRUE(),IF($L125="A faire","Analyse du besoin",""),IF($M125="A faire","CV",""),IF($N125="A faire","Questionnaire/Test",""),IF($O125="A faire","Contrat",""),IF($P125="A faire","Convocation",""),IF($Q125="A faire","Eval intermediaire",""),IF($R125="A faire","Eval finale",""),IF($S125="A faire","Questionnaire satisfaction",""),IF($T125="A faire","Document de fin","")) -> Analyse du besoin, CV, Questionnaire/Test, Contrat, Convocation, Eval intermediaire, Eval finale, Questionnaire satisfaction, Document de fin | V125: =COUNTIF(L125:T125,"Fait")/9 -> 0 | W125: =IF($F125="","",IF(AND(TODAY()>=(DATEVALUE($F125)+1),$U125<>""),"A RELANCER : "&$U125,"")) -> A RELANCER : Analyse du besoin, CV, Questionnaire/Test, Contrat, Convocation, Eval intermediaire, Eval finale, Questionnaire satisfaction, Document de fin | X125: =IF(SUMPRODUCT(($B$2:$B$153=$B125)*($D$2:$D$153=$D125)*($E$2:$E$153=$E125)*($A$2:$A$153<>$A125))>0,"DOUBLON A VERIFIER","") | Y125: Oui
A126: Proskills Institut | B126: MAKHLOUF Ahmed | C126: Sabri | D126: Communiquer sur les réseaux sociaux pour promouvoir sa TPE | E126: 2026-06-29 | F126: 2026-07-04 | G126: Accepté | H126: RUE Des galaxies 13015 MARSEILLE | I126: makamed@laposte.net | J126: 0616135827 | L126: A faire | M126: ='WEDOF - EXAMEN FINAL'!D126 -> A faire | N126: A faire | O126: A faire | P126: A faire | Q126: A faire | R126: A faire | S126: A faire | T126: A faire | U126: =TEXTJOIN(", ",TRUE(),IF($L126="A faire","Analyse du besoin",""),IF($M126="A faire","CV",""),IF($N126="A faire","Questionnaire/Test",""),IF($O126="A faire","Contrat",""),IF($P126="A faire","Convocation",""),IF($Q126="A faire","Eval intermediaire",""),IF($R126="A faire","Eval finale",""),IF($S126="A faire","Questionnaire satisfaction",""),IF($T126="A faire","Document de fin","")) -> Analyse du besoin, CV, Questionnaire/Test, Contrat, Convocation, Eval intermediaire, Eval finale, Questionnaire satisfaction, Document de fin | V126: =COUNTIF(L126:T126,"Fait")/9 -> 0 | W126: =IF($F126="","",IF(AND(TODAY()>=(DATEVALUE($F126)+1),$U126<>""),"A RELANCER : "&$U126,"")) -> A RELANCER : Analyse du besoin, CV, Questionnaire/Test, Contrat, Convocation, Eval intermediaire, Eval finale, Questionnaire satisfaction, Document de fin | X126: =IF(SUMPRODUCT(($B$2:$B$153=$B126)*($D$2:$D$153=$D126)*($E$2:$E$153=$E126)*($A$2:$A$153<>$A126))>0,"DOUBLON A VERIFIER","") | Y126: Oui
A127: Proskills Institut | B127: MAKHLOUF Ahmed | C127: Sabri | D127: Améliorer l'efficacité de sa TPE à l'aide de l'IA | E127: 2026-07-06 | F127: 2026-07-11 | G127: Accepté | L127: A faire | M127: ='WEDOF - EXAMEN FINAL'!D127 -> A faire | N127: A faire | O127: A faire | P127: A faire | Q127: A faire | R127: A faire | S127: A faire | T127: A faire | U127: =TEXTJOIN(", ",TRUE(),IF($L127="A faire","Analyse du besoin",""),IF($M127="A faire","CV",""),IF($N127="A faire","Questionnaire/Test",""),IF($O127="A faire","Contrat",""),IF($P127="A faire","Convocation",""),IF($Q127="A faire","Eval intermediaire",""),IF($R127="A faire","Eval finale",""),IF($S127="A faire","Questionnaire satisfaction",""),IF($T127="A faire","Document de fin","")) -> Analyse du besoin, CV, Questionnaire/Test, Contrat, Convocation, Eval intermediaire, Eval finale, Questionnaire satisfaction, Document de fin | V127: =COUNTIF(L127:T127,"Fait")/9 -> 0 | W127: =IF($F127="","",IF(AND(TODAY()>=(DATEVALUE($F127)+1),$U127<>""),"A RELANCER : "&$U127,"")) -> A RELANCER : Analyse du besoin, CV, Questionnaire/Test, Contrat, Convocation, Eval intermediaire, Eval finale, Questionnaire satisfaction, Document de fin | X127: =IF(SUMPRODUCT(($B$2:$B$153=$B127)*($D$2:$D$153=$D127)*($E$2:$E$153=$E127)*($A$2:$A$153<>$A127))>0,"DOUBLON A VERIFIER","") | Y127: Oui
A128: Proskills Institut | B128: MAKHLOUF Ahmed | C128: Sabri | D128: Réaliser les opérations comptables courantes d'une TPE | E128: 2026-07-13 | F128: 2026-07-18 | G128: Accepté | L128: A faire | M128: ='WEDOF - EXAMEN FINAL'!D128 -> A faire | N128: A faire | O128: A faire | P128: A faire | Q128: A faire | R128: A faire | S128: A faire | T128: A faire | U128: =TEXTJOIN(", ",TRUE(),IF($L128="A faire","Analyse du besoin",""),IF($M128="A faire","CV",""),IF($N128="A faire","Questionnaire/Test",""),IF($O128="A faire","Contrat",""),IF($P128="A faire","Convocation",""),IF($Q128="A faire","Eval intermediaire",""),IF($R128="A faire","Eval finale",""),IF($S128="A faire","Questionnaire satisfaction",""),IF($T128="A faire","Document de fin","")) -> Analyse du besoin, CV, Questionnaire/Test, Contrat, Convocation, Eval intermediaire, Eval finale, Questionnaire satisfaction, Document de fin | V128: =COUNTIF(L128:T128,"Fait")/9 -> 0 | W128: =IF($F128="","",IF(AND(TODAY()>=(DATEVALUE($F128)+1),$U128<>""),"A RELANCER : "&$U128,"")) -> A RELANCER : Analyse du besoin, CV, Questionnaire/Test, Contrat, Convocation, Eval intermediaire, Eval finale, Questionnaire satisfaction, Document de fin | X128: =IF(SUMPRODUCT(($B$2:$B$153=$B128)*($D$2:$D$153=$D128)*($E$2:$E$153=$E128)*($A$2:$A$153<>$A128))>0,"DOUBLON A VERIFIER","") | Y128: Oui
A129: Proskills Institut | B129: BOUMEZIOUD Nassim | C129: Sabri | D129: Communiquer sur les réseaux sociaux pour promouvoir sa TPE | E129: 2026-06-29 | F129: 2026-07-04 | G129: Accepté | H129: 2 RUE Rue Jaume 13220 CHATEAUNEUF LES MARTIGUES | I129: nassimboumezioud@gmail.com | J129: 0625126277 | L129: A faire | M129: ='WEDOF - EXAMEN FINAL'!D129 -> A faire | N129: A faire | O129: A faire | P129: A faire | Q129: A faire | R129: A faire | S129: A faire | T129: A faire | U129: =TEXTJOIN(", ",TRUE(),IF($L129="A faire","Analyse du besoin",""),IF($M129="A faire","CV",""),IF($N129="A faire","Questionnaire/Test",""),IF($O129="A faire","Contrat",""),IF($P129="A faire","Convocation",""),IF($Q129="A faire","Eval intermediaire",""),IF($R129="A faire","Eval finale",""),IF($S129="A faire","Questionnaire satisfaction",""),IF($T129="A faire","Document de fin","")) -> Analyse du besoin, CV, Questionnaire/Test, Contrat, Convocation, Eval intermediaire, Eval finale, Questionnaire satisfaction, Document de fin | V129: =COUNTIF(L129:T129,"Fait")/9 -> 0 | W129: =IF($F129="","",IF(AND(TODAY()>=(DATEVALUE($F129)+1),$U129<>""),"A RELANCER : "&$U129,"")) -> A RELANCER : Analyse du besoin, CV, Questionnaire/Test, Contrat, Convocation, Eval intermediaire, Eval finale, Questionnaire satisfaction, Document de fin | X129: =IF(SUMPRODUCT(($B$2:$B$153=$B129)*($D$2:$D$153=$D129)*($E$2:$E$153=$E129)*($A$2:$A$153<>$A129))>0,"DOUBLON A VERIFIER","") | Y129: Oui
A130: Proskills Institut | B130: BOUMEZIOUD Nassim | C130: Sabri | D130: Réaliser les opérations comptables courantes d'une TPE | E130: 2026-07-13 | F130: 2026-07-18 | G130: Accepté | L130: A faire | M130: ='WEDOF - EXAMEN FINAL'!D130 -> A faire | N130: A faire | O130: A faire | P130: A faire | Q130: A faire | R130: A faire | S130: A faire | T130: A faire | U130: =TEXTJOIN(", ",TRUE(),IF($L130="A faire","Analyse du besoin",""),IF($M130="A faire","CV",""),IF($N130="A faire","Questionnaire/Test",""),IF($O130="A faire","Contrat",""),IF($P130="A faire","Convocation",""),IF($Q130="A faire","Eval intermediaire",""),IF($R130="A faire","Eval finale",""),IF($S130="A faire","Questionnaire satisfaction",""),IF($T130="A faire","Document de fin","")) -> Analyse du besoin, CV, Questionnaire/Test, Contrat, Convocation, Eval intermediaire, Eval finale, Questionnaire satisfaction, Document de fin | V130: =COUNTIF(L130:T130,"Fait")/9 -> 0 | W130: =IF($F130="","",IF(AND(TODAY()>=(DATEVALUE($F130)+1),$U130<>""),"A RELANCER : "&$U130,"")) -> A RELANCER : Analyse du besoin, CV, Questionnaire/Test, Contrat, Convocation, Eval intermediaire, Eval finale, Questionnaire satisfaction, Document de fin | X130: =IF(SUMPRODUCT(($B$2:$B$153=$B130)*($D$2:$D$153=$D130)*($E$2:$E$153=$E130)*($A$2:$A$153<>$A130))>0,"DOUBLON A VERIFIER","") | Y130: Oui
A131: Proskills Institut | B131: ESPINEIRA Bryan | C131: Djody | D131: Développer son activité avec l'intelligence artificielle | E131: 2026-06-29 | F131: 2026-07-04 | G131: Accepté | H131: 4 IMP Florent Evrard 62220 CARVIN | I131: espineira.b@gmail.com | J131: 0663741170 | L131: A faire | M131: ='WEDOF - EXAMEN FINAL'!D131 -> A faire | N131: A faire | O131: A faire | P131: A faire | Q131: A faire | R131: A faire | S131: A faire | T131: A faire | U131: =TEXTJOIN(", ",TRUE(),IF($L131="A faire","Analyse du besoin",""),IF($M131="A faire","CV",""),IF($N131="A faire","Questionnaire/Test",""),IF($O131="A faire","Contrat",""),IF($P131="A faire","Convocation",""),IF($Q131="A faire","Eval intermediaire",""),IF($R131="A faire","Eval finale",""),IF($S131="A faire","Questionnaire satisfaction",""),IF($T131="A faire","Document de fin","")) -> Analyse du besoin, CV, Questionnaire/Test, Contrat, Convocation, Eval intermediaire, Eval finale, Questionnaire satisfaction, Document de fin | V131: =COUNTIF(L131:T131,"Fait")/9 -> 0 | W131: =IF($F131="","",IF(AND(TODAY()>=(DATEVALUE($F131)+1),$U131<>""),"A RELANCER : "&$U131,"")) -> A RELANCER : Analyse du besoin, CV, Questionnaire/Test, Contrat, Convocation, Eval intermediaire, Eval finale, Questionnaire satisfaction, Document de fin | X131: =IF(SUMPRODUCT(($B$2:$B$153=$B131)*($D$2:$D$153=$D131)*($E$2:$E$153=$E131)*($A$2:$A$153<>$A131))>0,"DOUBLON A VERIFIER","") | Y131: Oui
A132: Proskills Institut | B132: EL ARBAOUI Salwa | C132: Djody | D132: Réaliser les opérations comptables courantes d'une TPE E-LEARNING | E132: 2026-06-24 | F132: 2026-07-24 | G132: Accepté | H132: 70 RUE Glenmor 35410 CHATEAUGIRON | I132: salwaelarbaoui@gmail.com | J132: 767868281 | L132: A faire | M132: ='WEDOF - EXAMEN FINAL'!D132 -> A faire | N132: A faire | O132: A faire | P132: A faire | Q132: A faire | R132: A faire | S132: A faire | T132: A faire | U132: =TEXTJOIN(", ",TRUE(),IF($L132="A faire","Analyse du besoin",""),IF($M132="A faire","CV",""),IF($N132="A faire","Questionnaire/Test",""),IF($O132="A faire","Contrat",""),IF($P132="A faire","Convocation",""),IF($Q132="A faire","Eval intermediaire",""),IF($R132="A faire","Eval finale",""),IF($S132="A faire","Questionnaire satisfaction",""),IF($T132="A faire","Document de fin","")) -> Analyse du besoin, CV, Questionnaire/Test, Contrat, Convocation, Eval intermediaire, Eval finale, Questionnaire satisfaction, Document de fin | V132: =COUNTIF(L132:T132,"Fait")/9 -> 0 | W132: =IF($F132="","",IF(AND(TODAY()>=(DATEVALUE($F132)+1),$U132<>""),"A RELANCER : "&$U132,"")) | X132: =IF(SUMPRODUCT(($B$2:$B$153=$B132)*($D$2:$D$153=$D132)*($E$2:$E$153=$E132)*($A$2:$A$153<>$A132))>0,"DOUBLON A VERIFIER","") | Y132: Oui
...

Sheet WEDOF - EXAMEN FINAL
A1: Organisme | B1: Nom | C1: Apporteur | D1: CV | E1: CIN | F1: 6 dossiers admin | G1: Convocation examen | H1: Experience | I1: Adresse | J1: Email | K1: Mobile | L1: Date de naissance | M1: Missions a faire
A2: =APPRENANTS!A2 -> Proforma Institut | B2: =APPRENANTS!B2 -> Mohamed Ait Baha | C2: =APPRENANTS!C2 -> Djody | D2: A faire | E2: A faire | F2: A faire | G2: Fait | I2: =APPRENANTS!H2 -> 141 BD Maréchal Juin, 62110 HENIN BEAUMONT | J2: =APPRENANTS!I2 -> mohamed.aitbaha@hotmail.fr | K2: =APPRENANTS!J2 -> 782270615 | L2: =APPRENANTS!K2 -> 1982-09-04 | M2: =TEXTJOIN(", ",TRUE(),IF($D2="A faire","CV",""),IF($E2="A faire","CIN",""),IF($F2="A faire","6 dossiers admin",""),IF($G2="A faire","Convocation examen","")) -> CV, CIN, 6 dossiers admin
A3: =APPRENANTS!A3 -> Proforma Institut | B3: =APPRENANTS!B3 -> Frederic Roche | C3: =APPRENANTS!C3 -> Nedjma | D3: Fait | E3: A faire | F3: Fait | G3: Fait | H3: depuis 2004 effage construction ( 7 rue du devoir effage construction sud est ) manoeuvre, 3 AN 2008 AIDE COFFREUR 210 ET DEPUII 2015 230 | I3: =APPRENANTS!H3 -> 10 AV Des mimosas, 13015 MARSEILLE | J3: =APPRENANTS!I3 -> fred_mars13@hotmail.fr | K3: =APPRENANTS!J3 -> 613637315 | L3: =APPRENANTS!K3 -> 18/02/1981 | M3: =TEXTJOIN(", ",TRUE(),IF($D3="A faire","CV",""),IF($E3="A faire","CIN",""),IF($F3="A faire","6 dossiers admin",""),IF($G3="A faire","Convocation examen","")) -> CIN
A4: =APPRENANTS!A4 -> Proforma Institut | B4: =APPRENANTS!B4 -> SIAF Kamla | C4: =APPRENANTS!C4 -> Nedjma | D4: A faire | E4: A faire | F4: A faire | G4: Fait | I4: =APPRENANTS!H4 -> 171 AV du Merlan, 13014 MARSEILLE | J4: =APPRENANTS!I4 -> mimisiaf@gmail.com | K4: =APPRENANTS!J4 -> 629924780 | L4: =APPRENANTS!K4 -> 13/08/1965 | M4: =TEXTJOIN(", ",TRUE(),IF($D4="A faire","CV",""),IF($E4="A faire","CIN",""),IF($F4="A faire","6 dossiers admin",""),IF($G4="A faire","Convocation examen","")) -> CV, CIN, 6 dossiers admin
A5: =APPRENANTS!A5 -> Proforma Institut | B5: =APPRENANTS!B5 -> HAFIDHOU Mansouri | C5: =APPRENANTS!C5 -> Nedjma | D5: Fait | E5: Fait | F5: Fait | G5: Fait | H5: 10 ans eiffage coffreur depuis 3ans chef d equipe 10 ans eiffage coffreur depuis 3ans chef d equipe | I5: =APPRENANTS!H5 -> 178 AV Des chutes lavie, 13013 MARSEILLE | J5: =APPRENANTS!I5 -> mansourihafidou@gmail.com | K5: =APPRENANTS!J5 -> 763179407 | L5: =APPRENANTS!K5 -> 1990-07-05 | M5: =TEXTJOIN(", ",TRUE(),IF($D5="A faire","CV",""),IF($E5="A faire","CIN",""),IF($F5="A faire","6 dossiers admin",""),IF($G5="A faire","Convocation examen",""))
A6: =APPRENANTS!A6 -> Proforma Institut | B6: =APPRENANTS!B6 -> DELGADO DA CRUZ Francisco | C6: =APPRENANTS!C6 -> Nedjma | D6: Fait | E6: Fait | F6: Fait | G6: Fait | H6: 20 ans effage manoeuvre PUIS aide coffreur qualif 210 | I6: =APPRENANTS!H6 -> 29 PTR Sainte victoire, 13006 MARSEILLE | J6: =APPRENANTS!I6 -> chicodelgado72@gmail.com | K6: =APPRENANTS!J6 -> 783823367 | L6: =APPRENANTS!K6 -> 1972-11-07 | M6: =TEXTJOIN(", ",TRUE(),IF($D6="A faire","CV",""),IF($E6="A faire","CIN",""),IF($F6="A faire","6 dossiers admin",""),IF($G6="A faire","Convocation examen",""))
A7: =APPRENANTS!A7 -> Proforma Institut | B7: =APPRENANTS!B7 -> DOUMENC Christophe | C7: =APPRENANTS!C7 -> Nedjma | D7: Fait | E7: Fait | F7: Fait | G7: Fait | H7: 16 ans effage grutier qualif 270 CHEF D EQUPE ( voir parcours ) | I7: =APPRENANTS!H7 -> 16 RUE Nicolas copernic, 13013 MARSEILLE | J7: =APPRENANTS!I7 -> christophedoumenc13@gmail.com | K7: =APPRENANTS!J7 -> 681540974 | L7: =APPRENANTS!K7 -> 30/12/1972 | M7: =TEXTJOIN(", ",TRUE(),IF($D7="A faire","CV",""),IF($E7="A faire","CIN",""),IF($F7="A faire","6 dossiers admin",""),IF($G7="A faire","Convocation examen",""))
A8: =APPRENANTS!A8 -> Proforma Institut | B8: =APPRENANTS!B8 -> AHAMADA BOURHANE Soilihi | C8: =APPRENANTS!C8 -> Nedjma | D8: Fait | E8: Fait | F8: Fait | G8: Fait | H8: 8 ANS EIFFAGE GRUTIER AVANT COFFREUR TRAVEAUX DU MIDI | I8: =APPRENANTS!H8 -> 257 AV Saint antoine, 13015 MARSEILLE | J8: =APPRENANTS!I8 -> ahamada.s@live.fr | K8: =APPRENANTS!J8 -> 652632912 | L8: =APPRENANTS!K8 -> 22/06/1991 | M8: =TEXTJOIN(", ",TRUE(),IF($D8="A faire","CV",""),IF($E8="A faire","CIN",""),IF($F8="A faire","6 dossiers admin",""),IF($G8="A faire","Convocation examen",""))
A9: =APPRENANTS!A9 -> Proforma Institut | B9: =APPRENANTS!B9 -> BENGUEDIH Kader | C9: =APPRENANTS!C9 -> Nedjma | D9: Fait | E9: A faire | F9: Fait | G9: Fait | H9: RTM AIX ET RTM MARSEILLE | I9: =APPRENANTS!H9 -> 130 CHE Château gombert, 13013 MARSEILLE | J9: =APPRENANTS!I9 -> Benguedihk@yahoo.fr | K9: =APPRENANTS!J9 -> 617440902 | L9: =APPRENANTS!K9 -> 19/08/1987 | M9: =TEXTJOIN(", ",TRUE(),IF($D9="A faire","CV",""),IF($E9="A faire","CIN",""),IF($F9="A faire","6 dossiers admin",""),IF($G9="A faire","Convocation examen","")) -> CIN
A10: =APPRENANTS!A10 -> Proforma Institut | B10: =APPRENANTS!B10 -> Julie Scotto D Aniello | C10: =APPRENANTS!C10 -> Sabri | D10: Fait | E10: Fait | F10: Fait | G10: Fait | H10: Renault 3 ans , estecienne à son compte et après estecienne à Humbo st vic | I10: =APPRENANTS!H10 -> 23 BD Boulevard Georges Clemenceau, 13700 MARIGNANE | J10: =APPRENANTS!I10 -> 13julie@free.fr | K10: =APPRENANTS!J10 -> 643092268 | L10: =APPRENANTS!K10 -> 1994-05-09 | M10: =TEXTJOIN(", ",TRUE(),IF($D10="A faire","CV",""),IF($E10="A faire","CIN",""),IF($F10="A faire","6 dossiers admin",""),IF($G10="A faire","Convocation examen",""))
A11: =APPRENANTS!A11 -> Proforma Institut | B11: =APPRENANTS!B11 -> Malik Benameur | C11: =APPRENANTS!C11 -> Sabri | D11: Fait | E11: Fait | F11: Fait | G11: Fait | H11: 11 ans alyzia | I11: =APPRENANTS!H11 -> 12 RUE Pour la paix, 13120 GARDANNE | J11: =APPRENANTS!I11 -> Malik13950@gmail.com | K11: =APPRENANTS!J11 -> 608544404 | L11: =APPRENANTS!K11 -> 24/06/1994 | M11: =TEXTJOIN(", ",TRUE(),IF($D11="A faire","CV",""),IF($E11="A faire","CIN",""),IF($F11="A faire","6 dossiers admin",""),IF($G11="A faire","Convocation examen",""))
A12: =APPRENANTS!A12 -> Proforma Institut | B12: =APPRENANTS!B12 -> LEROY Aurelie | C12: =APPRENANTS!C12 -> Sabri | D12: Fait | E12: Fait | F12: Fait | G12: Fait | H12: Chômage et avant chez pas je demande si tu ve | I12: =APPRENANTS!H12 -> 335 CHE Chemin des romarins, 13820 ENSUES LA REDONNE | J12: =APPRENANTS!I12 -> aurelie542@hotmail.fr | K12: =APPRENANTS!J12 -> 631344712 | L12: =APPRENANTS!K12 -> 1986-04-07 | M12: =TEXTJOIN(", ",TRUE(),IF($D12="A faire","CV",""),IF($E12="A faire","CIN",""),IF($F12="A faire","6 dossiers admin",""),IF($G12="A faire","Convocation examen",""))
A13: =APPRENANTS!A13 -> Proforma Institut | B13: =APPRENANTS!B13 -> SANIGOU Livan | C13: =APPRENANTS!C13 -> Sabri | D13: Fait | E13: Fait | F13: Fait | G13: Fait | H13: 20 ans carrefour à Aix et 1 ans alyzia | I13: =APPRENANTS!H13 -> 1 IMP Du stade, 13080 AIX EN PROVENCE | J13: =APPRENANTS!I13 -> livansanigou@yahoo.fr | K13: =APPRENANTS!J13 -> 775959572 | L13: =APPRENANTS!K13 -> 19/10/1983 | M13: =TEXTJOIN(", ",TRUE(),IF($D13="A faire","CV",""),IF($E13="A faire","CIN",""),IF($F13="A faire","6 dossiers admin",""),IF($G13="A faire","Convocation examen",""))
A14: =APPRENANTS!A14 -> Proforma Institut | B14: =APPRENANTS!B14 -> GUILLOT Romain | C14: =APPRENANTS!C14 -> Sabri | D14: Fait | E14: Fait | F14: Fait | G14: Fait | H14: 5 ans daher 5 ans Airbus | I14: =APPRENANTS!H14 -> 150 RUE Du groupe Manouchian, 13130 BERRE L ETANG | J14: =APPRENANTS!I14 -> romain.guillot82@gmail.com | K14: =APPRENANTS!J14 -> 623318286 | L14: =APPRENANTS!K14 -> 30/10/1991 | M14: =TEXTJOIN(", ",TRUE(),IF($D14="A faire","CV",""),IF($E14="A faire","CIN",""),IF($F14="A faire","6 dossiers admin",""),IF($G14="A faire","Convocation examen",""))
A15: =APPRENANTS!A15 -> Proforma Institut | B15: =APPRENANTS!B15 -> Eric Poggi | C15: =APPRENANTS!C15 -> Sabri | D15: Fait | E15: Fait | F15: Fait | G15: A faire | H15: 10 ans alyzia | I15: =APPRENANTS!H15 -> RUE Lieutenant de vaisseau Le Bris, 13127 VITROLLES | J15: =APPRENANTS!I15 -> ericpoggi13130@gmail.com | K15: =APPRENANTS!J15 -> 614893272 | L15: =APPRENANTS!K15 -> 27/08/1979 | M15: =TEXTJOIN(", ",TRUE(),IF($D15="A faire","CV",""),IF($E15="A faire","CIN",""),IF($F15="A faire","6 dossiers admin",""),IF($G15="A faire","Convocation examen","")) -> Convocation examen
A16: =APPRENANTS!A16 -> Proforma Institut | B16: =APPRENANTS!B16 -> SCOTTO D ANIELLO Lisa | C16: =APPRENANTS!C16 -> Sabri | D16: Fait | E16: Fait | F16: Fait | G16: A faire | H16: 5 ans Renault 3 ans crédit mutuel | I16: =APPRENANTS!H16 -> SQ Louison bobet, 13700 MARIGNANE | J16: =APPRENANTS!I16 -> scottodaniellolisa@gmail.com | K16: =APPRENANTS!J16 -> 646571045 | L16: =APPRENANTS!K16 -> 23/11/1996 | M16: =TEXTJOIN(", ",TRUE(),IF($D16="A faire","CV",""),IF($E16="A faire","CIN",""),IF($F16="A faire","6 dossiers admin",""),IF($G16="A faire","Convocation examen","")) -> Convocation examen
... A18: =APPRENANTS!A18 -> Proforma Institut | B18: =APPRENANTS!B18 -> Jauffrey Arezki | C18: =APPRENANTS!C18 -> Sabri | D18: A faire | E18: Fait | F18: Fait | G18: A faire | H18: 5 ans alyzia 2 ans avia 2 ans jetex | I18: =APPRENANTS!H18 -> 4 RUE des caucaires, 13127 VITROLLES | J18: =APPRENANTS!I18 -> jauffrey.arezki@outlook.com | K18: =APPRENANTS!J18 -> 771067108 | L18: =APPRENANTS!K18 -> 21/10/1997 | M18: =TEXTJOIN(", ",TRUE(),IF($D18="A faire","CV",""),IF($E18="A faire","CIN",""),IF($F18="A faire","6 dossiers admin",""),IF($G18="A faire","Convocation examen","")) -> CV, Convocation examen
A19: =APPRENANTS!A19 -> Proforma Institut | B19: =APPRENANTS!B19 -> NIEL Lucas | C19: =APPRENANTS!C19 -> Sabri | D19: Fait | E19: Fait | F19: Fait | G19: A faire | I19: =APPRENANTS!H19 -> 45 RUE lagremeuse, 13100 AIX EN PROVENCE | J19: =APPRENANTS!I19 -> niel.lucas@outlook.fr | K19: =APPRENANTS!J19 -> 642413718 | L19: =APPRENANTS!K19 -> 1999-08-10 | M19: =TEXTJOIN(", ",TRUE(),IF($D19="A faire","CV",""),IF($E19="A faire","CIN",""),IF($F19="A faire","6 dossiers admin",""),IF($G19="A faire","Convocation examen","")) -> Convocation examen
A20: =APPRENANTS!A20 -> Proforma Institut | B20: =APPRENANTS!B20 -> GIACALONE Thomas | C20: =APPRENANTS!C20 -> Sabri | D20: Fait | E20: Fait | F20: Fait | G20: A faire | H20: 9 ans alyzia | I20: =APPRENANTS!H20 -> 99 RUE Vielles route de la gavottes, 13170 LES PENNES MIRABEAU | J20: =APPRENANTS!I20 -> g-no@hotmail.fr | K20: =APPRENANTS!J20 -> 610724860 | L20: =APPRENANTS!K20 -> 24/06/1998 | M20: =TEXTJOIN(", ",TRUE(),IF($D20="A faire","CV",""),IF($E20="A faire","CIN",""),IF($F20="A faire","6 dossiers admin",""),IF($G20="A faire","Convocation examen","")) -> Convocation examen
A21: =APPRENANTS!A21 -> Proforma Institut | B21: =APPRENANTS!B21 -> Alain PEYRON-BENOIT | C21: =APPRENANTS!C21 -> Moh | D21: A faire | E21: A faire | F21: A faire | G21: A faire | I21: =APPRENANTS!H21 -> 61 BD La pinède, 13400 AUBAGNE | J21: =APPRENANTS!I21 -> a.benayoun13@gmail.com | K21: =APPRENANTS!J21 -> 613252707 | L21: =APPRENANTS!K21 -> 25/07/1963 | M21: =TEXTJOIN(", ",TRUE(),IF($D21="A faire","CV",""),IF($E21="A faire","CIN",""),IF($F21="A faire","6 dossiers admin",""),IF($G21="A faire","Convocation examen","")) -> CV, CIN, 6 dossiers admin, Convocation examen
A22: =APPRENANTS!A22 -> Proforma Institut | B22: =APPRENANTS!B22 -> TROUSSELLE Thomas | C22: =APPRENANTS!C22 -> Moh | D22: A faire | E22: A faire | F22: A faire | G22: A faire | I22: =APPRENANTS!H22 -> 5 AV De la 1ere armée française, 13700 MARIGNANE | J22: =APPRENANTS!I22 -> Thomas.trousselle@yahoo.com | K22: =APPRENANTS!J22 -> 669994981 | L22: =APPRENANTS!K22 -> 19/12/1997 | M22: =TEXTJOIN(", ",TRUE(),IF($D22="A faire","CV",""),IF($E22="A faire","CIN",""),IF($F22="A faire","6 dossiers admin",""),IF($G22="A faire","Convocation examen","")) -> CV, CIN, 6 dossiers admin, Convocation examen
A23: =APPRENANTS!A23 -> Proforma Institut | B23: =APPRENANTS!B23 -> PREVOST Florian | C23: =APPRENANTS!C23 -> Moh | D23: A faire | E23: A faire | F23: A faire | G23: A faire | I23: =APPRENANTS!H23 -> 24 AV merle au ponty, 13013 MARSEILLE | J23: =APPRENANTS!I23 -> florianprevost0@gmail.com | K23: =APPRENANTS!J23 -> 766054536 | L23: =APPRENANTS!K23 -> 1994-02-05 | M23: =TEXTJOIN(", ",TRUE(),IF($D23="A faire","CV",""),IF($E23="A faire","CIN",""),IF($F23="A faire","6 dossiers admin",""),IF($G23="A faire","Convocation examen","")) -> CV, CIN, 6 dossiers admin, Convocation examen
A24: =APPRENANTS!A24 -> Proforma Institut | B24: =APPRENANTS!B24 -> DJIBILIAN Yoann | C24: =APPRENANTS!C24 -> Nedjma | D24: A faire | E24: A faire | F24: A faire | G24: A faire | I24: =APPRENANTS!H24 -> 18 PL place d'Amont, 13390 AURIOL | J24: =APPRENANTS!I24 -> yoann.djibilian@laposte.net | K24: =APPRENANTS!J24 -> 645742336 | L24: =APPRENANTS!K24 -> 26/09/1999 | M24: =TEXTJOIN(", ",TRUE(),IF($D24="A faire","CV",""),IF($E24="A faire","CIN",""),IF($F24="A faire","6 dossiers admin",""),IF($G24="A faire","Convocation examen","")) -> CV, CIN, 6 dossiers admin, Convocation examen
A25: =APPRENANTS!A25 -> Proforma Institut | B25: =APPRENANTS!B25 -> ROUAISSI Moncef | C25: =APPRENANTS!C25 -> Nedjma | D25: A faire | E25: A faire | F25: A faire | G25: A faire | I25: =APPRENANTS!H25 -> CHE saint français, 13710 FUVEAU | J25: =APPRENANTS!I25 -> rouaissimoncef63@gmail.com | K25: =APPRENANTS!J25 -> 618814668 | L25: =APPRENANTS!K25 -> 1963-04-10 | M25: =TEXTJOIN(", ",TRUE(),IF($D25="A faire","CV",""),IF($E25="A faire","CIN",""),IF($F25="A faire","6 dossiers admin",""),IF($G25="A faire","Convocation examen","")) -> CV, CIN, 6 dossiers admin, Convocation examen
A26: =APPRENANTS!A26 -> Proforma Institut | B26: =APPRENANTS!B26 -> BOUTI Yazid | C26: =APPRENANTS!C26 -> Nedjma | D26: A faire | E26: A faire | F26: A faire | G26: A faire | I26: =APPRENANTS!H26 -> 9 BD Boulevard Victor Hugo, 13180 GIGNAC LA NERTHE | J26: =APPRENANTS!I26 -> yazidbouti48@gmail.com | K26: =APPRENANTS!J26 -> 756870967 | L26: =APPRENANTS!K26 -> 19/02/1976 | M26: =TEXTJOIN(", ",TRUE(),IF($D26="A faire","CV",""),IF($E26="A faire","CIN",""),IF($F26="A faire","6 dossiers admin",""),IF($G26="A faire","Convocation examen","")) -> CV, CIN, 6 dossiers admin, Convocation examen
A27: =APPRENANTS!A27 -> Proforma Institut | B27: =APPRENANTS!B27 -> KOUIDER Alexandre | C27: =APPRENANTS!C27 -> Sabri | D27: Fait | E27: Fait | F27: Fait | G27: A faire | H27: Étudiant Roumanie dentiste intérim alyzia et la poste | I27: =APPRENANTS!H27 -> 13 IMP De la papeterie, 13005 MARSEILLE | J27: =APPRENANTS!I27 -> alexandre.kouider.thiers@gmail.com | K27: =APPRENANTS!J27 -> 772350340 | L27: =APPRENANTS!K27 -> 15/05/2003 | M27: =TEXTJOIN(", ",TRUE(),IF($D27="A faire","CV",""),IF($E27="A faire","CIN",""),IF($F27="A faire","6 dossiers admin",""),IF($G27="A faire","Convocation examen","")) -> Convocation examen
A28: =APPRENANTS!A28 -> Proforma Institut | B28: =APPRENANTS!B28 -> SOLAITIN Mathieu | C28: =APPRENANTS!C28 -> Sabri | D28: A faire | E28: A faire | F28: A faire | G28: A faire | I28: =APPRENANTS!H28 -> AV De Font Segugne, 13127 VITROLLES | J28: =APPRENANTS!I28 -> msolaitin@yahoo.com | K28: =APPRENANTS!J28 -> 649754907 | L28: =APPRENANTS!K28 -> 20/07/1993 | M28: =TEXTJOIN(", ",TRUE(),IF($D28="A faire","CV",""),IF($E28="A faire","CIN",""),IF($F28="A faire","6 dossiers admin",""),IF($G28="A faire","Convocation examen","")) -> CV, CIN, 6 dossiers admin, Convocation examen
A29: =APPRENANTS!A29 -> Proforma Institut | B29: =APPRENANTS!B29 -> Alexandre Schmerber | C29: =APPRENANTS!C29 -> Sabri | D29: A faire | E29: A faire | F29: A faire | G29: A faire | I29: =APPRENANTS!H29 -> 24 MTE De le belle france, 13015 MARSEILLE | J29: =APPRENANTS!I29 -> alexandre.schmerber@hotmail.com | K29: =APPRENANTS!J29 -> 699574950 | L29: =APPRENANTS!K29 -> 24/05/1993 | M29: =TEXTJOIN(", ",TRUE(),IF($D29="A faire","CV",""),IF($E29="A faire","CIN",""),IF($F29="A faire","6 dossiers admin",""),IF($G29="A faire","Convocation examen","")) -> CV, CIN, 6 dossiers admin, Convocation examen
A30: =APPRENANTS!A30 -> Proforma Institut | B30: =APPRENANTS!B30 -> CHAFIL Amine | C30: =APPRENANTS!C30 | D30: A faire | E30: A faire | F30: A faire | G30: A faire | I30: =APPRENANTS!H30 -> 23 RUE Professeur marcel Arnaud, 13013 MARSEILLE | J30: =APPRENANTS!I30 -> amine_du_13010@hotmail.fr | K30: =APPRENANTS!J30 -> 624685745 | L30: =APPRENANTS!K30 -> 1990-11-07 | M30: =TEXTJOIN(", ",TRUE(),IF($D30="A faire","CV",""),IF($E30="A faire","CIN",""),IF($F30="A faire","6 dossiers admin",""),IF($G30="A faire","Convocation examen","")) -> CV, CIN, 6 dossiers admin, Convocation examen
A31: =APPRENANTS!A31 -> Proforma Institut | B31: =APPRENANTS!B31 -> MARIOTTI Regis | C31: =APPRENANTS!C31 -> Sabri | D31: A faire | E31: A faire | F31: A faire | G31: A faire | I31: =APPRENANTS!H31 -> 11 TRA de la dominique, 13011 MARSEILLE | J31: =APPRENANTS!I31 -> regismariotti@hotmail.fr | K31: =APPRENANTS!J31 -> 612877388 | L31: =APPRENANTS!K31 -> 27/08/1977 | M31: =TEXTJOIN(", ",TRUE(),IF($D31="A faire","CV",""),IF($E31="A faire","CIN",""),IF($F31="A faire","6 dossiers admin",""),IF($G31="A faire","Convocation examen","")) -> CV, CIN, 6 dossiers admin, Convocation examen
A32: =APPRENANTS!A32 -> Proforma Institut | B32: =APPRENANTS!B32 -> GAUTHEROT Pascal | C32: =APPRENANTS!C32 -> GRAS | D32: A faire | E32: A faire | F32: A faire | G32: A faire | I32: =APPRENANTS!H32 -> 192 CHE du tour de l'étang, 13800 ISTRES | J32: =APPRENANTS!I32 -> pascal-gautherot@wanadoo.fr | K32: =APPRENANTS!J32 -> 689407179 | L32: =APPRENANTS!K32 -> 22/04/1966 | M32: =TEXTJOIN(", ",TRUE(),IF($D32="A faire","CV",""),IF($E32="A faire","CIN",""),IF($F32="A faire","6 dossiers admin",""),IF($G32="A faire","Convocation examen","")) -> CV, CIN, 6 dossiers admin, Convocation examen
A33: =APPRENANTS!A33 -> Proforma Institut | B33: =APPRENANTS!B33 -> GAUTHEROT Pascal | C33: =APPRENANTS!C33 -> GRAS | D33: A faire | E33: A faire | F33: A faire | G33: A faire | I33: =APPRENANTS!H33 -> 192 CHE du tour de l'étang, 13800 ISTRES | J33: =APPRENANTS!I33 -> pascal-gautherot@wanadoo.fr | K33: =APPRENANTS!J33 -> 689407179 | L33: =APPRENANTS!K33 -> 22/04/1966 | M33: =TEXTJOIN(", ",TRUE(),IF($D33="A faire","CV",""),IF($E33="A faire","CIN",""),IF($F33="A faire","6 dossiers admin",""),IF($G33="A faire","Convocation examen","")) -> CV, CIN, 6 dossiers admin, Convocation examen
A34: =APPRENANTS!A34 -> Proforma Institut | B34: =APPRENANTS!B34 -> GAUTHEROT Pascal | C34: =APPRENANTS!C34 -> GRAS | D34: A faire | E34: A faire | F34: A faire | G34: A faire | I34: =APPRENANTS!H34 -> 192 CHE du tour de l'étang, 13800 ISTRES | J34: =APPRENANTS!I34 -> pascal-gautherot@wanadoo.fr | K34: =APPRENANTS!J34 -> 689407179 | L34: =APPRENANTS!K34 -> 22/04/1966 | M34: =TEXTJOIN(", ",TRUE(),IF($D34="A faire","CV",""),IF($E34="A faire","CIN",""),IF($F34="A faire","6 dossiers admin",""),IF($G34="A faire","Convocation examen","")) -> CV, CIN, 6 dossiers admin, Convocation examen
A35: =APPRENANTS!A35 -> Proforma Institut | B35: =APPRENANTS!B35 -> VIRAPHONG Thuy | C35: =APPRENANTS!C35 -> jules | D35: A faire | E35: A faire | F35: A faire | G35: A faire | I35: =APPRENANTS!H35 -> 81 CHE De figuerolles, 13180 GIGNAC LA NERTHE | J35: =APPRENANTS!I35 -> johana131@gmail.com | K35: =APPRENANTS!J35 -> 769874867 | L35: =APPRENANTS!K35 -> 15/10/1989 | M35: =TEXTJOIN(", ",TRUE(),IF($D35="A faire","CV",""),IF($E35="A faire","CIN",""),IF($F35="A faire","6 dossiers admin",""),IF($G35="A faire","Convocation examen","")) -> CV, CIN, 6 dossiers admin, Convocation examen
A36: =APPRENANTS!A36 -> Proforma Institut | B36: =APPRENANTS!B36 -> POGGI Eric | C36: =APPRENANTS!C36 -> Sabri | D36: A faire | E36: A faire | F36: A faire | G36: A faire | I36: =APPRENANTS!H36 | J36: =APPRENANTS!I36 | K36: =APPRENANTS!J36 | L36: =APPRENANTS!K36 | M36: =TEXTJOIN(", ",TRUE(),IF($D36="A faire","CV",""),IF($E36="A faire","CIN",""),IF($F36="A faire","6 dossiers admin",""),IF($G36="A faire","Convocation examen","")) -> CV, CIN, 6 dossiers admin, Convocation examen
A37: =APPRENANTS!A37 -> Proforma Institut | B37: =APPRENANTS!B37 -> POGGI Eric | C37: =APPRENANTS!C37 -> Sabri | D37: A faire | E37: A faire | F37: A faire | G37: A faire | I37: =APPRENANTS!H37 | J37: =APPRENANTS!I37 | K37: =APPRENANTS!J37 | L37: =APPRENANTS!K37 | M37: =TEXTJOIN(", ",TRUE(),IF($D37="A faire","CV",""),IF($E37="A faire","CIN",""),IF($F37="A faire","6 dossiers admin",""),IF($G37="A faire","Convocation examen","")) -> CV, CIN, 6 dossiers admin, Convocation examen
A38: =APPRENANTS!A38 -> Proforma Institut | B38: =APPRENANTS!B38 -> MENDY Jean | C38: =APPRENANTS!C38 -> jean | D38: A faire | E38: A faire | F38: A faire | G38: A faire | I38: =APPRENANTS!H38 -> 11 CDEP Chemin des broutieres, 13015 MARSEILLE | J38: =APPRENANTS!I38 -> mendyjean1207@gmail.com | K38: =APPRENANTS!J38 -> 784862602 | L38: =APPRENANTS!K38 -> 1987-12-07 | M38: =TEXTJOIN(", ",TRUE(),IF($D38="A faire","CV",""),IF($E38="A faire","CIN",""),IF($F38="A faire","6 dossiers admin",""),IF($G38="A faire","Convocation examen","")) -> CV, CIN, 6 dossiers admin, Convocation examen
A39: =APPRENANTS!A39 -> Proforma Institut | B39: =APPRENANTS!B39 -> BOUASRIA Najwa | C39: =APPRENANTS!C39 -> frere karim | D39: A faire | E39: A faire | F39: A faire | G39: A faire | I39: =APPRENANTS!H39 -> AV Marius Ruinat, 13700 MARIGNANE | J39: =APPRENANTS!I39 -> najwa.bouasria@gmail.com | K39: =APPRENANTS!J39 -> 761272644 | L39: =APPRENANTS!K39 -> 1997-06-09 | M39: =TEXTJOIN(", ",TRUE(),IF($D39="A faire","CV",""),IF($E39="A faire","CIN",""),IF($F39="A faire","6 dossiers admin",""),IF($G39="A faire","Convocation examen","")) -> CV, CIN, 6 dossiers admin, Convocation examen
... A81: =APPRENANTS!A81 -> Proforma Institut | B81: =APPRENANTS!B81 -> BENSAID Lahouari | C81: =APPRENANTS!C81 -> hak | D81: A faire | E81: A faire | F81: A faire | G81: A faire | I81: =APPRENANTS!H81 | J81: =APPRENANTS!I81 | K81: =APPRENANTS!J81 | L81: =APPRENANTS!K81 | M81: =TEXTJOIN(", ",TRUE(),IF($D81="A faire","CV",""),IF($E81="A faire","CIN",""),IF($F81="A faire","6 dossiers admin",""),IF($G81="A faire","Convocation examen","")) -> CV, CIN, 6 dossiers admin, Convocation examen
A82: =APPRENANTS!A82 -> Proskills Institut | B82: =APPRENANTS!B82 -> LAUZERO Jose | C82: =APPRENANTS!C82 -> Jules | D82: A faire | E82: Fait | F82: A faire | G82: A faire | H82: 6 ANS DANS L A REATURATION | I82: =APPRENANTS!H82 -> 75 VMIN VIEUX CHEMIN D'ISTRES 13300 SALON DE PROVENCE | J82: =APPRENANTS!I82 -> jose.lauzero@gmail.com | K82: =APPRENANTS!J82 -> 0687216599 | L82: =APPRENANTS!K82 | M82: =TEXTJOIN(", ",TRUE(),IF($D82="A faire","CV",""),IF($E82="A faire","CIN",""),IF($F82="A faire","6 dossiers admin",""),IF($G82="A faire","Convocation examen","")) -> CV, 6 dossiers admin, Convocation examen
A83: =APPRENANTS!A83 -> Proskills Institut | B83: =APPRENANTS!B83 -> LAUZERO Jose | C83: =APPRENANTS!C83 -> Jules | D83: A faire | E83: Fait | F83: A faire | G83: A faire | H83: 6 ANS DANS L A REATURATION | I83: =APPRENANTS!H83 -> 75 VMIN VIEUX CHEMIN D'ISTRES 13300 SALON DE PROVENCE | J83: =APPRENANTS!I83 -> jose.lauzero@gmail.com | K83: =APPRENANTS!J83 | L83: =APPRENANTS!K83 | M83: =TEXTJOIN(", ",TRUE(),IF($D83="A faire","CV",""),IF($E83="A faire","CIN",""),IF($F83="A faire","6 dossiers admin",""),IF($G83="A faire","Convocation examen","")) -> CV, 6 dossiers admin, Convocation examen
A84: =APPRENANTS!A84 -> Proskills Institut | B84: =APPRENANTS!B84 -> LAUZERO Jose | C84: =APPRENANTS!C84 -> Jules | D84: A faire | E84: Fait | F84: A faire | G84: A faire | H84: 6 ANS DANS L A REATURATION | I84: =APPRENANTS!H84 -> 75 VMIN VIEUX CHEMIN D'ISTRES 13300 SALON DE PROVENCE | J84: =APPRENANTS!I84 -> jose.lauzero@gmail.com | K84: =APPRENANTS!J84 | L84: =APPRENANTS!K84 | M84: =TEXTJOIN(", ",TRUE(),IF($D84="A faire","CV",""),IF($E84="A faire","CIN",""),IF($F84="A faire","6 dossiers admin",""),IF($G84="A faire","Convocation examen","")) -> CV, 6 dossiers admin, Convocation examen
A85: =APPRENANTS!A85 -> Proskills Institut | B85: =APPRENANTS!B85 -> MIEGE Cesar | C85: =APPRENANTS!C85 -> Jules | D85: A faire | E85: Fait | F85: A faire | G85: A faire | I85: =APPRENANTS!H85 -> 75 VMIN Vieux chemin d’istres 13300 SALON DE PROVENCE | J85: =APPRENANTS!I85 -> cesarmege17@gmail.com | K85: =APPRENANTS!J85 -> 0686428862 | L85: =APPRENANTS!K85 | M85: =TEXTJOIN(", ",TRUE(),IF($D85="A faire","CV",""),IF($E85="A faire","CIN",""),IF($F85="A faire","6 dossiers admin",""),IF($G85="A faire","Convocation examen","")) -> CV, 6 dossiers admin, Convocation examen
A86: =APPRENANTS!A86 -> Proskills Institut | B86: =APPRENANTS!B86 -> MIEGE Cesar | C86: =APPRENANTS!C86 -> Jules | D86: A faire | E86: Fait | F86: A faire | G86: A faire | I86: =APPRENANTS!H86 -> 75 VMIN Vieux chemin d’istres 13300 SALON DE PROVENCE | J86: =APPRENANTS!I86 -> cesarmege17@gmail.com | K86: =APPRENANTS!J86 | L86: =APPRENANTS!K86 | M86: =TEXTJOIN(", ",TRUE(),IF($D86="A faire","CV",""),IF($E86="A faire","CIN",""),IF($F86="A faire","6 dossiers admin",""),IF($G86="A faire","Convocation examen","")) -> CV, 6 dossiers admin, Convocation examen
A87: =APPRENANTS!A87 -> Proskills Institut | B87: =APPRENANTS!B87 -> BONILLO Olivier | C87: =APPRENANTS!C87 -> Jules | D87: A faire | E87: A faire | F87: A faire | G87: A faire | I87: =APPRENANTS!H87 -> 190 RTE Petite route des milles 13290 AIX EN PROVENCE | J87: =APPRENANTS!I87 -> gilly.oliver1810@gmail.com | K87: =APPRENANTS!J87 -> 0761243015 | L87: =APPRENANTS!K87 | M87: =TEXTJOIN(", ",TRUE(),IF($D87="A faire","CV",""),IF($E87="A faire","CIN",""),IF($F87="A faire","6 dossiers admin",""),IF($G87="A faire","Convocation examen","")) -> CV, CIN, 6 dossiers admin, Convocation examen
A88: =APPRENANTS!A88 -> Proskills Institut | B88: =APPRENANTS!B88 -> BONILLO Olivier | C88: =APPRENANTS!C88 -> Jules | D88: A faire | E88: A faire | F88: A faire | G88: A faire | I88: =APPRENANTS!H88 -> 190 RTE Petite route des milles 13290 AIX EN PROVENCE | J88: =APPRENANTS!I88 -> gilly.oliver1810@gmail.com | K88: =APPRENANTS!J88 | L88: =APPRENANTS!K88 | M88: =TEXTJOIN(", ",TRUE(),IF($D88="A faire","CV",""),IF($E88="A faire","CIN",""),IF($F88="A faire","6 dossiers admin",""),IF($G88="A faire","Convocation examen","")) -> CV, CIN, 6 dossiers admin, Convocation examen
A89: =APPRENANTS!A89 -> Proskills Institut | B89: =APPRENANTS!B89 -> GRAS Arnaud | C89: =APPRENANTS!C89 -> Djody | D89: A faire | E89: A faire | F89: A faire | G89: A faire | I89: =APPRENANTS!H89 -> 86 RUE francois mauriac 13010 MARSEILLE | J89: =APPRENANTS!I89 -> arnaudgras@hotmail.com | K89: =APPRENANTS!J89 -> 0649516676 | L89: =APPRENANTS!K89 | M89: =TEXTJOIN(", ",TRUE(),IF($D89="A faire","CV",""),IF($E89="A faire","CIN",""),IF($F89="A faire","6 dossiers admin",""),IF($G89="A faire","Convocation examen","")) -> CV, CIN, 6 dossiers admin, Convocation examen
A90: =APPRENANTS!A90 -> Proskills Institut | B90: =APPRENANTS!B90 -> GUILLOU Mael | C90: =APPRENANTS!C90 -> Sabri | D90: A faire | E90: A faire | F90: A faire | G90: A faire | I90: =APPRENANTS!H90 -> 46 RUE Résidence du bosquet 13127 VITROLLES | J90: =APPRENANTS!I90 -> maelguilloux@yahoo.fr | K90: =APPRENANTS!J90 -> 0609475106 | L90: =APPRENANTS!K90 | M90: =TEXTJOIN(", ",TRUE(),IF($D90="A faire","CV",""),IF($E90="A faire","CIN",""),IF($F90="A faire","6 dossiers admin",""),IF($G90="A faire","Convocation examen","")) -> CV, CIN, 6 dossiers admin, Convocation examen
A91: =APPRENANTS!A91 -> Proskills Institut | B91: =APPRENANTS!B91 -> GUILLOU Mael | C91: =APPRENANTS!C91 -> Sabri | D91: A faire | E91: A faire | F91: A faire | G91: A faire | I91: =APPRENANTS!H91 -> 46 RUE Résidence du bosquet 13127 VITROLLES | J91: =APPRENANTS!I91 | K91: =APPRENANTS!J91 | L91: =APPRENANTS!K91 | M91: =TEXTJOIN(", ",TRUE(),IF($D91="A faire","CV",""),IF($E91="A faire","CIN",""),IF($F91="A faire","6 dossiers admin",""),IF($G91="A faire","Convocation examen","")) -> CV, CIN, 6 dossiers admin, Convocation examen
A92: =APPRENANTS!A92 -> Proskills Institut | B92: =APPRENANTS!B92 -> AMEUR Kamel | C92: =APPRENANTS!C92 -> Brian | D92: A faire | E92: A faire | F92: A faire | G92: A faire | I92: =APPRENANTS!H92 -> 12 RES Rue Arthur lamendin 62430 SALLAUMINES | J92: =APPRENANTS!I92 -> kamel621@outlook.fr | K92: =APPRENANTS!J92 -> 0762665937 | L92: =APPRENANTS!K92 | M92: =TEXTJOIN(", ",TRUE(),IF($D92="A faire","CV",""),IF($E92="A faire","CIN",""),IF($F92="A faire","6 dossiers admin",""),IF($G92="A faire","Convocation examen","")) -> CV, CIN, 6 dossiers admin, Convocation examen
A93: =APPRENANTS!A93 -> Proskills Institut | B93: =APPRENANTS!B93 -> AMEUR Kamel | C93: =APPRENANTS!C93 -> Brian | D93: A faire | E93: A faire | F93: A faire | G93: A faire | I93: =APPRENANTS!H93 -> 12 RES Rue Arthur lamendin 62430 SALLAUMINES | J93: =APPRENANTS!I93 -> kamel621@outlook.fr | K93: =APPRENANTS!J93 | L93: =APPRENANTS!K93 | M93: =TEXTJOIN(", ",TRUE(),IF($D93="A faire","CV",""),IF($E93="A faire","CIN",""),IF($F93="A faire","6 dossiers admin",""),IF($G93="A faire","Convocation examen","")) -> CV, CIN, 6 dossiers admin, Convocation examen
A94: =APPRENANTS!A94 -> Proskills Institut | B94: =APPRENANTS!B94 -> LAUZERO Caroline | C94: =APPRENANTS!C94 -> Jules | D94: A faire | E94: Fait | F94: A faire | G94: A faire | I94: =APPRENANTS!H94 -> 75 VMIN VIEUX CHEMIN D'ISTRES 13300 SALON DE PROVENCE | J94: =APPRENANTS!I94 -> cclauzero@gmail.com | K94: =APPRENANTS!J94 -> 0647572721 | L94: =APPRENANTS!K94 | M94: =TEXTJOIN(", ",TRUE(),IF($D94="A faire","CV",""),IF($E94="A faire","CIN",""),IF($F94="A faire","6 dossiers admin",""),IF($G94="A faire","Convocation examen","")) -> CV, 6 dossiers admin, Convocation examen
A95: =APPRENANTS!A95 -> Proskills Institut | B95: =APPRENANTS!B95 -> LAUZERO Caroline | C95: =APPRENANTS!C95 -> Jules | D95: A faire | E95: Fait | F95: A faire | G95: A faire | I95: =APPRENANTS!H95 -> 75 VMIN VIEUX CHEMIN D'ISTRES 13300 SALON DE PROVENCE | J95: =APPRENANTS!I95 | K95: =APPRENANTS!J95 | L95: =APPRENANTS!K95 | M95: =TEXTJOIN(", ",TRUE(),IF($D95="A faire","CV",""),IF($E95="A faire","CIN",""),IF($F95="A faire","6 dossiers admin",""),IF($G95="A faire","Convocation examen","")) -> CV, 6 dossiers admin, Convocation examen
A96: =APPRENANTS!A96 -> Proskills Institut | B96: =APPRENANTS!B96 -> LAUZERO Caroline | C96: =APPRENANTS!C96 -> Jules | D96: A faire | E96: Fait | F96: A faire | G96: A faire | I96: =APPRENANTS!H96 -> 75 VMIN VIEUX CHEMIN D'ISTRES 13300 SALON DE PROVENCE | J96: =APPRENANTS!I96 | K96: =APPRENANTS!J96 | L96: =APPRENANTS!K96 | M96: =TEXTJOIN(", ",TRUE(),IF($D96="A faire","CV",""),IF($E96="A faire","CIN",""),IF($F96="A faire","6 dossiers admin",""),IF($G96="A faire","Convocation examen","")) -> CV, 6 dossiers admin, Convocation examen
... A153: =APPRENANTS!A153 -> Proskills Institut | B153: =APPRENANTS!B153 -> BOGGIO Andre | C153: =APPRENANTS!C153 -> Sabri | D153: A faire | E153: A faire | F153: A faire | G153: A faire | I153: =APPRENANTS!H153 | J153: =APPRENANTS!I153 | K153: =APPRENANTS!J153 | L153: =APPRENANTS!K153 | M153: =TEXTJOIN(", ",TRUE(),IF($D153="A faire","CV",""),IF($E153="A faire","CIN",""),IF($F153="A faire","6 dossiers admin",""),IF($G153="A faire","Convocation examen","")) -> CV, CIN, 6 dossiers admin, Convocation examen

Sheet PAIEMENTS & COMMISSIONS
A1: Organisme | B1: Nom | C1: Formation | D1: Apporteur | E1: Date fin formation | F1: Date paiement apporteur (J+35) | G1: Statut EDOF | H1: Reste a charge (E) | I1: Budget dossier (E) | J1: Montant commission | K1: Commission versee ? | L1: Statut commission | M1: Mois paiement | N1: Inscription confirmee | O1: CA confirme (E) | P1: Commission confirmee
A2: =APPRENANTS!A2 -> Proforma Institut | B2: =APPRENANTS!B2 -> Mohamed Ait Baha | C2: =APPRENANTS!D2 -> Réaliser les opérations comptables courantes d'une TPE | D2: =APPRENANTS!C2 -> Djody | E2: =APPRENANTS!F2 -> 2026-03-06 | F2: =IF(E2="","",DATEVALUE(E2)+35) -> 46122 | G2: =APPRENANTS!G2 -> Payé | H2: 100 | I2: 1500 | J2: =IF(APPRENANTS!Y2="Oui",IF(H2>0,825,750),0) -> 825 | K2: Non | L2: =IF(APPRENANTS!Y2="Non","Inscription non confirmee",IF(K2="Oui","Payee",IF(F2="","",IF(TODAY()>=F2,"En retard - a verser","A venir")))) -> En retard - a verser | M2: =IF(F2="","",CHOOSE(MONTH(F2),"janvier","fevrier","mars","avril","mai","juin","juillet","aout","septembre","octobre","novembre","decembre")&" "&YEAR(F2)) -> avril 2026 | N2: =APPRENANTS!Y2 -> Oui | O2: =IF($N2="Oui",I2,0) -> 1500 | P2: =IF($N2="Oui",J2,0) -> 825
A3: =APPRENANTS!A3 -> Proforma Institut | B3: =APPRENANTS!B3 -> Frederic Roche | C3: =APPRENANTS!D3 -> Réaliser les opérations comptables courantes d'une TPE | D3: =APPRENANTS!C3 -> Nedjma | E3: =APPRENANTS!F3 -> 2026-03-06 | F3: =IF(E3="","",DATEVALUE(E3)+35) -> 46122 | G3: =APPRENANTS!G3 -> Payé | H3: 100 | I3: 1500 | J3: =IF(APPRENANTS!Y3="Oui",IF(H3>0,825,750),0) -> 825 | K3: Non | L3: =IF(APPRENANTS!Y3="Non","Inscription non confirmee",IF(K3="Oui","Payee",IF(F3="","",IF(TODAY()>=F3,"En retard - a verser","A venir")))) -> En retard - a verser | M3: =IF(F3="","",CHOOSE(MONTH(F3),"janvier","fevrier","mars","avril","mai","juin","juillet","aout","septembre","octobre","novembre","decembre")&" "&YEAR(F3)) -> avril 2026 | N3: =APPRENANTS!Y3 -> Oui | O3: =IF($N3="Oui",I3,0) -> 1500 | P3: =IF($N3="Oui",J3,0) -> 825
A4: =APPRENANTS!A4 -> Proforma Institut | B4: =APPRENANTS!B4 -> SIAF Kamla | C4: =APPRENANTS!D4 -> Réaliser les opérations comptables courantes d'une TPE | D4: =APPRENANTS!C4 -> Nedjma | E4: =APPRENANTS!F4 -> 2026-03-27 | F4: =IF(E4="","",DATEVALUE(E4)+35) -> 46143 | G4: =APPRENANTS!G4 -> Payé | H4: 100 | I4: 1500 | J4: =IF(APPRENANTS!Y4="Oui",IF(H4>0,825,750),0) -> 825 | K4: Non | L4: =IF(APPRENANTS!Y4="Non","Inscription non confirmee",IF(K4="Oui","Payee",IF(F4="","",IF(TODAY()>=F4,"En retard - a verser","A venir")))) -> En retard - a verser | M4: =IF(F4="","",CHOOSE(MONTH(F4),"janvier","fevrier","mars","avril","mai","juin","juillet","aout","septembre","octobre","novembre","decembre")&" "&YEAR(F4)) -> mai 2026 | N4: =APPRENANTS!Y4 -> Oui | O4: =IF($N4="Oui",I4,0) -> 1500 | P4: =IF($N4="Oui",J4,0) -> 825
A5: =APPRENANTS!A5 -> Proforma Institut | B5: =APPRENANTS!B5 -> HAFIDHOU Mansouri | C5: =APPRENANTS!D5 -> Réaliser les opérations comptables courantes d'une TPE | D5: =APPRENANTS!C5 -> Nedjma | E5: =APPRENANTS!F5 -> 2026-03-27 | F5: =IF(E5="","",DATEVALUE(E5)+35) -> 46143 | G5: =APPRENANTS!G5 -> Payé | H5: 100 | I5: 1500 | J5: =IF(APPRENANTS!Y5="Oui",IF(H5>0,825,750),0) -> 825 | K5: Non | L5: =IF(APPRENANTS!Y5="Non","Inscription non confirmee",IF(K5="Oui","Payee",IF(F5="","",IF(TODAY()>=F5,"En retard - a verser","A venir")))) -> En retard - a verser | M5: =IF(F5="","",CHOOSE(MONTH(F5),"janvier","fevrier","mars","avril","mai","juin","juillet","aout","septembre","octobre","novembre","decembre")&" "&YEAR(F5)) -> mai 2026 | N5: =APPRENANTS!Y5 -> Oui | O5: =IF($N5="Oui",I5,0) -> 1500 | P5: =IF($N5="Oui",J5,0) -> 825
A6: =APPRENANTS!A6 -> Proforma Institut | B6: =APPRENANTS!B6 -> DELGADO DA CRUZ Francisco | C6: =APPRENANTS!D6 -> Réaliser les opérations comptables courantes d'une TPE | D6: =APPRENANTS!C6 -> Nedjma | E6: =APPRENANTS!F6 -> 2026-03-27 | F6: =IF(E6="","",DATEVALUE(E6)+35) -> 46143 | G6: =APPRENANTS!G6 -> Payé | H6: 100 | I6: 1500 | J6: =IF(APPRENANTS!Y6="Oui",IF(H6>0,825,750),0) -> 825 | K6: Non | L6: =IF(APPRENANTS!Y6="Non","Inscription non confirmee",IF(K6="Oui","Payee",IF(F6="","",IF(TODAY()>=F6,"En retard - a verser","A venir")))) -> En retard - a verser | M6: =IF(F6="","",CHOOSE(MONTH(F6),"janvier","fevrier","mars","avril","mai","juin","juillet","aout","septembre","octobre","novembre","decembre")&" "&YEAR(F6)) -> mai 2026 | N6: =APPRENANTS!Y6 -> Oui | O6: =IF($N6="Oui",I6,0) -> 1500 | P6: =IF($N6="Oui",J6,0) -> 825
A7: =APPRENANTS!A7 -> Proforma Institut | B7: =APPRENANTS!B7 -> DOUMENC Christophe | C7: =APPRENANTS!D7 -> Réaliser les opérations comptables courantes d'une TPE | D7: =APPRENANTS!C7 -> Nedjma | E7: =APPRENANTS!F7 -> 2026-03-27 | F7: =IF(E7="","",DATEVALUE(E7)+35) -> 46143 | G7: =APPRENANTS!G7 -> Payé | H7: 100 | I7: 1500 | J7: =IF(APPRENANTS!Y7="Oui",IF(H7>0,825,750),0) -> 825 | K7: Non | L7: =IF(APPRENANTS!Y7="Non","Inscription non confirmee",IF(K7="Oui","Payee",IF(F7="","",IF(TODAY()>=F7,"En retard - a verser","A venir")))) -> En retard - a verser | M7: =IF(F7="","",CHOOSE(MONTH(F7),"janvier","fevrier","mars","avril","mai","juin","juillet","aout","septembre","octobre","novembre","decembre")&" "&YEAR(F7)) -> mai 2026 | N7: =APPRENANTS!Y7 -> Oui | O7: =IF($N7="Oui",I7,0) -> 1500 | P7: =IF($N7="Oui",J7,0) -> 825
A8: =APPRENANTS!A8 -> Proforma Institut | B8: =APPRENANTS!B8 -> AHAMADA BOURHANE Soilihi | C8: =APPRENANTS!D8 -> Réaliser les opérations comptables courantes d'une TPE | D8: =APPRENANTS!C8 -> Nedjma | E8: =APPRENANTS!F8 -> 2026-04-17 | F8: =IF(E8="","",DATEVALUE(E8)+35) -> 46164 | G8: =APPRENANTS!G8 -> FACTURE | H8: 100 | I8: 1500 | J8: =IF(APPRENANTS!Y8="Oui",IF(H8>0,825,750),0) -> 825 | K8: Non | L8: =IF(APPRENANTS!Y8="Non","Inscription non confirmee",IF(K8="Oui","Payee",IF(F8="","",IF(TODAY()>=F8,"En retard - a verser","A venir")))) -> En retard - a verser | M8: =IF(F8="","",CHOOSE(MONTH(F8),"janvier","fevrier","mars","avril","mai","juin","juillet","aout","septembre","octobre","novembre","decembre")&" "&YEAR(F8)) -> mai 2026 | N8: =APPRENANTS!Y8 -> Oui | O8: =IF($N8="Oui",I8,0) -> 1500 | P8: =IF($N8="Oui",J8,0) -> 825
A9: =APPRENANTS!A9 -> Proforma Institut | B9: =APPRENANTS!B9 -> BENGUEDIH Kader | C9: =APPRENANTS!D9 -> Réaliser les opérations comptables courantes d'une TPE | D9: =APPRENANTS!C9 -> Nedjma | E9: =APPRENANTS!F9 -> 2026-04-17 | F9: =IF(E9="","",DATEVALUE(E9)+35) -> 46164 | G9: =APPRENANTS!G9 -> FACTURE | H9: 0 | I9: 1500 | J9: =IF(APPRENANTS!Y9="Oui",IF(H9>0,825,750),0) -> 750 | K9: Non | L9: =IF(APPRENANTS!Y9="Non","Inscription non confirmee",IF(K9="Oui","Payee",IF(F9="","",IF(TODAY()>=F9,"En retard - a verser","A venir")))) -> En retard - a verser | M9: =IF(F9="","",CHOOSE(MONTH(F9),"janvier","fevrier","mars","avril","mai","juin","juillet","aout","septembre","octobre","novembre","decembre")&" "&YEAR(F9)) -> mai 2026 | N9: =APPRENANTS!Y9 -> Oui | O9: =IF($N9="Oui",I9,0) -> 1500 | P9: =IF($N9="Oui",J9,0) -> 750
A10: =APPRENANTS!A10 -> Proforma Institut | B10: =APPRENANTS!B10 -> Julie Scotto D Aniello | C10: =APPRENANTS!D10 -> Réaliser les opérations comptables courantes d'une TPE | D10: =APPRENANTS!C10 -> Sabri | E10: =APPRENANTS!F10 -> 2026-03-04 | F10: =IF(E10="","",DATEVALUE(E10)+35) -> 46120 | G10: =APPRENANTS!G10 -> Payé | H10: 100 | I10: 1500 | J10: =IF(APPRENANTS!Y10="Oui",IF(H10>0,825,750),0) -> 825 | K10: Non | L10: =IF(APPRENANTS!Y10="Non","Inscription non confirmee",IF(K10="Oui","Payee",IF(F10="","",IF(TODAY()>=F10,"En retard - a verser","A venir")))) -> En retard - a verser | M10: =IF(F10="","",CHOOSE(MONTH(F10),"janvier","fevrier","mars","avril","mai","juin","juillet","aout","septembre","octobre","novembre","decembre")&" "&YEAR(F10)) -> avril 2026 | N10: =APPRENANTS!Y10 -> Oui | O10: =IF($N10="Oui",I10,0) -> 1500 | P10: =IF($N10="Oui",J10,0) -> 825
A11: =APPRENANTS!A11 -> Proforma Institut | B11: =APPRENANTS!B11 -> Malik Benameur | C11: =APPRENANTS!D11 -> Réaliser les opérations comptables courantes d'une TPE | D11: =APPRENANTS!C11 -> Sabri | E11: =APPRENANTS!F11 -> 2026-03-11 | F11: =IF(E11="","",DATEVALUE(E11)+35) -> 46127 | G11: =APPRENANTS!G11 -> Payé | H11: 100 | I11: 1500 | J11: =IF(APPRENANTS!Y11="Oui",IF(H11>0,825,750),0) -> 825 | K11: Non | L11: =IF(APPRENANTS!Y11="Non","Inscription non confirmee",IF(K11="Oui","Payee",IF(F11="","",IF(TODAY()>=F11,"En retard - a verser","A venir")))) -> En retard - a verser | M11: =IF(F11="","",CHOOSE(MONTH(F11),"janvier","fevrier","mars","avril","mai","juin","juillet","aout","septembre","octobre","novembre","decembre")&" "&YEAR(F11)) -> avril 2026 | N11: =APPRENANTS!Y11 -> Oui | O11: =IF($N11="Oui",I11,0) -> 1500 | P11: =IF($N11="Oui",J11,0) -> 825
A12: =APPRENANTS!A12 -> Proforma Institut | B12: =APPRENANTS!B12 -> LEROY Aurelie | C12: =APPRENANTS!D12 -> Réaliser les opérations comptables courantes d'une TPE | D12: =APPRENANTS!C12 -> Sabri | E12: =APPRENANTS!F12 -> 2026-03-27 | F12: =IF(E12="","",DATEVALUE(E12)+35) -> 46143 | G12: =APPRENANTS!G12 -> Payé | H12: 0 | I12: 1500 | J12: =IF(APPRENANTS!Y12="Oui",IF(H12>0,825,750),0) -> 750 | K12: Non | L12: =IF(APPRENANTS!Y12="Non","Inscription non confirmee",IF(K12="Oui","Payee",IF(F12="","",IF(TODAY()>=F12,"En retard - a verser","A venir")))) -> En retard - a verser | M12: =IF(F12="","",CHOOSE(MONTH(F12),"janvier","fevrier","mars","avril","mai","juin","juillet","aout","septembre","octobre","novembre","decembre")&" "&YEAR(F12)) -> mai 2026 | N12: =APPRENANTS!Y12 -> Oui | O12: =IF($N12="Oui",I12,0) -> 1500 | P12: =IF($N12="Oui",J12,0) -> 750
A13: =APPRENANTS!A13 -> Proforma Institut | B13: =APPRENANTS!B13 -> SANIGOU Livan | C13: =APPRENANTS!D13 -> Réaliser les opérations comptables courantes d'une TPE | D13: =APPRENANTS!C13 -> Sabri | E13: =APPRENANTS!F13 -> 2026-03-27 | F13: =IF(E13="","",DATEVALUE(E13)+35) -> 46143 | G13: =APPRENANTS!G13 -> Payé | H13: 0 | I13: 1500 | J13: =IF(APPRENANTS!Y13="Oui",IF(H13>0,825,750),0) -> 750 | K13: Non | L13: =IF(APPRENANTS!Y13="Non","Inscription non confirmee",IF(K13="Oui","Payee",IF(F13="","",IF(TODAY()>=F13,"En retard - a verser","A venir")))) -> En retard - a verser | M13: =IF(F13="","",CHOOSE(MONTH(F13),"janvier","fevrier","mars","avril","mai","juin","juillet","aout","septembre","octobre","novembre","decembre")&" "&YEAR(F13)) -> mai 2026 | N13: =APPRENANTS!Y13 -> Oui | O13: =IF($N13="Oui",I13,0) -> 1500 | P13: =IF($N13="Oui",J13,0) -> 750
... A153: =APPRENANTS!A153 -> Proskills Institut | B153: =APPRENANTS!B153 -> BOGGIO Andre | C153: =APPRENANTS!D153 -> Réaliser les opérations comptables courantes d'une TPE | D153: =APPRENANTS!C153 -> Sabri | E153: =APPRENANTS!F153 -> 2026-08-15 | F153: =IF(E153="","",DATEVALUE(E153)+35) -> 46284 | G153: =APPRENANTS!G153 -> en attente | H153: 0 | I153: 1500 | J153: =IF(APPRENANTS!Y153="Oui",IF(H153>0,825,750),0) -> 0 | K153: Non | L153: =IF(APPRENANTS!Y153="Non","Inscription non confirmee",IF(K153="Oui","Payee",IF(F153="","",IF(TODAY()>=F153,"En retard - a verser","A venir")))) -> Inscription non confirmee | M153: =IF(F153="","",CHOOSE(MONTH(F153),"janvier","fevrier","mars","avril","mai","juin","juillet","aout","septembre","octobre","novembre","decembre")&" "&YEAR(F153)) -> septembre 2026 | N153: =APPRENANTS!Y153 -> Non | O153: =IF($N153="Oui",I153,0) -> 0 | P153: =IF($N153="Oui",J153,0) -> 0

Sheet AUTOMATISATION
A1: NOTES POUR LE DEVELOPPEUR - LOGIQUE DE DECLENCHEMENT DE LA GENERATION DE DOCUMENTS
A3: GENERATION "CLASSIQUE" (documents d evaluation standard : analyse du besoin, questionnaire/test, contrat, convocation, eval intermediaire, eval finale, questionnaire satisfaction, document de fin)
A4: Condition PRET_GENERATION_CLASSIQUE = VRAI <=> Formation (col E) ET Date debut session (col F) ET Date fin session (col G) sont tous renseignes.
A5: Autrement dit : l apprenant est considere INSCRIT. Des que c est VRAI, le dossier peut generer ses documents standards.
A6: Le declenchement reel se fait via la case GENERER_MAINTENANT_CLASSIQUE (colonne U), cochee manuellement une fois PRET_GENERATION_CLASSIQUE = VRAI.
A8: Condition PRET_GENERATION_WEDOF = VRAI <=> CIN ok (col O) = "Fait" ET (CV recu (col N) = "Fait" OU Experience (col P) <> ""). | T8: T and U == True (Document generate)
A9: Le CV peut etre fourni par l apprenant lui-meme (CV recu = Fait) ; sinon, si l Experience est renseignee, l automatisation peut generer le CV elle-meme a partir de cette experience.
A10: Le declenchement reel se fait via la case GENERER_MAINTENANT_WEDOF (colonne W), cochee manuellement une fois PRET_GENERATION_WEDOF = VRAI.
A11: Le declenchement reel se fait via la case GENERER_MAINTENANT_WEDOF (colonne V), cochee manuellement une fois PRET_GENERATION_WEDOF = VRAI.
A12: Nom | B12: Organisme | C12: Apporteur | D12: Statut EDOF | E12: Formation | F12: Date debut session | G12: Date fin session | H12: Adresse | I12: Email | J12: Telephone | K12: Date de naissance | L12: Code certification (E) | M12: Date examen (E) | N12: CV recu | O12: CIN ok | P12: Experience (E) | Q12: 6 dossiers admin ok | R12: Lien signature (E) | S12: Budget dossier | T12: PRET_GENERATION_CLASSIQUE | U12: PRET_GENERATION_WEDOF | V12: GENERER_MAINTENANT_CLASSIQUE (E) | W12: GENERER_MAINTENANT_WEDOF (E) | X12: Inscription confirmee
A13: =APPRENANTS!B2 -> Mohamed Ait Baha | B13: =APPRENANTS!A2 -> Proforma Institut | C13: =APPRENANTS!C2 -> Djody | D13: =APPRENANTS!G2 -> Payé | E13: =APPRENANTS!D2 -> Réaliser les opérations comptables courantes d'une TPE | F13: =APPRENANTS!E2 -> 2026-02-18 | G13: =APPRENANTS!F2 -> 2026-03-06 | H13: =APPRENANTS!H2 -> 141 BD Maréchal Juin, 62110 HENIN BEAUMONT | I13: =APPRENANTS!I2 -> mohamed.aitbaha@hotmail.fr | J13: =APPRENANTS!J2 -> 782270615 | K13: =APPRENANTS!K2 -> 1982-09-04 | N13: ='WEDOF - EXAMEN FINAL'!D2 -> A faire | O13: ='WEDOF - EXAMEN FINAL'!E2 -> A faire | P13: ='WEDOF - EXAMEN FINAL'!H2 | Q13: ='WEDOF - EXAMEN FINAL'!F2 -> A faire | S13: ='PAIEMENTS & COMMISSIONS'!I2 -> 1500 | T13: =IF(AND($E13<>"",$F13<>"",$G13<>"",$X13="Oui"),TRUE(),FALSE()) -> TRUE | U13: =IF(AND($O13="Fait",OR($N13="Fait",$P13<>""),$X13="Oui"),TRUE(),FALSE()) -> FALSE | V13: =FALSE() -> FALSE | W13: =FALSE() -> FALSE | X13: =APPRENANTS!Y2 -> Oui
A14: =APPRENANTS!B3 -> Frederic Roche | B14: =APPRENANTS!A3 -> Proforma Institut | C14: =APPRENANTS!C3 -> Nedjma | D14: =APPRENANTS!G3 -> Payé | E14: =APPRENANTS!D3 -> Réaliser les opérations comptables courantes d'une TPE | F14: =APPRENANTS!E3 -> 2026-02-18 | G14: =APPRENANTS!F3 -> 2026-03-06 | H14: =APPRENANTS!H3 -> 10 AV Des mimosas, 13015 MARSEILLE | I14: =APPRENANTS!I3 -> fred_mars13@hotmail.fr | J14: =APPRENANTS!J3 -> 613637315 | K14: =APPRENANTS!K3 -> 18/02/1981 | N14: ='WEDOF - EXAMEN FINAL'!D3 -> Fait | O14: ='WEDOF - EXAMEN FINAL'!E3 -> A faire | P14: ='WEDOF - EXAMEN FINAL'!H3 -> depuis 2004 effage construction ( 7 rue du devoir effage construction sud est ) manoeuvre, 3 AN 2008 AIDE COFFREUR 210 ET DEPUII 2015 230 | Q14: ='WEDOF - EXAMEN FINAL'!F3 -> Fait | S14: ='PAIEMENTS & COMMISSIONS'!I3 -> 1500 | T14: =IF(AND($E14<>"",$F14<>"",$G14<>"",$X14="Oui"),TRUE(),FALSE()) -> TRUE | U14: =IF(AND($O14="Fait",OR($N14="Fait",$P14<>""),$X14="Oui"),TRUE(),FALSE()) -> FALSE | V14: =FALSE() -> FALSE | W14: =FALSE() -> FALSE | X14: =APPRENANTS!Y3 -> Oui
A15: =APPRENANTS!B4 -> SIAF Kamla | B15: =APPRENANTS!A4 -> Proforma Institut | C15: =APPRENANTS!C4 -> Nedjma | D15: =APPRENANTS!G4 -> Payé | E15: =APPRENANTS!D4 -> Réaliser les opérations comptables courantes d'une TPE | F15: =APPRENANTS!E4 -> 2026-03-09 | G15: =APPRENANTS!F4 -> 2026-03-27 | H15: =APPRENANTS!H4 -> 171 AV du Merlan, 13014 MARSEILLE | I15: =APPRENANTS!I4 -> mimisiaf@gmail.com | J15: =APPRENANTS!J4 -> 629924780 | K15: =APPRENANTS!K4 -> 13/08/1965 | N15: ='WEDOF - EXAMEN FINAL'!D4 -> A faire | O15: ='WEDOF - EXAMEN FINAL'!E4 -> A faire | P15: ='WEDOF - EXAMEN FINAL'!H4 | Q15: ='WEDOF - EXAMEN FINAL'!F4 -> A faire | S15: ='PAIEMENTS & COMMISSIONS'!I4 -> 1500 | T15: =IF(AND($E15<>"",$F15<>"",$G15<>"",$X15="Oui"),TRUE(),FALSE()) -> TRUE | U15: =IF(AND($O15="Fait",OR($N15="Fait",$P15<>""),$X15="Oui"),TRUE(),FALSE()) -> FALSE | V15: =FALSE() -> FALSE | W15: =FALSE() -> FALSE | X15: =APPRENANTS!Y4 -> Oui
A16: =APPRENANTS!B5 -> HAFIDHOU Mansouri | B16: =APPRENANTS!A5 -> Proforma Institut | C16: =APPRENANTS!C5 -> Nedjma | D16: =APPRENANTS!G5 -> Payé | E16: =APPRENANTS!D5 -> Réaliser les opérations comptables courantes d'une TPE | F16: =APPRENANTS!E5 -> 2026-03-09 | G16: =APPRENANTS!F5 -> 2026-03-27 | H16: =APPRENANTS!H5 -> 178 AV Des chutes lavie, 13013 MARSEILLE | I16: =APPRENANTS!I5 -> mansourihafidou@gmail.com | J16: =APPRENANTS!J5 -> 763179407 | K16: =APPRENANTS!K5 -> 1990-07-05 | N16: ='WEDOF - EXAMEN FINAL'!D5 -> Fait | O16: ='WEDOF - EXAMEN FINAL'!E5 -> Fait | P16: ='WEDOF - EXAMEN FINAL'!H5 -> 10 ans eiffage coffreur depuis 3ans chef d equipe 10 ans eiffage coffreur depuis 3ans chef d equipe | Q16: ='WEDOF - EXAMEN FINAL'!F5 -> Fait | S16: ='PAIEMENTS & COMMISSIONS'!I5 -> 1500 | T16: =IF(AND($E16<>"",$F16<>"",$G16<>"",$X16="Oui"),TRUE(),FALSE()) -> TRUE | U16: =IF(AND($O16="Fait",OR($N16="Fait",$P16<>""),$X16="Oui"),TRUE(),FALSE()) -> TRUE | V16: =FALSE() -> FALSE | W16: =FALSE() -> FALSE | X16: =APPRENANTS!Y5 -> Oui
A17: =APPRENANTS!B6 -> DELGADO DA CRUZ Francisco | B17: =APPRENANTS!A6 -> Proforma Institut | C17: =APPRENANTS!C6 -> Nedjma | D17: =APPRENANTS!G6 -> Payé | E17: =APPRENANTS!D6 -> Réaliser les opérations comptables courantes d'une TPE | F17: =APPRENANTS!E6 -> 2026-03-09 | G17: =APPRENANTS!F6 -> 2026-03-27 | H17: =APPRENANTS!H6 -> 29 PTR Sainte victoire, 13006 MARSEILLE | I17: =APPRENANTS!I6 -> chicodelgado72@gmail.com | J17: =APPRENANTS!J6 -> 783823367 | K17: =APPRENANTS!K6 -> 1972-11-07 | N17: ='WEDOF - EXAMEN FINAL'!D6 -> Fait | O17: ='WEDOF - EXAMEN FINAL'!E6 -> Fait | P17: ='WEDOF - EXAMEN FINAL'!H6 -> 20 ans effage manoeuvre PUIS aide coffreur qualif 210 | Q17: ='WEDOF - EXAMEN FINAL'!F6 -> Fait | S17: ='PAIEMENTS & COMMISSIONS'!I6 -> 1500 | T17: =IF(AND($E17<>"",$F17<>"",$G17<>"",$X17="Oui"),TRUE(),FALSE()) -> TRUE | U17: =IF(AND($O17="Fait",OR($N17="Fait",$P17<>""),$X17="Oui"),TRUE(),FALSE()) -> TRUE | V17: =FALSE() -> FALSE | W17: =FALSE() -> FALSE | X17: =APPRENANTS!Y6 -> Oui
A18: =APPRENANTS!B7 -> DOUMENC Christophe | B18: =APPRENANTS!A7 -> Proforma Institut | C18: =APPRENANTS!C7 -> Nedjma | D18: =APPRENANTS!G7 -> Payé | E18: =APPRENANTS!D7 -> Réaliser les opérations comptables courantes d'une TPE | F18: =APPRENANTS!E7 -> 2026-03-09 | G18: =APPRENANTS!F7 -> 2026-03-27 | H18: =APPRENANTS!H7 -> 16 RUE Nicolas copernic, 13013 MARSEILLE | I18: =APPRENANTS!I7 -> christophedoumenc13@gmail.com | J18: =APPRENANTS!J7 -> 681540974 | K18: =APPRENANTS!K7 -> 30/12/1972 | N18: ='WEDOF - EXAMEN FINAL'!D7 -> Fait | O18: ='WEDOF - EXAMEN FINAL'!E7 -> Fait | P18: ='WEDOF - EXAMEN FINAL'!H7 -> 16 ans effage grutier qualif 270 CHEF D EQUPE ( voir parcours ) | Q18: ='WEDOF - EXAMEN FINAL'!F7 -> Fait | S18: ='PAIEMENTS & COMMISSIONS'!I7 -> 1500 | T18: =IF(AND($E18<>"",$F18<>"",$G18<>"",$X18="Oui"),TRUE(),FALSE()) -> TRUE | U18: =IF(AND($O18="Fait",OR($N18="Fait",$P18<>""),$X18="Oui"),TRUE(),FALSE()) -> TRUE | V18: =FALSE() -> FALSE | W18: =FALSE() -> FALSE | X18: =APPRENANTS!Y7 -> Oui
A19: =APPRENANTS!B8 -> AHAMADA BOURHANE Soilihi | B19: =APPRENANTS!A8 -> Proforma Institut | C19: =APPRENANTS!C8 -> Nedjma | D19: =APPRENANTS!G8 -> FACTURE | E19: =APPRENANTS!D8 -> Réaliser les opérations comptables courantes d'une TPE | F19: =APPRENANTS!E8 -> 2026-03-30 | G19: =APPRENANTS!F8 -> 2026-04-17 | H19: =APPRENANTS!H8 -> 257 AV Saint antoine, 13015 MARSEILLE | I19: =APPRENANTS!I8 -> ahamada.s@live.fr | J19: =APPRENANTS!J8 -> 652632912 | K19: =APPRENANTS!K8 -> 22/06/1991 | N19: ='WEDOF - EXAMEN FINAL'!D8 -> Fait | O19: ='WEDOF - EXAMEN FINAL'!E8 -> Fait | P19: ='WEDOF - EXAMEN FINAL'!H8 -> 8 ANS EIFFAGE GRUTIER AVANT COFFREUR TRAVEAUX DU MIDI | Q19: ='WEDOF - EXAMEN FINAL'!F8 -> Fait | S19: ='PAIEMENTS & COMMISSIONS'!I8 -> 1500 | T19: =IF(AND($E19<>"",$F19<>"",$G19<>"",$X19="Oui"),TRUE(),FALSE()) -> TRUE | U19: =IF(AND($O19="Fait",OR($N19="Fait",$P19<>""),$X19="Oui"),TRUE(),FALSE()) -> TRUE | V19: =FALSE() -> FALSE | W19: =FALSE() -> FALSE | X19: =APPRENANTS!Y8 -> Oui
A20: =APPRENANTS!B9 -> BENGUEDIH Kader | B20: =APPRENANTS!A9 -> Proforma Institut | C20: =APPRENANTS!C9 -> Nedjma | D20: =APPRENANTS!G9 -> FACTURE | E20: =APPRENANTS!D9 -> Réaliser les opérations comptables courantes d'une TPE | F20: =APPRENANTS!E9 -> 2026-03-30 | G20: =APPRENANTS!F9 -> 2026-04-17 | H20: =APPRENANTS!H9 -> 130 CHE Château gombert, 13013 MARSEILLE | I20: =APPRENANTS!I9 -> Benguedihk@yahoo.fr | J20: =APPRENANTS!J9 -> 617440902 | K20: =APPRENANTS!K9 -> 19/08/1987 | N20: ='WEDOF - EXAMEN FINAL'!D9 -> Fait | O20: ='WEDOF - EXAMEN FINAL'!E9 -> A faire | P20: ='WEDOF - EXAMEN FINAL'!H9 -> RTM AIX ET RTM MARSEILLE | Q20: ='WEDOF - EXAMEN FINAL'!F9 -> Fait | S20: ='PAIEMENTS & COMMISSIONS'!I9 -> 1500 | T20: =IF(AND($E20<>"",$F20<>"",$G20<>"",$X20="Oui"),TRUE(),FALSE()) -> TRUE | U20: =IF(AND($O20="Fait",OR($N20="Fait",$P20<>""),$X20="Oui"),TRUE(),FALSE()) -> FALSE | V20: =FALSE() -> FALSE | W20: =FALSE() -> FALSE | X20: =APPRENANTS!Y9 -> Oui
A21: =APPRENANTS!B10 -> Julie Scotto D Aniello | B21: =APPRENANTS!A10 -> Proforma Institut | C21: =APPRENANTS!C10 -> Sabri | D21: =APPRENANTS!G10 -> Payé | E21: =APPRENANTS!D10 -> Réaliser les opérations comptables courantes d'une TPE | F21: =APPRENANTS!E10 -> 2026-02-18 | G21: =APPRENANTS!F10 -> 2026-03-04 | H21: =APPRENANTS!H10 -> 23 BD Boulevard Georges Clemenceau, 13700 MARIGNANE | I21: =APPRENANTS!I10 -> 13julie@free.fr | J21: =APPRENANTS!J10 -> 643092268 | K21: =APPRENANTS!K10 -> 1994-05-09 | N21: ='WEDOF - EXAMEN FINAL'!D10 -> Fait | O21: ='WEDOF - EXAMEN FINAL'!E10 -> Fait | P21: ='WEDOF - EXAMEN FINAL'!H10 -> Renault 3 ans , estecienne à son compte et après estecienne à Humbo st vic | Q21: ='WEDOF - EXAMEN FINAL'!F10 -> Fait | S21: ='PAIEMENTS & COMMISSIONS'!I10 -> 1500 | T21: =IF(AND($E21<>"",$F21<>"",$G21<>"",$X21="Oui"),TRUE(),FALSE()) -> TRUE | U21: =IF(AND($O21="Fait",OR($N21="Fait",$P21<>""),$X21="Oui"),TRUE(),FALSE()) -> TRUE | V21: =FALSE() -> FALSE | W21: =FALSE() -> FALSE | X21: =APPRENANTS!Y10 -> Oui
A22: =APPRENANTS!B11 -> Malik Benameur | B22: =APPRENANTS!A11 -> Proforma Institut | C22: =APPRENANTS!C11 -> Sabri | D22: =APPRENANTS!G11 -> Payé | E22: =APPRENANTS!D11 -> Réaliser les opérations comptables courantes d'une TPE | F22: =APPRENANTS!E11 -> 2026-02-20 | G22: =APPRENANTS!F11 -> 2026-03-11 | H22: =APPRENANTS!H11 -> 12 RUE Pour la paix, 13120 GARDANNE | I22: =APPRENANTS!I11 -> Malik13950@gmail.com | J22: =APPRENANTS!J11 -> 608544404 | K22: =APPRENANTS!K11 -> 24/06/1994 | N22: ='WEDOF - EXAMEN FINAL'!D11 -> Fait | O22: ='WEDOF - EXAMEN FINAL'!E11 -> Fait | P22: ='WEDOF - EXAMEN FINAL'!H11 -> 11 ans alyzia | Q22: ='WEDOF - EXAMEN FINAL'!F11 -> Fait | S22: ='PAIEMENTS & COMMISSIONS'!I11 -> 1500 | T22: =IF(AND($E22<>"",$F22<>"",$G22<>"",$X22="Oui"),TRUE(),FALSE()) -> TRUE | U22: =IF(AND($O22="Fait",OR($N22="Fait",$P22<>""),$X22="Oui"),TRUE(),FALSE()) -> TRUE | V22: =FALSE() -> FALSE | W22: =FALSE() -> FALSE | X22: =APPRENANTS!Y11 -> Oui
A23: =APPRENANTS!B12 -> LEROY Aurelie | B23: =APPRENANTS!A12 -> Proforma Institut | C23: =APPRENANTS!C12 -> Sabri | D23: =APPRENANTS!G12 -> Payé | E23: =APPRENANTS!D12 -> Réaliser les opérations comptables courantes d'une TPE | F23: =APPRENANTS!E12 -> 2026-03-09 | G23: =APPRENANTS!F12 -> 2026-03-27 | H23: =APPRENANTS!H12 -> 335 CHE Chemin des romarins, 13820 ENSUES LA REDONNE | I23: =APPRENANTS!I12 -> aurelie542@hotmail.fr | J23: =APPRENANTS!J12 -> 631344712 | K23: =APPRENANTS!K12 -> 1986-04-07 | N23: ='WEDOF - EXAMEN FINAL'!D12 -> Fait | O23: ='WEDOF - EXAMEN FINAL'!E12 -> Fait | P23: ='WEDOF - EXAMEN FINAL'!H12 -> Chômage et avant chez pas je demande si tu ve | Q23: ='WEDOF - EXAMEN FINAL'!F12 -> Fait | S23: ='PAIEMENTS & COMMISSIONS'!I12 -> 1500 | T23: =IF(AND($E23<>"",$F23<>"",$G23<>"",$X23="Oui"),TRUE(),FALSE()) -> TRUE | U23: =IF(AND($O23="Fait",OR($N23="Fait",$P23<>""),$X23="Oui"),TRUE(),FALSE()) -> TRUE | V23: =FALSE() -> FALSE | W23: =FALSE() -> FALSE | X23: =APPRENANTS!Y12 -> Oui
A24: =APPRENANTS!B13 -> SANIGOU Livan | B24: =APPRENANTS!A13 -> Proforma Institut | C24: =APPRENANTS!C13 -> Sabri | D24: =APPRENANTS!G13 -> Payé | E24: =APPRENANTS!D13 -> Réaliser les opérations comptables courantes d'une TPE | F24: =APPRENANTS!E13 -> 2026-03-09 | G24: =APPRENANTS!F13 -> 2026-03-27 | H24: =APPRENANTS!H13 -> 1 IMP Du stade, 13080 AIX EN PROVENCE | I24: =APPRENANTS!I13 -> livansanigou@yahoo.fr | J24: =APPRENANTS!J13 -> 775959572 | K24: =APPRENANTS!K13 -> 19/10/1983 | N24: ='WEDOF - EXAMEN FINAL'!D13 -> Fait | O24: ='WEDOF - EXAMEN FINAL'!E13 -> Fait | P24: ='WEDOF - EXAMEN FINAL'!H13 -> 20 ans carrefour à Aix et 1 ans alyzia | Q24: ='WEDOF - EXAMEN FINAL'!F13 -> Fait | S24: ='PAIEMENTS & COMMISSIONS'!I13 -> 1500 | T24: =IF(AND($E24<>"",$F24<>"",$G24<>"",$X24="Oui"),TRUE(),FALSE()) -> TRUE | U24: =IF(AND($O24="Fait",OR($N24="Fait",$P24<>""),$X24="Oui"),TRUE(),FALSE()) -> TRUE | V24: =FALSE() -> FALSE | W24: =FALSE() -> FALSE | X24: =APPRENANTS!Y13 -> Oui
... A164: =APPRENANTS!B153 -> BOGGIO Andre | B164: =APPRENANTS!A153 -> Proskills Institut | C164: =APPRENANTS!C153 -> Sabri | D164: =APPRENANTS!G153 -> en attente | E164: =APPRENANTS!D153 -> Réaliser les opérations comptables courantes d'une TPE | F164: =APPRENANTS!E153 -> 2026-08-10 | G164: =APPRENANTS!F153 -> 2026-08-15 | H164: =APPRENANTS!H153 | I164: =APPRENANTS!I153 | J164: =APPRENANTS!J153 | K164: =APPRENANTS!K153 | N164: ='WEDOF - EXAMEN FINAL'!D153 -> A faire | O164: ='WEDOF - EXAMEN FINAL'!E153 -> A faire | P164: ='WEDOF - EXAMEN FINAL'!H153 | Q164: ='WEDOF - EXAMEN FINAL'!F153 -> A faire | S164: ='PAIEMENTS & COMMISSIONS'!I153 -> 1500 | T164: =IF(AND($E164<>"",$F164<>"",$G164<>"",$X164="Oui"),TRUE(),FALSE()) -> FALSE | U164: =IF(AND($O164="Fait",OR($N164="Fait",$P164<>""),$X164="Oui"),TRUE(),FALSE()) -> FALSE | V164: =FALSE() -> FALSE | W164: =FALSE() -> FALSE | X164: =APPRENANTS!Y153 -> Non

Sheet LIENS INSCRIPTION
A1: Organisme | B1: Formation | C1: Lien inscription
A2: Proforma Institut | B2: Réaliser les opérations comptables courantes d'une TPE | C2: https://www.moncompteformation.gouv.fr/espace-prive/html/#/formation/recherche/97879287700034_ROCTPE4/97879287700034_ROCTPE4
A3: Proforma Institut | B3: Réaliser les opérations comptables courantes d'une TPE E-LEARNING | C3: https://www.moncompteformation.gouv.fr/espace-prive/html/#/formation/recherche/97879287700034_ROCTPE4/97879287700034_ROCTPEEL
A4: Proforma Institut | B4: Communiquer sur les réseaux sociaux pour promouvoir sa TPE | C4: https://www.moncompteformation.gouv.fr/espace-prive/html/#/formation/recherche/97879287700034_CRSTPE/97879287700034_CRSTPE
A5: Proforma Institut | B5: Améliorer l'efficacité de sa TPE à l'aide de l'IA | C5: https://www.moncompteformation.gouv.fr/espace-prive/html/#/formation/recherche/97879287700034_AETPEIA/97879287700034_AETPEIA
A6: Proforma Institut | B6: Améliorer l'efficacité de sa TPE à l'aide de l'IA E-learning | C6: https://www.moncompteformation.gouv.fr/espace-prive/html/#/formation/recherche/97879287700034_AETPEIA/97879287700034_IAtpeel
A7: Proforma Institut | B7: Développer son activité avec l'intelligence artificielle | C7: https://www.moncompteformation.gouv.fr/espace-prive/html/#/formation/recherche/97879287700034_DAIA/97879287700034_DAIA
A8: Proskills Institut | B8: Réaliser les opérations comptables courantes d'une TPE | C8: https://www.moncompteformation.gouv.fr/espace-prive/html/#/formation/recherche/95288071400011_ROCTPE/95288071400011_ROCTPE
A9: Proskills Institut | B9: Développer son activité avec l'intelligence artificielle | C9: https://www.moncompteformation.gouv.fr/espace-prive/html/#/formation/recherche/95288071400011_DAIA/95288071400011_IA1
A10: Proskills Institut | B10: Communiquer sur les réseaux sociaux pour promouvoir sa TPE | C10: https://www.moncompteformation.gouv.fr/espace-prive/html/#/formation/recherche/95288071400011_CRSTPE/95288071400011_CRSTPE
A11: Proskills Institut | B11: Améliorer l'efficacité de sa TPE à l'aide de l'IA | C11: https://www.moncompteformation.gouv.fr/espace-prive/html/#/formation/recherche/95288071400011_AETPEIA/95288071400011_AETPEIA
A12: Proskills Institut | B12: Améliorer l'efficacité de sa TPE à l'aide de l'IA E-learning | C12: https://www.moncompteformation.gouv.fr/espace-prive/html/#/formation/recherche/95288071400011_AETPEIA/95288071400011_IATPEEL
... A19: Proskills Institut | B19: TEST DE POSITIONNEMENT Réaliser les opérations comptables courantes d'une TPE PROSKILLS INSTITUT | C19: https://docs.google.com/forms/d/e/1FAIpQLSf89Y4VAx-2gy3Bta91sM3vmq_ThYV76cpDthwhwgQDmYH-8Q/viewform?usp=publish-editor

Sheet SYNTHESE PAIEMENTS
B2: SYNTHESE PAR APPORTEUR
B3: Apporteur | C3: Nb dossiers | D3: Total commission due | E3: Deja versee | F3: Reste a verser | G3: Nb en retard
B4: Brian | C4: =COUNTIF('PAIEMENTS & COMMISSIONS'!$D$2:$D$153,$B4) -> 5 | D4: =SUMIF('PAIEMENTS & COMMISSIONS'!$D$2:$D$153,$B4,'PAIEMENTS & COMMISSIONS'!$P$2:$P$153) -> 3750 | E4: =SUMIFS('PAIEMENTS & COMMISSIONS'!$P$2:$P$153,'PAIEMENTS & COMMISSIONS'!$D$2:$D$153,$B4,'PAIEMENTS & COMMISSIONS'!$K$2:$K$153,"Oui") -> 0 | F4: =D4-E4 -> 3750 | G4: =COUNTIFS('PAIEMENTS & COMMISSIONS'!$D$2:$D$153,$B4,'PAIEMENTS & COMMISSIONS'!$L$2:$L$153,"En retard - a verser") -> 5
B5: Djody | C5: =COUNTIF('PAIEMENTS & COMMISSIONS'!$D$2:$D$153,$B5) -> 14 | D5: =SUMIF('PAIEMENTS & COMMISSIONS'!$D$2:$D$153,$B5,'PAIEMENTS & COMMISSIONS'!$P$2:$P$153) -> 10575 | E5: =SUMIFS('PAIEMENTS & COMMISSIONS'!$P$2:$P$153,'PAIEMENTS & COMMISSIONS'!$D$2:$D$153,$B5,'PAIEMENTS & COMMISSIONS'!$K$2:$K$153,"Oui") -> 0 | F5: =D5-E5 -> 10575 | G5: =COUNTIFS('PAIEMENTS & COMMISSIONS'!$D$2:$D$153,$B5,'PAIEMENTS & COMMISSIONS'!$L$2:$L$153,"En retard - a verser") -> 4
B6: frere karim | C6: =COUNTIF('PAIEMENTS & COMMISSIONS'!$D$2:$D$153,$B6) -> 9 | D6: =SUMIF('PAIEMENTS & COMMISSIONS'!$D$2:$D$153,$B6,'PAIEMENTS & COMMISSIONS'!$P$2:$P$153) -> 6750 | E6: =SUMIFS('PAIEMENTS & COMMISSIONS'!$P$2:$P$153,'PAIEMENTS & COMMISSIONS'!$D$2:$D$153,$B6,'PAIEMENTS & COMMISSIONS'!$K$2:$K$153,"Oui") -> 0 | F6: =D6-E6 -> 6750 | G6: =COUNTIFS('PAIEMENTS & COMMISSIONS'!$D$2:$D$153,$B6,'PAIEMENTS & COMMISSIONS'!$L$2:$L$153,"En retard - a verser") -> 2
B7: GRAS | C7: =COUNTIF('PAIEMENTS & COMMISSIONS'!$D$2:$D$153,$B7) -> 15 | D7: =SUMIF('PAIEMENTS & COMMISSIONS'!$D$2:$D$153,$B7,'PAIEMENTS & COMMISSIONS'!$P$2:$P$153) -> 9750 | E7: =SUMIFS('PAIEMENTS & COMMISSIONS'!$P$2:$P$153,'PAIEMENTS & COMMISSIONS'!$D$2:$D$153,$B7,'PAIEMENTS & COMMISSIONS'!$K$2:$K$153,"Oui") -> 0 | F7: =D7-E7 -> 9750 | G7: =COUNTIFS('PAIEMENTS & COMMISSIONS'!$D$2:$D$153,$B7,'PAIEMENTS & COMMISSIONS'!$L$2:$L$153,"En retard - a verser") -> 1
B8: hak | C8: =COUNTIF('PAIEMENTS & COMMISSIONS'!$D$2:$D$153,$B8) -> 12 | D8: =SUMIF('PAIEMENTS & COMMISSIONS'!$D$2:$D$153,$B8,'PAIEMENTS & COMMISSIONS'!$P$2:$P$153) -> 6750 | E8: =SUMIFS('PAIEMENTS & COMMISSIONS'!$P$2:$P$153,'PAIEMENTS & COMMISSIONS'!$D$2:$D$153,$B8,'PAIEMENTS & COMMISSIONS'!$K$2:$K$153,"Oui") -> 0 | F8: =D8-E8 -> 6750 | G8: =COUNTIFS('PAIEMENTS & COMMISSIONS'!$D$2:$D$153,$B8,'PAIEMENTS & COMMISSIONS'!$L$2:$L$153,"En retard - a verser") -> 0
B9: jean | C9: =COUNTIF('PAIEMENTS & COMMISSIONS'!$D$2:$D$153,$B9) -> 7 | D9: =SUMIF('PAIEMENTS & COMMISSIONS'!$D$2:$D$153,$B9,'PAIEMENTS & COMMISSIONS'!$P$2:$P$153) -> 5250 | E9: =SUMIFS('PAIEMENTS & COMMISSIONS'!$P$2:$P$153,'PAIEMENTS & COMMISSIONS'!$D$2:$D$153,$B9,'PAIEMENTS & COMMISSIONS'!$K$2:$K$153,"Oui") -> 0 | F9: =D9-E9 -> 5250 | G9: =COUNTIFS('PAIEMENTS & COMMISSIONS'!$D$2:$D$153,$B9,'PAIEMENTS & COMMISSIONS'!$L$2:$L$153,"En retard - a verser") -> 0
